Workbook
Name BP: BP!$B$4:$J$77

Sheet BP
A3: ($ em milhões)
A4: Código da Conta | B4: Descrição da Conta | C4: 2024 | D4: 2023 | E4: 2022 | F4: 2021 | G4: 2020 | H4: 2019 | I4: 2018 | J4: 2017
A5: 1 | B5: Ativo Total | C5: 4466987 | D5: 4581833 | E5: 4199825 | F5: 3754136 | G5: 2824635 | H5: 1945403 | I5: 1789529 | J5: 1733859
A6: 1.01 | B6: Ativo Circulante | C6: 2967747 | D6: 3575173 | E6: 3430062 | F6: 3120040 | G6: 2211237 | H6: 1471763 | I6: 1418740 | J6: 1411332
A7: 1.01.01 | B7: Caixa e Equivalentes de Caixa | C7: 566929 | D7: 591375 | E7: 426576 | F7: 359007 | G7: 544162 | H7: 460714 | I7: 393348 | J7: 387826
A8: 1.01.02 | B8: Aplicações Financeiras | C8: 0 | D8: 0 | E8: 0 | F8: 0 | G8: 0 | H8: 0 | I8: 0 | J8: 0
A9: 1.01.03 | B9: Contas a Receber | C9: 860937 | D9: 1326360 | E9: 1132483 | F9: 762625 | G9: 698044 | H9: 258642 | I9: 235282 | J9: 276246
A10: 1.01.04 | B10: Estoques | C10: 1096246 | D10: 1256483 | E10: 1390723 | F10: 1690347 | G10: 645750 | H10: 494422 | I10: 534726 | J10: 506539
A11: 1.01.06 | B11: Tributos a Recuperar | C11: 301400 | D11: 304370 | E11: 361523 | F11: 176025 | G11: 221036 | H11: 124615 | I11: 129445 | J11: 142158
A12: 1.01.06.01 | B12: Tributos Correntes a Recuperar | C12: 301400 | D12: 304370 | E12: 361523 | F12: 176025 | G12: 221036 | H12: 124615 | I12: 129445 | J12: 0
A13: 1.01.06.01.01 | B13: Tributos a Recuperar | C13: 200109 | D13: 210811 | E13: 309169 | F13: 157222 | G13: 183356 | H13: 87826 | I13: 101769 | J13: 0
A14: 1.01.06.01.02 | B14: Imposto de Renda e Contribuição Social a Recuperar | C14: 101291 | D14: 0 | E14: 0 | F14: 0 | G14: 0 | H14: 0 | I14: 0 | J14: 0
A15: 1.01.08 | B15: Outros Ativos Cirulantes | C15: 142235 | D15: 96585 | E15: 118748 | F15: 132036 | G15: 102245 | H15: 133370 | I15: 125939 | J15: 98563
A16: 1.01.08.03 | B16: Outros | C16: 142235 | D16: 96585 | E16: 118748 | F16: 132036 | G16: 102245 | H16: 133370 | I16: 125939 | J16: 98563
A17: 1.01.08.03.01 | B17: Partes Relacionadas | C17: 21658 | D17: 12382 | E17: 13997 | F17: 14502 | G17: 20410 | H17: 20378 | I17: 21103 | J17: 12383
... A27: 1.02.01.10.05 | B27: Depósitos Judiciais | C27: 35760 | D27: 0 | E27: 0 | F27: 0 | G27: 0 | H27: 0 | I27: 0 | J27: 0
B28: ATIVO FIXO | C28: =SUM(C29,C32,C35) -> 733438 | D28: =SUM(D29,D32,D35) -> 504314 | E28: =SUM(E29,E32,E35) -> 385891 | F28: =SUM(F29,F32,F35) -> 294114 | G28: =SUM(G29,G32,G35) -> 275813 | H28: =SUM(H29,H32,H35) -> 267289 | I28: =SUM(I29,I32,I35) -> 178249 | J28: =SUM(J29,J32,J35) -> 172866
A29: 1.02.02 | B29: Investimentos | C29: 256770 | D29: 226969 | E29: 164127 | F29: 114226 | G29: 91692 | H29: 73433 | I29: 48087 | J29: 53604
A30: 1.02.02.01 | B30: Participações Societárias | C30: 256770 | D30: 226969 | E30: 164127 | F30: 114226 | G30: 91692 | H30: 73433 | I30: 48087 | J30: 53604
A31: 1.02.02.01.01 | B31: Participações em Coligadas | C31: 136724 | D31: 226969 | E31: 131714 | F31: 76284 | G31: 53154 | H31: 27317 | I31: 8303 | J31: 0
A32: 1.02.03 | B32: Imobilizado | C32: 155481 | D32: 146818 | E32: 110987 | F32: 92894 | G32: 86298 | H32: 88718 | I32: 50746 | J32: 57092
A33: 1.02.03.01 | B33: Imobilizado em Operação | C33: 125036 | D33: 116974 | E33: 84915 | F33: 60279 | G33: 47700 | H33: 0 | I33: 0 | J33: 0
A34: 1.02.03.02 | B34: Direito de Uso em Arrendamento | C34: 30445 | D34: 29844 | E34: 26072 | F34: 32615 | G34: 38598 | H34: 41694 | I34: 0 | J34: 0
A35: 1.02.04 | B35: Intangível | C35: 321187 | D35: 130527 | E35: 110777 | F35: 86994 | G35: 97823 | H35: 105138 | I35: 79416 | J35: 62170
A36: 2 | B36: Passivo Total | C36: 4466987 | D36: 4581833 | E36: 4199825 | F36: 3754136 | G36: 2824635 | H36: 1945403 | I36: 1789529 | J36: 1733859
A37: 2.01 | B37: Passivo Circulante | C37: 1503102 | D37: 1934265 | E37: 1773213 | F37: 1937651 | G37: 1370932 | H37: 1178943 | I37: 1111886 | J37: 1090782
A38: 2.01.01 | B38: Obrigações Sociais e Trabalhistas | C38: 105953 | D38: 80891 | E38: 42753 | F38: 38387 | G38: 33263 | H38: 20281 | I38: 18205 | J38: 20122
A39: 2.01.02 | B39: Fornecedores | C39: 658247 | D39: 832121 | E39: 594245 | F39: 1186214 | G39: 562210 | H39: 383964 | I39: 449260 | J39: 486141
A40: 2.01.02.01 | B40: Fornecedores Nacionais | C40: 105953 | D40: 191211 | E40: 290682 | F40: 280741 | G40: 207963 | H40: 196025 | I40: 280194 | J40: 0
A41: 2.01.02.01.01 | B41: Fornecedores | C41: 167077 | D41: 0 | E41: 0 | F41: 0 | G41: 0 | H41: 0 | I41: 0 | J41: 0
A42: 2.01.02.01.02 | B42: Fornecedores - Convênio | C42: 491170 | D42: 0 | E42: 0 | F42: 0 | G42: 0 | H42: 0 | I42: 0 | J42: 0
A43: 2.01.03 | B43: Obrigações Fiscais | C43: 102656 | D43: 73369 | E43: 192806 | F43: 52814 | G43: 32037 | H43: 24035 | I43: 21563 | J43: 35970
A44: 2.01.03.01 | B44: Obrigações Fiscais Federais | C44: 100299 | D44: 60165 | E44: 180197 | F44: 40831 | G44: 27643 | H44: 19004 | I44: 20242 | J44: 0
A45: 2.01.03.01.02 | B45: Tributos a Recolher | C45: 93811 | D45: 0 | E45: 0 | F45: 0 | G45: 0 | H45: 0 | I45: 0 | J45: 0
A46: 2.01.04 | B46: Empréstimos e Financiamentos | C46: 341080 | D46: 694839 | E46: 655704 | F46: 400196 | G46: 461373 | H46: 601728 | I46: 519434 | J46: 439705
A47: 2.01.05 | B47: Outras Obrigações | C47: 156265 | D47: 123124 | E47: 118263 | F47: 95975 | G47: 135275 | H47: 57980 | I47: 24220 | J47: 19028
A48: 2.01.05.01 | B48: Passivos com Partes Relacionadas | C48: 1205 | D48: 2949 | E48: 1140 | F48: 745 | G48: 1213 | H48: 763 | I48: 755 | J48: 3814
... A76: 2.03.08 | B76: Outros Resultados Abrangentes | C76: 0 | D76: 0 | E76: 0 | F76: 0 | G76: 0 | H76: 0 | I76: 0 | J76: 0
A77: TOTAL DO PASSIVO E PATRIMÔNIO LÍQUIDO | C77: =SUM(C68,C36) -> 6113108 | D77: =SUM(D68,D36) -> 6178260 | E77: =SUM(E36,E68) -> 5606145 | F77: =SUM(F36,F68) -> 4935797 | G77: =SUM(G36,G68) -> 3857773 | H77: =SUM(H36,H68) -> 2480297 | I77: =SUM(I36,I68) -> 2299437 | J77: =J36+J68 -> 2240234
B84: .

Sheet DRE
A1: Demonstração do Resultado do Exercício - Análise Horizontal (ANO BASE 2017)
A2: Código da Conta | B2: Descrição da Conta | C2: 2024 | D2: 2023 | E2: 2022 | F2: 2021 | G2: 2020 | H2: 2019 | I2: 2018 | J2: 2017
A3: 3.01 | B3: Receita de Venda de Bens e/ou Serviços | C3: 3688326 | D3: 3926631 | E3: 4993235 | F3: 3365487 | G3: 2192173 | H3: 1915308 | I3: 1890654 | J3: 1913608
A4: 3.02 | B4: Custo dos Bens e/ou Serviços Vendidos | C4: -2764289 | D4: -2864102 | E4: -3796478 | F4: -2596881 | G4: -1743427 | H4: -1435200 | I4: -1436949 | J4: -1420259
A5: 3.03 | B5: Resultado Bruto | C5: 924037 | D5: 1062529 | E5: 1196757 | F5: 768606 | G5: 448746 | H5: 480108 | I5: 453705 | J5: 493349
B6: Margem Bruta | C6: =C5/C3 -> 0.25053019 | D6: =D5/D3 -> 0.27059558 | E6: =E5/E3 -> 0.23967568 | F6: =F5/F3 -> 0.22837883 | G6: =G5/G3 -> 0.20470373 | H6: =H5/H3 -> 0.25066882 | I6: =I5/I3 -> 0.23997252 | J6: =J5/J3 -> 0.2578109
A7: 3.04 | B7: Despesas/Receitas Operacionais | C7: -614527 | D7: -553952 | E7: -571662 | F7: -465457 | G7: -171070 | H7: -381253 | I7: -378691 | J7: -454272
B8: %Receita Líquida | D8: =D7/D3 -> -0.14107564 | E8: =E7/E3 -> -0.1144873 | F8: =F7/F3 -> -0.13830302 | G8: =G7/G3 -> -0.078036724 | H8: =H7/H3 -> -0.19905571 | I8: =I7/I3 -> -0.2002963 | J8: =J7/J3 -> -0.23739031
A9: 3.04.01 | B9: Despesas com Vendas | C9: -436329 | D9: -496236 | E9: -540264 | F9: -363763 | G9: -310653 | H9: -273006 | I9: -276226 | J9: -332140
A10: 3.04.02 | B10: Despesas Gerais e Administrativas | C10: 220817 | D10: -216172 | E10: -197325 | F10: -163437 | G10: -82691 | H10: -112095 | I10: -105148 | J10: -98920
A11: 3.04.03 | B11: Perdas pela Não Recuperabilidade de Ativos | C11: 0 | D11: 0 | E11: 0 | F11: 0 | G11: 0 | H11: 0 | I11: 0 | J11: 0
A12: 3.04.04 | B12: Outras Receitas Operacionais | C12: 50284 | D12: 165013 | E12: 174197 | F12: 57585 | G12: 221150 | H12: 5896 | I12: 5610 | J12: 0
A13: 3.04.06 | B13: Resultado de Equivalência Patrimonial | C13: -7665 | D13: -6557 | E13: -8270 | F13: 4158 | G13: 1124 | H13: -2048 | I13: -2927 | J13: -6125
A14: 3.05 | B14: Resultado Antes do Resultado Financeiro e dos Tributos | C14: 309510 | D14: 508577 | E14: 625095 | F14: 303149 | G14: 277676 | H14: 98855 | I14: 75014 | J14: 39077
A15: 3.06 | B15: Resultado Financeiro | C15: -207374 | D15: -254426 | E15: -31811 | F15: -94912 | G15: -5287 | H15: -70575 | I15: -64781 | J15: -83064
A16: 3.06.01 | B16: Receitas Financeiras | C16: 114170 | D16: 104320 | E16: 39509 | F16: 63856 | G16: 95289 | H16: 37406 | I16: 48130 | J16: 65135
A17: 3.06.02 | B17: Despesas Financeiras | C17: -321544 | D17: 104320 | E17: 86350 | F17: 43706 | G17: 59756 | H17: 32306 | I17: 48130 | J17: 65135
A18: 3.07 | B18: Resultado Antes dos Tributos sobre o Lucro | C18: 102136 | D18: 254151 | E18: 306984 | F18: 208237 | G18: 272389 | H18: 28280 | I18: 10233 | J18: -43987
A19: 3.08 | B19: Imposto de Renda e Contribuição Social sobre o Lucro | C19: -17098 | D19: -3269 | E19: -627 | F19: -5341 | G19: -76547 | H19: -7432 | I19: -10694 | J19: -3564
A20: 3.09 | B20: Resultado Líquido das Operações Continuadas | C20: 85038 | D20: 250882 | E20: 306357 | F20: 202896 | G20: 195842 | H20: 20848 | I20: -461 | J20: -47551
... A22: 3.11.01 | B22: Atribuído a Sócios da Empresa Controladora | C22: 80378 | D22: 246760 | E22: 303117 | F22: 200258 | G22: 190971 | H22: 16459 | I22: -461 | J22: -47551
A23: 3.99 | B23: Lucro por Ação - (Reais / Ação) | C23: 0.00000
A24: 3.99.01 | B24: Lucro Básico por Ação | C24: 0.00000
A25: 3.99.01.01 | B25: ON | D25: 1.7617 | E25: 2.1673 | F25: 1.4287 | G25: 1.4024
A26: 3.99.02 | B26: Lucro Diluído por Ação | C26: 0.57450
A27: 3.99.02.01 | B27: ON | C27: 0.57390 | D27: 1.7583 | E27: 2.1638 | F27: 1.4234 | G27: 1.4005

Sheet DFC
A1: Demonstração de Fluxo de Caixa (Método Indireto - Reais Mil) - Analise Vertical
A2: Código da Conta | B2: Descrição da Conta | C2: 2024 | D2: 2023 | E2: 2022 | F2: 2021 | G2: 2020 | H2: 2019 | I2: 2018 | J2: 2017
A3: 6.01 | B3: Caixa Líquido Atividades Operacionais | C3: 529080 | D3: 540734 | E3: -329969 | F3: -145748 | G3: -223656 | H3: -3671 | I3: -64563 | J3: 112580
A4: 6.01.01 | B4: Caixa Gerado nas Operações | C4: 314101 | D4: 538204 | E4: 601369 | F4: 355087 | G4: 207768 | H4: 128411 | I4: 101775 | J4: 21794
A5: 6.01.01.01 | B5: Lucro Líquido do Período | C5: 85038 | D5: 250882 | E5: 306357 | F5: 202896 | G5: 195842 | H5: 20848 | I5: -461 | J5: -47551
A6: 6.01.01.02 | B6: Depreciação e Amortização | C6: 57417 | D6: 56230 | E6: 49891 | F6: 42344 | G6: 46102 | H6: 35995 | I6: 32586 | J6: 31999
A7: 6.01.01.03 | B7: Equivalência Patrimonial | C7: 7665 | D7: 6557 | E7: 8270 | F7: -4158 | G7: -1124 | H7: 2048 | I7: 2927 | J7: 6125
A8: 6.01.01.04 | B8: Ganho no Valor Justo e Ajuste a Valor Presente | C8: -26243 | D8: -44979 | E8: -155260 | F8: -35656 | G8: -23551 | H8: -8549 | I8: 13083 | J8: -38532
A9: 6.01.01.05 | B9: Provisão (Reversão) para Riscos Tributários, Trabalhistas e Cíveis | C9: 156059 | D9: 7714 | E9: 11645 | F9: 11488 | G9: 4717 | H9: -1868 | I9: -1419 | J9: -1064
A10: 6.01.01.06 | B10: Provisão para Créditos de Liquidação Duvidosa | C10: -1078 | D10: 7655 | E10: 50824 | F10: 7401 | G10: 11252 | H10: 2582 | I10: 7045 | J10: 7923
A11: 6.01.01.07 | B11: Provisão (Reversão) para Perdas em Estoques | C11: 9124 | D11: -2433 | E11: 30934 | F11: 20827 | G11: 23802 | H11: -1867 | I11: 1266 | J11: 15457
A12: 6.01..01.08 | B12: Provisão e Receitas Diferidas | C12: -26017 | D12: 23175 | E12: 28996 | F12: 41884 | G12: 71107 | H12: 0 | I12: 0 | J12: 0
A13: 6.01.01.09 | B13: Stock Options | C13: 1071 | D13: 1882 | E13: 1299 | F13: 1475 | G13: 431 | H13: 425 | I13: 675 | J13: 316
... A56: 6.05.02 | B56: Saldo Final de Caixa e Equivalentes | C56: 566929 | D56: 591375 | E56: 426576 | F56: 359007 | G56: 544162 | H56: 460714 | I56: 393348 | J56: 387826

Sheet DFC - AH E AV
A1: Demonstração de Fluxo de Caixa (Método Indireto - Reais Mil) - Analise Horizontal e Vertical
A2: Código da Conta | B2: Descrição da Conta | C2: 2024 | D2: AH24 | E2: AV24 | F2: 2023 | G2: AH23 | H2: AV23 | I2: 2022 | J2: AH22 | K2: AV22 | L2: 2021 | M2: AH21 | N2: AV21 | O2: 2020 | P2: AH20 | Q2: AV20 | R2: 2019 | S2: AH19 | T2: AV19 | U2: 2018 | V2: AH18 | W2: AV18 | X2: 2017 | Y2: AH17 | Z2: AV17
A3: 6.01 | B3: Caixa Líquido Atividades Operacionais | C3: 529080 | D3: =(C3/X3)*Y3 -> 469.95914 | E3: =C3/$C$3 -> 1 | F3: 540734 | G3: =(F3/X3)*Y3 -> 480.31089 | H3: =F3/$F$3 -> 1 | I3: -329969 | J3: =(I3/X3)*Y3 -> -293.09735 | K3: =I3/$I$3 -> 1 | L3: -145748 | M3: =(L3/X3)*Y3 -> -129.46172 | N3: =L3/$L$3 -> 1 | O3: -223656 | P3: =(O3/X3)*Y3 -> -198.66406 | Q3: =O3/$O$3 -> 1 | R3: -3671 | S3: =(R3/X3)*Y3 -> -3.2607923 | T3: =R3/$R$3 -> 1 | U3: -64563 | V3: =(U3/X3)*Y3 -> -57.348552 | W3: =U3/$U$3 -> 1 | X3: 112580 | Y3: 100 | Z3: =X3/$X$3 -> 1
A4: 6.01.01 | B4: Caixa Gerado nas Operações | C4: 314101 | D4: =(C4/X4)*Y4 -> 1441.2269 | E4: =C4/$C$3 -> 0.59367392 | F4: 538204 | G4: =(F4/X4)*Y4 -> 2469.5054 | H4: =F4/$F$3 -> 0.99532117 | I4: 601369 | J4: =(I4/X4)*Y4 -> 2759.3328 | K4: =I4/$I$3 -> -1.8225015 | L4: 355087 | M4: =(L4/X4)*Y4 -> 1629.2879 | N4: =L4/$L$3 -> -2.4363079 | O4: 207768 | P4: =(O4/X4)*Y4 -> 953.3266 | Q4: =O4/$O$3 -> -0.92896234 | R4: 128411 | S4: =(R4/X4)*Y4 -> 589.20345 | T4: =R4/$R$3 -> -34.979842 | U4: 101775 | V4: =(U4/X4)*Y4 -> 466.98633 | W4: =U4/$U$3 -> -1.5763673 | X4: 21794 | Y4: 100 | Z4: =X4/$X$3 -> 0.19358678
A5: 6.01.01.01 | B5: Lucro Líquido do Período | C5: 85038 | D5: =(C5/X5)*Y5 -> -178.83536 | E5: =C5/$C$3 -> 0.16072806 | F5: 250882 | G5: =(F5/X5)*Y5 -> -527.60615 | H5: =F5/$F$3 -> 0.46396565 | I5: 306357 | J5: =(I5/X5)*Y5 -> -644.27036 | K5: =I5/$I$3 -> -0.92844176 | L5: 202896 | M5: =(L5/X5)*Y5 -> -426.69134 | N5: =L5/$L$3 -> -1.3921014 | O5: 195842 | P5: =(O5/X5)*Y5 -> -411.85674 | Q5: =O5/$O$3 -> -0.87563937 | R5: 20848 | S5: =(R5/X5)*Y5 -> -43.843452 | T5: =R5/$R$3 -> -5.6791065 | U5: -461 | V5: =(U5/X5)*Y5 -> 0.96948539 | W5: =U5/$U$3 -> 0.0071403126 | X5: -47551 | Y5: 100 | Z5: =X5/$X$3 -> -0.4223752
A6: 6.01.01.02 | B6: Depreciação e Amortização | C6: 57417 | D6: =(C6/X6)*Y6 -> 179.43373 | E6: =C6/$C$3 -> 0.10852234 | F6: 56230 | G6: =(F6/X6)*Y6 -> 175.72424 | H6: =F6/$F$3 -> 0.10398828 | I6: 49891 | J6: =(I6/X6)*Y6 -> 155.91425 | K6: =I6/$I$3 -> -0.15119905 | L6: 42344 | M6: =(L6/X6)*Y6 -> 132.32914 | N6: =L6/$L$3 -> -0.29052886 | O6: 46102 | P6: =(O6/X6)*Y6 -> 144.07325 | Q6: =O6/$O$3 -> -0.20612906 | R6: 35995 | S6: =(R6/X6)*Y6 -> 112.48789 | T6: =R6/$R$3 -> -9.8052302 | U6: 32586 | V6: =(U6/X6)*Y6 -> 101.83443 | W6: =U6/$U$3 -> -0.50471632 | X6: 31999 | Y6: 100 | Z6: =X6/$X$3 -> 0.28423343
A7: 6.01.01.03 | B7: Equivalência Patrimonial | C7: 7665 | D7: =(C7/X7)*Y7 -> 125.14286 | E7: =C7/$C$3 -> 0.014487412 | F7: 6557 | G7: =(F7/X7)*Y7 -> 107.05306 | H7: =F7/$F$3 -> 0.01212611 | I7: 8270 | J7: =(I7/X7)*Y7 -> 135.02041 | K7: =I7/$I$3 -> -0.02506296 | L7: -4158 | M7: =(L7/X7)*Y7 -> -67.885714 | N7: =L7/$L$3 -> 0.028528693 | O7: -1124 | P7: =(O7/X7)*Y7 -> -18.35102 | Q7: =O7/$O$3 -> 0.005025575 | R7: 2048 | S7: =(R7/X7)*Y7 -> 33.436735 | T7: =R7/$R$3 -> -0.55788613 | U7: 2927 | V7: =(U7/X7)*Y7 -> 47.787755 | W7: =U7/$U$3 -> -0.045335564 | X7: 6125 | Y7: 100 | Z7: =X7/$X$3 -> 0.054405756
A8: 6.01.01.04 | B8: Ganho no Valor Justo e Ajuste a Valor Presente | C8: -26243 | D8: =(C8/X8)*Y8 -> 68.107028 | E8: =C8/$C$3 -> -0.049601195 | F8: -44979 | G8: =(F8/X8)*Y8 -> 116.73155 | H8: =F8/$F$3 -> -0.083181379 | I8: -155260 | J8: =(I8/X8)*Y8 -> 402.93782 | K8: =I8/$I$3 -> 0.47052905 | L8: -35656 | M8: =(L8/X8)*Y8 -> 92.536074 | N8: =L8/$L$3 -> 0.24464144 | O8: -23551 | P8: =(O8/X8)*Y8 -> 61.120627 | Q8: =O8/$O$3 -> 0.1053001 | R8: -8549 | S8: =(R8/X8)*Y8 -> 22.186754 | T8: =R8/$R$3 -> 2.3287932 | U8: 13083 | V8: =(U8/X8)*Y8 -> -33.953597 | W8: =U8/$U$3 -> -0.20263928 | X8: -38532 | Y8: 100 | Z8: =X8/$X$3 -> -0.34226328
A9: 6.01.01.05 | B9: Provisão (Reversão) para Riscos Tributários, Trabalhistas e Cíveis | C9: 156059 | D9: =(C9/X9)*Y9 -> -14667.199 | E9: =C9/$C$3 -> 0.29496295 | F9: 7714 | G9: =(F9/X9)*Y9 -> -725 | H9: =F9/$F$3 -> 0.014265794 | I9: 11645 | J9: =(I9/X9)*Y9 -> -1094.4549 | K9: =I9/$I$3 -> -0.035291194 | L9: 11488 | M9: =(L9/X9)*Y9 -> -1079.6992 | N9: =L9/$L$3 -> -0.078820979 | O9: 4717 | P9: =(O9/X9)*Y9 -> -443.32707 | Q9: =O9/$O$3 -> -0.021090425 | R9: -1868 | S9: =(R9/X9)*Y9 -> 175.56391 | T9: =R9/$R$3 -> 0.50885317 | U9: -1419 | V9: =(U9/X9)*Y9 -> 133.36466 | W9: =U9/$U$3 -> 0.021978533 | X9: -1064 | Y9: 100 | Z9: =X9/$X$3 -> -0.009451057
A10: 6.01.01.06 | B10: Provisão para Créditos de Liquidação Duvidosa | C10: -1078 | D10: =(C10/X10)*Y10 -> -13.605957 | E10: =C10/$C$3 -> -0.0020374991 | F10: 7655 | G10: =(F10/X10)*Y10 -> 96.617443 | H10: =F10/$F$3 -> 0.014156683 | I10: 50824 | J10: =(I10/X10)*Y10 -> 641.47419 | K10: =I10/$I$3 -> -0.15402659 | L10: 7401 | M10: =(L10/X10)*Y10 -> 93.411587 | N10: =L10/$L$3 -> -0.050779428 | O10: 11252 | P10: =(O10/X10)*Y10 -> 142.01691 | Q10: =O10/$O$3 -> -0.050309404 | R10: 2582 | S10: =(R10/X10)*Y10 -> 32.588666 | T10: =R10/$R$3 -> -0.70335059 | U10: 7045 | V10: =(U10/X10)*Y10 -> 88.918339 | W10: =U10/$U$3 -> -0.10911823 | X10: 7923 | Y10: 100 | Z10: =X10/$X$3 -> 0.070376621
A11: 6.01.01.07 | B11: Provisão (Reversão) para Perdas em Estoques | C11: 9124 | D11: =(C11/X11)*Y11 -> 59.028272 | E11: =C11/$C$3 -> 0.017245029 | F11: -2433 | G11: =(F11/X11)*Y11 -> -15.740441 | H11: =F11/$F$3 -> -0.0044994397 | I11: 30934 | J11: =(I11/X11)*Y11 -> 200.12939 | K11: =I11/$I$3 -> -0.093748201 | L11: 20827 | M11: =(L11/X11)*Y11 -> 134.74154 | N11: =L11/$L$3 -> -0.14289733 | O11: 23802 | P11: =(O11/X11)*Y11 -> 153.98848 | Q11: =O11/$O$3 -> -0.10642236 | R11: -1867 | S11: =(R11/X11)*Y11 -> -12.07867 | T11: =R11/$R$3 -> 0.50858077 | U11: 1266 | V11: =(U11/X11)*Y11 -> 8.1904639 | W11: =U11/$U$3 -> -0.019608754 | X11: 15457 | Y11: 100 | Z11: =X11/$X$3 -> 0.13729792
A12: 6.01..01.08 | B12: Provisão e Receitas Diferidas | C12: -26017 | E12: =C12/$C$3 -> -0.049174038 | F12: 23175 | H12: =F12/$F$3 -> 0.042858411 | I12: 28996 | K12: =I12/$I$3 -> -0.087874922 | L12: 41884 | N12: =L12/$L$3 -> -0.28737273 | O12: 71107 | Q12: =O12/$O$3 -> -0.31793021 | R12: 0 | T12: =R12/$R$3 -> 0 | U12: 0 | W12: =U12/$U$3 -> 0 | X12: 0 | Y12: 100 | Z12: =X12/$X$3 -> 0
A13: 6.01.01.09 | B13: Stock Options | C13: 1071 | D13: =(C13/X13)*Y13 -> 338.92405 | E13: =C13/$C$3 -> 0.0020242685 | F13: 1882 | G13: =(F13/X13)*Y13 -> 595.56962 | H13: =F13/$F$3 -> 0.0034804543 | I13: 1299 | J13: =(I13/X13)*Y13 -> 411.07595 | K13: =I13/$I$3 -> -0.0039367335 | L13: 1475 | M13: =(L13/X13)*Y13 -> 466.77215 | N13: =L13/$L$3 -> -0.010120207 | O13: 431 | P13: =(O13/X13)*Y13 -> 136.39241 | Q13: =O13/$O$3 -> -0.0019270666 | R13: 425 | S13: =(R13/X13)*Y13 -> 134.49367 | T13: =R13/$R$3 -> -0.11577227 | U13: 675 | V13: =(U13/X13)*Y13 -> 213.60759 | W13: =U13/$U$3 -> -0.010454905 | X13: 316 | Y13: 100 | Z13: =X13/$X$3 -> 0.0028068929
A14: 6.01.01.10 | B14: Encargos Sobre Empréstimos e Contratos de Arrendamento | C14: 165561 | D14: =(C14/X14)*Y14 -> 212.45653 | E14: =C14/$C$3 -> 0.31292243 | F14: 235958 | G14: =(F14/X14)*Y14 -> 302.79364 | H14: =F14/$F$3 -> 0.43636612 | I14: 271262 | J14: =(I14/X14)*Y14 -> 348.09758 | K14: =I14/$I$3 -> -0.82208329 | L14: 89200 | M14: =(L14/X14)*Y14 -> 114.4661 | N14: =L14/$L$3 -> -0.61201526 | O14: 61796 | P14: =(O14/X14)*Y14 -> 79.299858 | Q14: =O14/$O$3 -> -0.27629932 | R14: 71813 | S14: =(R14/X14)*Y14 -> 92.154196 | T14: =R14/$R$3 -> -19.562245 | U14: 57138 | V14: =(U14/X14)*Y14 -> 73.322468 | W14: =U14/$U$3 -> -0.88499605 | X14: 77927 | Y14: 100 | Z14: =X14/$X$3 -> 0.69219222
A15: 6.01.01.11 | B15: Variação Cambial | C15: 29622 | D15: =(C15/X15)*Y15 -> -86.185627 | E15: =C15/$C$3 -> 0.055987752 | F15: -5380 | G15: =(F15/X15)*Y15 -> 15.653186 | H15: =F15/$F$3 -> -0.0099494391 | I15: 6129 | J15: =(I15/X15)*Y15 -> -17.832412 | K15: =I15/$I$3 -> -0.018574472 | L15: 6743 | M15: =(L15/X15)*Y15 -> -19.618854 | N15: =L15/$L$3 -> -0.046264786 | O15: -5967 | P15: =(O15/X15)*Y15 -> 17.361071 | Q15: =O15/$O$3 -> 0.026679365 | R15: -5384 | S15: =(R15/X15)*Y15 -> 15.664824 | T15: =R15/$R$3 -> 1.4666303 | U15: -17204 | V15: =(U15/X15)*Y15 -> 50.055281 | W15: =U15/$U$3 -> 0.26646841 | X15: -34370 | Y15: 100 | Z15: =X15/$X$3 -> -0.30529401
A16: 6.01.01.12 | B16: Juros Sobre Impostos e Atualização Monetária | C16: 5607 | E16: =C16/$C$3 -> 0.010597641 | F16: -2326 | H16: =F16/$F$3 -> -0.0043015605 | I16: -9605 | K16: =I16/$I$3 -> 0.029108795 | L16: -16506 | N16: =L16/$L$3 -> 0.11325027 | O16: -31810 | Q16: =O16/$O$3 -> 0.14222735 | R16: -3403 | T16: =R16/$R$3 -> 0.92699537 | U16: -4555 | W16: =U16/$U$3 -> 0.070551245 | X16: 0 | Y16: 100 | Z16: =X16/$X$3 -> 0
A17: 6.01.01.13 | B17: Ganhos (Perdas) em Processos Administrativos e Judiciais | C17: 0 | E17: =C17/$C$3 -> 0 | F17: 0 | H17: =F17/$F$3 -> 0 | I17: 0 | K17: =I17/$I$3 -> 0 | L17: -14734 | N17: =L17/$L$3 -> 0.1010923 | O17: -221376 | Q17: =O17/$O$3 -> 0.98980577 | R17: 0 | T17: =R17/$R$3 -> 0 | U17: 0 | W17: =U17/$U$3 -> 0 | X17: 0 | Y17: 100 | Z17: =X17/$X$3 -> 0
A18: 6.01.01.14 | B18: Imposto de Renda e Contribuição Social (Corrente e Diferido) | C18: 17098 | E18: =C18/$C$3 -> 0.032316474 | F18: 3269 | H18: =F18/$F$3 -> 0.0060454863 | I18: 627 | K18: =I18/$I$3 -> -0.0019001785 | L18: 5341 | N18: =L18/$L$3 -> -0.036645443 | O18: 76547 | Q18: =O18/$O$3 -> -0.34225328 | R18: 7432 | T18: =R18/$R$3 -> -2.0245165 | U18: 10694 | W18: =U18/$U$3 -> -0.16563666 | X18: 0 | Y18: 100 | Z18: =X18/$X$3 -> 0
A19: 6.01.01.15 | B19: Ganho na Alienação de Imobilizados | C19: 0 | E19: =C19/$C$3 -> 0 | F19: 0 | H19: =F19/$F$3 -> 0 | I19: 0 | K19: =I19/$I$3 -> 0 | L19: -3458 | N19: =L19/$L$3 -> 0.023725883 | O19: 0 | Q19: =O19/$O$3 -> 0 | R19: 0 | T19: =R19/$R$3 -> 0 | U19: 0 | W19: =U19/$U$3 -> 0 | X19: 0 | Y19: 100 | Z19: =X19/$X$3 -> 0
A20: 6.01.02 | B20: Variações nos Ativos e Passivos | C20: 214979 | D20: =(C20/X20)*Y20 -> 236.79752 | E20: =C20/$C$3 -> 0.40632608 | F20: 2530 | G20: =(F20/X20)*Y20 -> 2.7867733 | H20: =F20/$F$3 -> 0.0046788254 | I20: -931338 | J20: =(I20/X20)*Y20 -> -1025.8608 | K20: =I20/$I$3 -> 2.8225015 | L20: -500835 | M20: =(L20/X20)*Y20 -> -551.66546 | N20: =L20/$L$3 -> 3.4363079 | O20: -431424 | P20: =(O20/X20)*Y20 -> -475.20983 | Q20: =O20/$O$3 -> 1.9289623 | R20: -132082 | S20: =(R20/X20)*Y20 -> -145.48719 | T20: =R20/$R$3 -> 35.979842 | U20: -166338 | V20: =(U20/X20)*Y20 -> -183.21988 | W20: =U20/$U$3 -> 2.5763673 | X20: 90786 | Y20: 100 | Z20: =X20/$X$3 -> 0.80641322
A21: 6.01.02.01 | B21: Contas a Receber | C21: 441827 | D21: =(C21/X21)*Y21 -> 3974.3366 | E21: =C21/$C$3 -> 0.83508543 | F21: -200525 | G21: =(F21/X21)*Y21 -> -1803.769 | H21: =F21/$F$3 -> -0.37083853 | I21: -441003 | J21: =(I21/X21)*Y21 -> -3966.9245 | K21: =I21/$I$3 -> 1.3364983 | L21: -74514 | M21: =(L21/X21)*Y21 -> -670.27076 | N21: =L21/$L$3 -> 0.5112523 | O21: -451149 | P21: =(O21/X21)*Y21 -> -4058.1902 | Q21: =O21/$O$3 -> 2.0171558 | R21: -25435 | S21: =(R21/X21)*Y21 -> -228.79374 | T21: =R21/$R$3 -> 6.9286298 | U21: 58353 | V21: =(U21/X21)*Y21 -> 524.8988 | W21: =U21/$U$3 -> -0.90381488 | X21: 11117 | Y21: 100 | Z21: =X21/$X$3 -> 0.098747557
A22: 6.01.02.02 | B22: Estoques | C22: 152343 | D22: =(C22/X22)*Y22 -> -224.91695 | E22: =C22/$C$3 -> 0.28793944 | F22: 148528 | G22: =(F22/X22)*Y22 -> -219.28454 | H22: =F22/$F$3 -> 0.27467849 | I22: 265514 | J22: =(I22/X22)*Y22 -> -392.00094 | K22: =I22/$I$3 -> -0.80466347 | L22: -1061553 | M22: =(L22/X22)*Y22 -> 1567.2612 | N22: =L22/$L$3 -> 7.2834824 | O22: -190753 | P22: =(O22/X22)*Y22 -> 281.62491 | Q22: =O22/$O$3 -> 0.85288568 | R22: 22777 | S22: =(R22/X22)*Y22 -> -33.627626 | T22: =R22/$R$3 -> -6.2045764 | U22: -63200 | V22: =(U22/X22)*Y22 -> 93.307546 | W22: =U22/$U$3 -> 0.97888884 | X22: -67733 | Y22: 100 | Z22: =X22/$X$3 -> -0.60164328
A23: 6.01.02.03 | B23: Imposto a Recuperar | C23: -30560 | D23: =(C23/X23)*Y23 -> -140.24138 | E23: =C23/$C$3 -> -0.057760641 | F23: -104020 | G23: =(F23/X23)*Y23 -> -477.35304 | H23: =F23/$F$3 -> -0.19236815 | I23: -206173 | J23: =(I23/X23)*Y23 -> -946.13831 | K23: =I23/$I$3 -> 0.62482536 | L23: 69167 | M23: =(L23/X23)*Y23 -> 317.41086 | N23: =L23/$L$3 -> -0.47456569 | O23: -37104 | P23: =(O23/X23)*Y23 -> -170.27213 | Q23: =O23/$O$3 -> 0.16589763 | R23: -8262 | S23: =(R23/X23)*Y23 -> -37.914735 | T23: =R23/$R$3 -> 2.2506129 | U23: 8497 | V23: =(U23/X23)*Y23 -> 38.993162 | W23: =U23/$U$3 -> -0.13160789 | X23: 21791 | Y23: 100 | Z23: =X23/$X$3 -> 0.19356014
A24: 6.01.02.04 | B24: Adiantamentos Diversos | C24: 15713 | D24: =(C24/X24)*Y24 -> -221.96638 | E24: =C24/$C$3 -> 0.029698722 | F24: -5607 | G24: =(F24/X24)*Y24 -> 79.206103 | H24: =F24/$F$3 -> -0.010369239 | I24: 6075 | J24: =(I24/X24)*Y24 -> -85.817206 | K24: =I24/$I$3 -> -0.01841082 | L24: -7860 | M24: =(L24/X24)*Y24 -> 111.03263 | N24: =L24/$L$3 -> 0.053928699 | O24: 15790 | P24: =(O24/X24)*Y24 -> -223.0541 | Q24: =O24/$O$3 -> -0.070599492 | R24: 4100 | S24: =(R24/X24)*Y24 -> -57.917785 | T24: =R24/$R$3 -> -1.1168619 | U24: -20053 | V24: =(U24/X24)*Y24 -> 283.27447 | W24: =U24/$U$3 -> 0.31059585 | X24: -7079 | Y24: 100 | Z24: =X24/$X$3 -> -0.06287973
A25: 6.01.02.05 | B25: Contas a Receber de Partes Relacionadas | C25: -1532 | E25: =C25/$C$3 -> -0.0028955923 | F25: 442 | H25: =F25/$F$3 -> 0.00081740745 | I25: 704 | K25: =I25/$I$3 -> -0.0021335338 | L25: 9904 | N25: =L25/$L$3 -> -0.067952905 | O25: 15296 | Q25: =O25/$O$3 -> -0.068390743 | R25: 0 | T25: =R25/$R$3 -> 0 | U25: 0 | W25: =U25/$U$3 -> 0 | X25: 0 | Y25: 100 | Z25: =X25/$X$3 -> 0
A26: 6.01.02.06 | B26: Outros Créditos | C26: 18047 | D26: =(C26/X26)*Y26 -> 1180.3139 | E26: =C26/$C$3 -> 0.034110153 | F26: 74404 | G26: =(F26/X26)*Y26 -> 4866.1871 | H26: =F26/$F$3 -> 0.13759815 | I26: 12900 | J26: =(I26/X26)*Y26 -> 843.68869 | K26: =I26/$I$3 -> -0.039094582 | L26: -19615 | M26: =(L26/X26)*Y26 -> -1282.8646 | N26: =L26/$L$3 -> 0.13458161 | O26: 15352 | P26: =(O26/X26)*Y26 -> 1004.0549 | Q26: =O26/$O$3 -> -0.068641127 | R26: -21639 | S26: =(R26/X26)*Y26 -> -1415.2387 | T26: =R26/$R$3 -> 5.8945791 | U26: -49586 | V26: =(U26/X26)*Y26 -> -3243.0347 | W26: =U26/$U$3 -> 0.76802503 | X26: 1529 | Y26: 100 | Z26: =X26/$X$3 -> 0.013581453
A27: 6.01.02.07 | B27: Fornecedores | C27: -207637 | D27: =(C27/X27)*Y27 -> -158.59959 | E27: =C27/$C$3 -> -0.39244916 | F27: 218471 | G27: =(F27/X27)*Y27 -> 166.87494 | H27: =F27/$F$3 -> 0.40402675 | I27: -601854 | J27: =(I27/X27)*Y27 -> -459.71479 | K27: =I27/$I$3 -> 1.8239713 | L27: 659992 | M27: =(L27/X27)*Y27 -> 504.1224 | N27: =L27/$L$3 -> -4.5283091 | O27: 178231 | P27: =(O27/X27)*Y27 -> 136.13838 | Q27: =O27/$O$3 -> -0.79689791 | R27: -56863 | S27: =(R27/X27)*Y27 -> -43.433726 | T27: =R27/$R$3 -> 15.489785 | U27: -18115 | V27: =(U27/X27)*Y27 -> -13.8368 | W27: =U27/$U$3 -> 0.28057866 | X27: 130919 | Y27: 100 | Z27: =X27/$X$3 -> 1.1628975
A28: 6.01.02.08 | B28: Obrigações Tributarias | C28: 20966 | D28: =(C28/X28)*Y28 -> 81.19433 | E28: =C28/$C$3 -> 0.039627278 | F28: 42891 | G28: =(F28/X28)*Y28 -> 166.10255 | H28: =F28/$F$3 -> 0.079319961 | I28: 139992 | J28: =(I28/X28)*Y28 -> 542.14236 | K28: =I28/$I$3 -> -0.42425804 | L28: 20777 | M28: =(L28/X28)*Y28 -> 80.462396 | N28: =L28/$L$3 -> -0.14255427 | O28: 8002 | P28: =(O28/X28)*Y28 -> 30.989079 | Q28: =O28/$O$3 -> -0.035778159 | R28: -848 | S28: =(R28/X28)*Y28 -> -3.2840214 | T28: =R28/$R$3 -> 0.23099973 | U28: -24700 | V28: =(U28/X28)*Y28 -> -95.654868 | W28: =U28/$U$3 -> 0.38257206 | X28: 25822 | Y28: 100 | Z28: =X28/$X$3 -> 0.22936578
A29: 6.01.02.09 | B29: Outras Contas a Pagar | C29: 3086 | D29: =(C29/X29)*Y29 -> -101.04781 | E29: =C29/$C$3 -> 0.0058327663 | F29: -1687 | G29: =(F29/X29)*Y29 -> 55.239031 | H29: =F29/$F$3 -> -0.0031198334 | I29: -2674 | J29: =(I29/X29)*Y29 -> 87.557302 | K29: =I29/$I$3 -> 0.0081037916 | L29: -23041 | M29: =(L29/X29)*Y29 -> 754.45318 | N29: =L29/$L$3 -> 0.15808793 | O29: 55323 | P29: =(O29/X29)*Y29 -> -1811.4931 | Q29: =O29/$O$3 -> -0.24735755 | R29: -942 | S29: =(R29/X29)*Y29 -> 30.844794 | T29: =R29/$R$3 -> 0.25660583 | U29: 804 | V29: =(U29/X29)*Y29 -> -26.32613 | W29: =U29/$U$3 -> -0.012452953 | X29: -3054 | Y29: 100 | Z29: =X29/$X$3 -> -0.027127376
A30: 6.01.02.10 | B30: Contas a Pagar de Partes Relacionadas | C30: 193 | E30: =C30/$C$3 -> 0.00036478415 | F30: -128 | H30: =F30/$F$3 -> -0.00023671528 | I30: 0 | K30: =I30/$I$3 -> 0 | L30: 0 | N30: =L30/$L$3 -> 0 | O30: 0 | Q30: =O30/$O$3 -> 0 | R30: 0 | T30: =R30/$R$3 -> 0 | U30: 0 | W30: =U30/$U$3 -> 0 | X30: 0 | Y30: 100 | Z30: =X30/$X$3 -> 0
A31: 6.01.02.11 | B31: Pagamento de Juros Sobre Empréstimos e Contratos de Arrendamento | C31: -185862 | D31: =(C31/X31)*Y31 -> 522.62745 | E31: =C31/$C$3 -> -0.35129281 | F31: -162205 | G31: =(F31/X31)*Y31 -> 456.10607 | H31: =F31/$F$3 -> -0.29997189 | I31: -100278 | J31: =(I31/X31)*Y31 -> 281.97284 | K31: =I31/$I$3 -> 0.30390128 | L31: -68264 | M31: =(L31/X31)*Y31 -> 191.95231 | N31: =L31/$L$3 -> 0.46837006 | O31: -40412 | P31: =(O31/X31)*Y31 -> 113.63496 | Q31: =O31/$O$3 -> 0.1806882 | R31: -63766 | S31: =(R31/X31)*Y31 -> 179.30433 | T31: =R31/$R$3 -> 17.370199 | U31: -82795 | V31: =(U31/X31)*Y31 -> 232.81219 | W31: =U31/$U$3 -> 1.2823908 | X31: -35563 | Y31: 100 | Z31: =X31/$X$3 -> -0.31589092
A32: 6.01.02.12 | B32: Indenizações | C32: -11605 | E32: =C32/$C$3 -> -0.021934301 | F32: -8034 | H32: =F32/$F$3 -> -0.014857582 | I32: -4541 | K32: =I32/$I$3 -> 0.013761899 | L32: -5828 | N32: =L32/$L$3 -> 0.039986827 | O32: 0 | Q32: =O32/$O$3 -> 0 | R32: 0 | T32: =R32/$R$3 -> 0 | U32: 0 | W32: =U32/$U$3 -> 0 | X32: 0 | Y32: 100 | Z32: =X32/$X$3 -> 0
A33: 6.01.03 | B33: Outros | C33: 0 | E33: =C33/$C$3 -> 0 | F33: 0 | H33: =F33/$F$3 -> 0 | I33: 0 | K33: =I33/$I$3 -> 0 | L33: 0 | N33: =L33/$L$3 -> 0 | O33: 0 | Q33: =O33/$O$3 -> 0 | R33: 0 | T33: =R33/$R$3 -> 0 | U33: 0 | W33: =U33/$U$3 -> 0 | X33: 0 | Y33: 100 | Z33: =X33/$X$3 -> 0
A34: 6.02 | B34: Caixa Líquido Atividades de Investimento | C34: -286526 | D34: =(C34/X34)*Y34 -> 665.42651 | E34: =C34/$C$3 -> -0.54155515 | F34: -161297 | G34: =(F34/X34)*Y34 -> 374.59532 | H34: =F34/$F$3 -> -0.29829269 | I34: -155602 | J34: =(I34/X34)*Y34 -> 361.36928 | K34: =I34/$I$3 -> 0.47156551 | L34: -67034 | M34: =(L34/X34)*Y34 -> 155.67942 | N34: =L34/$L$3 -> 0.45993084 | O34: -43307 | P34: =(O34/X34)*Y34 -> 100.57595 | Q34: =O34/$O$3 -> 0.19363219 | R34: -31968 | S34: =(R34/X34)*Y34 -> 74.242319 | T34: =R34/$R$3 -> 8.7082539 | U34: -10853 | V34: =(U34/X34)*Y34 -> 25.204951 | W34: =U34/$U$3 -> 0.16809938 | X34: -43059 | Y34: 100 | Z34: =X34/$X$3 -> -0.38247468
A35: 6.02.01 | B35: Recebimento de Dividendos | C35: 0 | E35: =C35/$C$3 -> 0 | F35: 0 | H35: =F35/$F$3 -> 0 | I35: 0 | K35: =I35/$I$3 -> 0 | L35: 0 | N35: =L35/$L$3 -> 0 | O35: 0 | Q35: =O35/$O$3 -> 0 | R35: 0 | T35: =R35/$R$3 -> 0 | U35: 0 | W35: =U35/$U$3 -> 0 | X35: 0 | Y35: 100 | Z35: =X35/$X$3 -> 0
A36: 6.02.02 | B36: Integralização de Capital - Investida | C36: -23196 | E36: =C36/$C$3 -> -0.043842141 | F36: -68677 | H36: =F36/$F$3 -> -0.12700699 | I36: -72553 | K36: =I36/$I$3 -> 0.21987823 | L36: -13501 | N36: =L36/$L$3 -> 0.092632489 | O36: -12000 | Q36: =O36/$O$3 -> 0.053653826 | R36: -12600 | T36: =R36/$R$3 -> 3.4323073 | U36: 0 | W36: =U36/$U$3 -> 0 | X36: 0 | Y36: 100 | Z36: =X36/$X$3 -> 0
A37: 6.02.03 | B37: Aquisição de Investimento | C37: 0 | E37: =C37/$C$3 -> 0 | F37: 0 | H37: =F37/$F$3 -> 0 | I37: 0 | K37: =I37/$I$3 -> 0 | L37: 0 | N37: =L37/$L$3 -> 0 | O37: 0 | Q37: =O37/$O$3 -> 0 | R37: 0 | T37: =R37/$R$3 -> 0 | U37: 7673 | W37: =U37/$U$3 -> -0.11884516 | X37: 0 | Y37: 100 | Z37: =X37/$X$3 -> 0
A38: 6.02.04 | B38: Aquisição de Imobilizado | C38: -20886 | D38: =(C38/X38)*Y38 -> 132.53379 | E38: =C38/$C$3 -> -0.039476072 | F38: -49228 | G38: =(F38/X38)*Y38 -> 312.38023 | H38: =F38/$F$3 -> -0.091039217 | I38: -35286 | J38: =(I38/X38)*Y38 -> 223.91015 | K38: =I38/$I$3 -> 0.10693732 | L38: -27481 | M38: =(L38/X38)*Y38 -> 174.38289 | N38: =L38/$L$3 -> 0.18855147 | O38: -9186 | P38: =(O38/X38)*Y38 -> 58.290501 | Q38: =O38/$O$3 -> 0.041072003 | R38: -5078 | S38: =(R38/X38)*Y38 -> 32.222857 | T38: =R38/$R$3 -> 1.3832743 | U38: -4283 | V38: =(U38/X38)*Y38 -> 27.17812 | W38: =U38/$U$3 -> 0.066338305 | X38: -15759 | Y38: 100 | Z38: =X38/$X$3 -> -0.13998046
A39: 6.02.05 | B39: Aumento do Intangível | C39: -70198 | D39: =(C39/X39)*Y39 -> 257.13553 | E39: =C39/$C$3 -> -0.13267937 | F39: -36571 | G39: =(F39/X39)*Y39 -> 133.95971 | H39: =F39/$F$3 -> -0.067632144 | I39: -47763 | J39: =(I39/X39)*Y39 -> 174.95604 | K39: =I39/$I$3 -> 0.14474996 | L39: -16043 | M39: =(L39/X39)*Y39 -> 58.765568 | N39: =L39/$L$3 -> 0.11007355 | O39: -22121 | P39: =(O39/X39)*Y39 -> 81.029304 | Q39: =O39/$O$3 -> 0.098906356 | R39: -14290 | S39: =(R39/X39)*Y39 -> 52.344322 | T39: =R39/$R$3 -> 3.8926723 | U39: -14243 | V39: =(U39/X39)*Y39 -> 52.172161 | W39: =U39/$U$3 -> 0.22060623 | X39: -27300 | Y39: 100 | Z39: =X39/$X$3 -> -0.24249423
A40: 6.02.06 | B40: Pagamento por aquisição de contolada | C40: 0 | E40: =C40/$C$3 -> 0 | F40: -7229 | H40: =F40/$F$3 -> -0.013368865 | I40: 0 | K40: =I40/$I$3 -> 0 | L40: -10009 | N40: =L40/$L$3 -> 0.068673327 | O40: 0 | Q40: =O40/$O$3 -> 0 | R40: 0 | T40: =R40/$R$3 -> 0 | U40: 0 | W40: =U40/$U$3 -> 0 | X40: 0 | Y40: 100 | Z40: =X40/$X$3 -> 0
A41: 6.02.07 | B41: Mútuo e demais operações com investidas/partes relacionadas | C41: -13123 | E41: =C41/$C$3 -> -0.024803432 | F41: 0 | H41: =F41/$F$3 -> 0 | I41: 0 | K41: =I41/$I$3 -> 0 | L41: 0 | N41: =L41/$L$3 -> 0 | O41: 0 | Q41: =O41/$O$3 -> 0 | R41: 0 | T41: =R41/$R$3 -> 0 | U41: 0 | W41: =U41/$U$3 -> 0 | X41: 0 | Y41: 100 | Z41: =X41/$X$3 -> 0
A42: 6.03 | B42: Caixa Líquido Atividades de Financiamento | C42: -262982 | D42: =(C42/X42)*Y42 -> 163.99272 | E42: =C42/$C$3 -> -0.49705527 | F42: -214854 | G42: =(F42/X42)*Y42 -> 133.98062 | H42: =F42/$F$3 -> -0.39733769 | I42: 552079 | J42: =(I42/X42)*Y42 -> -344.27046 | K42: =I42/$I$3 -> -1.6731238 | L42: 28564 | M42: =(L42/X42)*Y42 -> -17.8122 | N42: =L42/$L$3 -> -0.19598211 | O42: 351552 | P42: =(O42/X42)*Y42 -> -219.22401 | Q42: =O42/$O$3 -> -1.5718425 | R42: 103155 | S42: =(R42/X42)*Y42 -> -64.326337 | T42: =R42/$R$3 -> -28.099973 | U42: 80262 | V42: =(U42/X42)*Y42 -> -50.050511 | W42: =U42/$U$3 -> -1.2431578 | X42: -160362 | Y42: 100 | Z42: =X42/$X$3 -> -1.4244271
A43: 6.03.01 | B43: Aumento do Capital Social | C43: 0 | E43: =C43/$C$3 -> 0 | F43: 0 | H43: =F43/$F$3 -> 0 | I43: 0 | K43: =I43/$I$3 -> 0 | L43: 0 | N43: =L43/$L$3 -> 0 | O43: 332670 | Q43: =O43/$O$3 -> -1.4874182 | R43: 0 | T43: =R43/$R$3 -> 0 | U43: 0 | W43: =U43/$U$3 -> 0 | X43: 0 | Y43: 100 | Z43: =X43/$X$3 -> 0
A44: 6.03.02 | B44: Pagamento de Dividendo | C44: -61992 | E44: =C44/$C$3 -> -0.11716943 | F44: -77368 | H44: =F44/$F$3 -> -0.14307959 | I44: -50329 | K44: =I44/$I$3 -> 0.15252645 | L44: -52591 | N44: =L44/$L$3 -> 0.36083514 | O44: -5518 | Q44: =O44/$O$3 -> 0.024671817 | R44: 0 | T44: =R44/$R$3 -> 0 | U44: 0 | W44: =U44/$U$3 -> 0 | X44: 0 | Y44: 100 | Z44: =X44/$X$3 -> 0
A45: 6.03.03 | B45: Captação de Empréstimos | C45: 1153228 | D45: =(C45/X45)*Y45 -> 178.1691 | E45: =C45/$C$3 -> 2.1796855 | F45: 494659 | G45: =(F45/X45)*Y45 -> 76.422831 | H45: =F45/$F$3 -> 0.91479175 | I45: 1198679 | J45: =(I45/X45)*Y45 -> 185.1911 | K45: =I45/$I$3 -> -3.6327019 | L45: 689110 | M45: =(L45/X45)*Y45 -> 106.46473 | N45: =L45/$L$3 -> -4.7280923 | O45: 698105 | P45: =(O45/X45)*Y45 -> 107.85442 | Q45: =O45/$O$3 -> -3.1213337 | R45: 727649 | S45: =(R45/X45)*Y45 -> 112.41885 | T45: =R45/$R$3 -> -198.21547 | U45: 628394 | V45: =(U45/X45)*Y45 -> 97.084352 | W45: =U45/$U$3 -> -9.7330359 | X45: 647266 | Y45: 100 | Z45: =X45/$X$3 -> 5.7493871
A46: 6.03.04 | B46: Amortização de Empréstimos | C46: -1321355 | E46: =C46/$C$3 -> -2.4974579 | F46: -622569 | H46: =F46/$F$3 -> -1.1513406 | I46: -575486 | K46: =I46/$I$3 -> 1.7440608 | L46: -588090 | N46: =L46/$L$3 -> 4.0349782 | O46: -658452 | Q46: =O46/$O$3 -> 2.9440391 | R46: -616552 | T46: =R46/$R$3 -> 167.95206 | U46: -543148 | W46: =U46/$U$3 -> 8.4126822 | X46: 0 | Y46: 100 | Z46: =X46/$X$3 -> 0
A47: 6.03.05 | B47: Pagamentos de Contratos de Arrendamentos | C47: -11352 | D47: =(C47/X47)*Y47 -> 1.395728 | E47: =C47/$C$3 -> -0.021456112 | F47: -11381 | G47: =(F47/X47)*Y47 -> 1.3992935 | H47: =F47/$F$3 -> -0.021047317 | I47: -10267 | J47: =(I47/X47)*Y47 -> 1.2623273 | K47: =I47/$I$3 -> 0.031115044 | L47: -8604 | M47: =(L47/X47)*Y47 -> 1.0578615 | N47: =L47/$L$3 -> 0.0590334 | O47: 0 | P47: =(O47/X47)*Y47 -> 0 | Q47: =O47/$O$3 -> 0 | R47: 0 | S47: =(R47/X47)*Y47 -> 0 | T47: =R47/$R$3 -> 0 | U47: 0 | V47: =(U47/X47)*Y47 -> 0 | W47: =U47/$U$3 -> 0 | X47: -813339 | Y47: 100 | Z47: =X47/$X$3 -> -7.2245425
A48: 6.03.06 | B48: Captação de empréstimos junto ao BNDES | C48: 0 | D48: =(C48/X48)*Y48 -> 0 | E48: =C48/$C$3 -> 0 | F48: 0 | G48: =(F48/X48)*Y48 -> 0 | H48: =F48/$F$3 -> 0 | I48: 0 | J48: =(I48/X48)*Y48 -> 0 | K48: =I48/$I$3 -> 0 | L48: 0 | M48: =(L48/X48)*Y48 -> 0 | N48: =L48/$L$3 -> 0 | O48: 0 | P48: =(O48/X48)*Y48 -> 0 | Q48: =O48/$O$3 -> 0 | R48: 0 | S48: =(R48/X48)*Y48 -> 0 | T48: =R48/$R$3 -> 0 | U48: 0 | V48: =(U48/X48)*Y48 -> 0 | W48: =U48/$U$3 -> 0 | X48: 20318 | Y48: 100 | Z48: =X48/$X$3 -> 0.18047611
A49: 6.03.07 | B49: Recompra de Ações | C49: -9201 | E49: =C49/$C$3 -> -0.017390565 | F49: 0 | H49: =F49/$F$3 -> 0 | I49: 0 | K49: =I49/$I$3 -> 0 | L49: -14632 | N49: =L49/$L$3 -> 0.10039246 | O49: -1901 | Q49: =O49/$O$3 -> 0.0084996602 | R49: 0 | T49: =R49/$R$3 -> 0 | U49: 0 | W49: =U49/$U$3 -> 0 | X49: 0 | Y49: 100 | Z49: =X49/$X$3 -> 0
A50: 6.03.08 | B50: Recursos Provenientes do Exercício de Opções de Ações | C50: 2799 | E50: =C50/$C$3 -> 0.0052903153 | F50: 585 | H50: =F50/$F$3 -> 0.0010818628 | I50: 983 | K50: =I50/$I$3 -> -0.0029790677 | L50: 3371 | N50: =L50/$L$3 -> -0.023128962 | O50: 394 | Q50: =O50/$O$3 -> -0.0017616339 | R50: 0 | T50: =R50/$R$3 -> 0 | U50: 0 | W50: =U50/$U$3 -> 0 | X50: 0 | Y50: 100 | Z50: =X50/$X$3 -> 0
A51: 6.03.09 | B51: Partes relacionadas | C51: -1937 | D51: =(C51/X51)*Y51 -> 14.155218 | E51: =C51/$C$3 -> -0.003661072 | F51: 1220 | G51: =(F51/X51)*Y51 -> -8.9155218 | H51: =F51/$F$3 -> 0.0022561925 | I51: -1354 | J51: =(I51/X51)*Y51 -> 9.8947676 | K51: =I51/$I$3 -> 0.0041034158 | L51: 0 | M51: =(L51/X51)*Y51 -> 0 | N51: =L51/$L$3 -> 0 | O51: 394 | P51: =(O51/X51)*Y51 -> -2.8792751 | Q51: =O51/$O$3 -> -0.0017616339 | R51: -2460 | S51: =(R51/X51)*Y51 -> 17.9772 | T51: =R51/$R$3 -> 0.67011713 | U51: -4029 | V51: =(U51/X51)*Y51 -> 29.443145 | W51: =U51/$U$3 -> 0.062404163 | X51: -13684 | Y51: 100 | Z51: =X51/$X$3 -> -0.12154912
A52: 6.03.10 | B52: Pagamento por aquisição de contolada | C52: -13172 | E52: =C52/$C$3 -> -0.024896046 | F52: 0 | H52: =F52/$F$3 -> 0 | I52: -10147 | K52: =I52/$I$3 -> 0.030751374 | L52: 0 | N52: =L52/$L$3 -> 0 | O52: -5331 | Q52: =O52/$O$3 -> 0.023835712 | R52: 0 | T52: =R52/$R$3 -> 0 | U52: 0 | W52: =U52/$U$3 -> 0 | X52: 0 | Y52: 100 | Z52: =X52/$X$3 -> 0
A53: 6.04 | B53: Variação cambial s/caixa e Equivalentes | C53: -4018 | D53: =(C53/X53)*Y53 -> -1380.756 | E53: =C53/$C$3 -> -0.0075943147 | F53: 216 | G53: =(F53/X53)*Y53 -> 74.226804 | H53: =F53/$F$3 -> 0.00039945703 | I53: 1061 | J53: =(I53/X53)*Y53 -> 364.60481 | K53: =I53/$I$3 -> -0.0032154536 | L53: -937 | M53: =(L53/X53)*Y53 -> -321.99313 | N53: =L53/$L$3 -> 0.0064289047 | O53: -1141 | P53: =(O53/X53)*Y53 -> -392.09622 | Q53: =O53/$O$3 -> 0.0051015846 | R53: -150 | S53: =(R53/X53)*Y53 -> -51.546392 | T53: =R53/$R$3 -> 0.040860801 | U53: 676 | V53: =(U53/X53)*Y53 -> 232.30241 | W53: =U53/$U$3 -> -0.010470393 | X53: 291 | Y53: 100 | Z53: =X53/$X$3 -> 0.0025848286
A54: 6.05 | B54: Aumento (Redução) de Caixa e Equivalentes | C54: -24446 | D54: =(C54/X54)*Y54 -> 26.997239 | E54: =C54/$C$3 -> -0.046204733 | F54: 164799 | G54: =(F54/X54)*Y54 -> -181.99779 | H54: =F54/$F$3 -> 0.30476907 | I54: 67569 | J54: =(I54/X54)*Y54 -> -74.620652 | K54: =I54/$I$3 -> -0.20477378 | L54: -185155 | M54: =(L54/X54)*Y54 -> 204.47819 | N54: =L54/$L$3 -> 1.2703776 | O54: 83448 | P54: =(O54/X54)*Y54 -> -92.156819 | Q54: =O54/$O$3 -> -0.3731087 | R54: 67366 | S54: =(R54/X54)*Y54 -> -74.396466 | T54: =R54/$R$3 -> -18.350858 | U54: 5522 | V54: =(U54/X54)*Y54 -> -6.0982882 | W54: =U54/$U$3 -> -0.085528863 | X54: -90550 | Y54: 100 | Z54: =X54/$X$3 -> -0.80431693
A55: 6.05.01 | B55: Saldo Inicial de Caixa e Equivalentes | C55: 591375 | D55: =(C55/X55)*Y55 -> 123.62138 | E55: =C55/$C$3 -> 1.1177421 | F55: 426576 | G55: =(F55/X55)*Y55 -> 89.171698 | H55: =F55/$F$3 -> 0.78888326 | I55: 359007 | J55: =(I55/X55)*Y55 -> 75.047034 | K55: =I55/$I$3 -> -1.0880022 | L55: 544162 | M55: =(L55/X55)*Y55 -> 113.75194 | N55: =L55/$L$3 -> -3.7335812 | O55: 460714 | P55: =(O55/X55)*Y55 -> 96.307925 | Q55: =O55/$O$3 -> -2.0599224 | R55: 393348 | S55: =(R55/X55)*Y55 -> 82.225697 | T55: =R55/$R$3 -> -107.1501 | U55: 387826 | V55: =(U55/X55)*Y55 -> 81.071375 | W55: =U55/$U$3 -> -6.006939 | X55: 478376 | Y55: 100 | Z55: =X55/$X$3 -> 4.2492095
A56: 6.05.02 | B56: Saldo Final de Caixa e Equivalentes | C56: 566929 | D56: =(C56/X56)*Y56 -> 146.18128 | E56: =C56/$C$3 -> 1.0715374 | F56: 591375 | G56: =(F56/X56)*Y56 -> 152.48462 | H56: =F56/$F$3 -> 1.0936523 | I56: 426576 | J56: =(I56/X56)*Y56 -> 109.99159 | K56: =I56/$I$3 -> -1.292776 | L56: 359007 | M56: =(L56/X56)*Y56 -> 92.56909 | N56: =L56/$L$3 -> -2.4632036 | O56: 544162 | P56: =(O56/X56)*Y56 -> 140.31086 | Q56: =O56/$O$3 -> -2.4330311 | R56: 460714 | S56: =(R56/X56)*Y56 -> 118.794 | T56: =R56/$R$3 -> -125.50095 | U56: 393348 | V56: =(U56/X56)*Y56 -> 101.42383 | W56: =U56/$U$3 -> -6.0924678 | X56: 387826 | Y56: 100 | Z56: =X56/$X$3 -> 3.4448925

Sheet BP - AH e AV
A1: Balanço Patrimonial - Análise Vertical
A2: Código da Conta | B2: Descrição da Conta | C2: 2024 | D2: AH24 | E2: AV24 | F2: 2023 | G2: AH23 | H2: AV23 | I2: 2022 | J2: AH22 | K2: AV22 | L2: 2021 | M2: AH21 | N2: AV21 | O2: 2020 | P2: AH20 | Q2: AV20 | R2: 2019 | S2: AH19 | T2: AV19 | U2: 2018 | V2: AH18 | W2: AV18 | X2: 2017 | Y2: AH17 | Z2: AV18
A3: 1 | B3: Ativo Total | C3: 4466987 | D3: =(C3/X3)*Y3 -> 257.63266 | E3: =F3/F3 -> 1 | F3: 4581833 | G3: =(F$3/X3)*$Y3 -> 264.25638 | H3: =$I$3/$I$3 -> 1 | I3: 4199825 | J3: =(I$3/X3)*$Y3 -> 242.22414 | K3: =$L$3/$L$3 -> 1 | L3: 3754136 | M3: =(L$3/X3)*$Y3 -> 216.51911 | N3: =$L$3/$L$3 -> 1 | O3: 2824635 | P3: =(O$3/X3)*$Y3 -> 162.91031 | Q3: =$O$3/$O$3 -> 1 | R3: 1945403 | S3: =(R$3/X3)*$Y3 -> 112.20076 | T3: =$R$3/$R$3 -> 1 | U3: 1789529 | V3: =(U3/X3)*Y3 -> 103.21076 | W3: =$U$3/$U$3 -> 1 | X3: 1733859 | Y3: 100 | Z3: =X3/$X$3 -> 1
A4: 1.01 | B4: Ativo Circulante | C4: 2967747 | D4: =(C4/X4)*Y4 -> 210.27986 | E4: =C4/$C$3 -> 0.66437332 | F4: 3575173 | G4: =(F$3/X4)*$Y4 -> 324.64601 | H4: =$F4/$F$3 -> 0.78029317 | I4: 3430062 | J4: =(I$3/X4)*$Y4 -> 297.57881 | K4: =$I4/$I$3 -> 0.81671546 | L4: 3120040 | M4: =(L$3/X4)*$Y4 -> 265.9995 | N4: =$L4/$L$3 -> 0.83109403 | O4: 2211237 | P4: =(O$3/X4)*$Y4 -> 200.13966 | Q4: =$O4/$O$3 -> 0.78283991 | R4: 1471763 | S4: =(R$3/X4)*$Y4 -> 137.84163 | T4: =$R4/$R$3 -> 0.75653374 | U4: 1418740 | V4: =(U4/X4)*Y4 -> 100.52489 | W4: =$U4/$U$3 -> 0.79280079 | X4: 1411332 | Y4: 100 | Z4: =X4/$X$3 -> 0.81398314
A5: 1.01.01 | B5: Caixa e Equivalentes de Caixa | C5: 566929 | D5: =(C5/X5)*Y5 -> 146.18128 | E5: =C5/$C$3 -> 0.1269153 | F5: 591375 | G5: =(F$3/X5)*$Y5 -> 1181.4146 | H5: =$F5/$F$3 -> 0.12906952 | I5: 426576 | J5: =(I$3/X5)*$Y5 -> 1082.9148 | K5: =$I5/$I$3 -> 0.10156995 | L5: 359007 | M5: =(L$3/X5)*$Y5 -> 967.99493 | N5: =$L5/$L$3 -> 0.095629727 | O5: 544162 | P5: =(O$3/X5)*$Y5 -> 728.32533 | Q5: =$O5/$O$3 -> 0.19264861 | R5: 460714 | S5: =(R$3/X5)*$Y5 -> 501.61748 | T5: =$R5/$R$3 -> 0.23682188 | U5: 393348 | V5: =(U5/X5)*Y5 -> 101.42383 | W5: =$U5/$U$3 -> 0.21980532 | X5: 387826 | Y5: 100 | Z5: =X5/$X$3 -> 0.22367793
A6: 1.01.02 | B6: Aplicações Financeiras | C6: 0 | D6: 0 | E6: =C6/$C$3 -> 0 | F6: 0 | H6: =$F6/$F$3 -> 0 | I6: 0 | K6: =$I6/$I$3 -> 0 | L6: 0 | N6: =$L6/$L$3 -> 0 | O6: 0 | Q6: =$O6/$O$3 -> 0 | R6: 0 | T6: =$R6/$R$3 -> 0 | U6: 0 | W6: =$U6/$U$3 -> 0 | X6: 0 | Y6: 100 | Z6: =X6/$X$3 -> 0
A7: 1.01.03 | B7: Contas a Receber | C7: 860937 | D7: =(C7/X7)*Y7 -> 311.65592 | E7: =C7/$C$3 -> 0.19273327 | F7: 1326360 | G7: =(F$3/X7)*$Y7 -> 1658.6061 | H7: =$F7/$F$3 -> 0.2894824 | I7: 1132483 | J7: =(I$3/X7)*$Y7 -> 1520.3207 | K7: =$I7/$I$3 -> 0.26965004 | L7: 762625 | M7: =(L$3/X7)*$Y7 -> 1358.9829 | N7: =$L7/$L$3 -> 0.20314261 | O7: 698044 | P7: =(O$3/X7)*$Y7 -> 1022.5071 | Q7: =$O7/$O$3 -> 0.24712715 | R7: 258642 | S7: =(R$3/X7)*$Y7 -> 704.22848 | T7: =$R7/$R$3 -> 0.13295034 | U7: 235282 | V7: =(U7/X7)*Y7 -> 85.171188 | W7: =$U7/$U$3 -> 0.13147705 | X7: 276246 | Y7: 100 | Z7: =X7/$X$3 -> 0.15932437
A8: 1.01.04 | B8: Estoques | C8: 1096246 | D8: =(C8/X8)*Y8 -> 216.41887 | E8: =C8/$C$3 -> 0.24541061 | F8: 1256483 | G8: =(F$3/X8)*$Y8 -> 904.53706 | H8: =$F8/$F$3 -> 0.27423151 | I8: 1390723 | J8: =(I$3/X8)*$Y8 -> 829.12175 | K8: =$I8/$I$3 -> 0.33113832 | L8: 1690347 | M8: =(L$3/X8)*$Y8 -> 741.13464 | N8: =$L8/$L$3 -> 0.45026259 | O8: 645750 | P8: =(O$3/X8)*$Y8 -> 557.63426 | Q8: =$O8/$O$3 -> 0.22861361 | R8: 494422 | S8: =(R$3/X8)*$Y8 -> 384.05789 | T8: =$R8/$R$3 -> 0.25414888 | U8: 534726 | V8: =(U8/X8)*Y8 -> 105.56463 | W8: =$U8/$U$3 -> 0.29880823 | X8: 506539 | Y8: 100 | Z8: =X8/$X$3 -> 0.29214544
A9: 1.01.06 | B9: Tributos a Recuperar | C9: 301400 | D9: =(C9/X9)*Y9 -> 212.01761 | E9: =C9/$C$3 -> 0.067472773 | F9: 304370 | G9: =(F$3/X9)*$Y9 -> 3223.0567 | H9: =$F9/$F$3 -> 0.066429745 | I9: 361523 | J9: =(I$3/X9)*$Y9 -> 2954.336 | K9: =$I9/$I$3 -> 0.086080491 | L9: 176025 | M9: =(L$3/X9)*$Y9 -> 2640.8194 | N9: =$L9/$L$3 -> 0.046888285 | O9: 221036 | P9: =(O$3/X9)*$Y9 -> 1986.9687 | Q9: =$O9/$O$3 -> 0.078252942 | R9: 124615 | S9: =(R$3/X9)*$Y9 -> 1368.4794 | T9: =$R9/$R$3 -> 0.064056136 | U9: 129445 | V9: =(U9/X9)*Y9 -> 91.057134 | W9: =$U9/$U$3 -> 0.072334676 | X9: 142158 | Y9: 100 | Z9: =X9/$X$3 -> 0.081989366
A10: 1.01.06.01 | B10: Tributos Correntes a Recuperar | C10: 301400 | E10: =C10/$C$3 -> 0.067472773 | F10: 304370 | H10: =$F10/$F$3 -> 0.066429745 | I10: 361523 | K10: =$I10/$I$3 -> 0.086080491 | L10: 176025 | N10: =$L10/$L$3 -> 0.046888285 | O10: 221036 | Q10: =$O10/$O$3 -> 0.078252942 | R10: 124615 | T10: =$R10/$R$3 -> 0.064056136 | U10: 129445 | W10: =$U10/$U$3 -> 0.072334676 | X10: 0 | Y10: 100 | Z10: =X10/$X$3 -> 0
A11: 1.01.06.01.01 | B11: Tributos a Recuperar | C11: 200109 | E11: =C11/$C$3 -> 0.04479731 | F11: 210811 | H11: =$F11/$F$3 -> 0.046010188 | I11: 309169 | K11: =$I11/$I$3 -> 0.073614734 | L11: 157222 | N11: =$L11/$L$3 -> 0.041879676 | O11: 183356 | Q11: =$O11/$O$3 -> 0.064913166 | R11: 87826 | T11: =$R11/$R$3 -> 0.045145402 | U11: 101769 | W11: =$U11/$U$3 -> 0.056869154 | X11: 0 | Y11: 100 | Z11: =X11/$X$3 -> 0
A12: 1.01.06.01.02 | B12: Imposto de Renda e Contribuição Social a Recuperar | C12: 101291 | E12: =C12/$C$3 -> 0.022675463 | F12: 0 | H12: =$F12/$F$3 -> 0 | I12: 0 | K12: =$I12/$I$3 -> 0 | L12: 0 | N12: =$L12/$L$3 -> 0 | O12: 0 | Q12: =$O12/$O$3 -> 0 | R12: 0 | T12: =$R12/$R$3 -> 0 | U12: 0 | W12: =$U12/$U$3 -> 0 | X12: 0 | Y12: 100 | Z12: =X12/$X$3 -> 0
A13: 1.01.08 | B13: Outros Ativos Cirulantes | C13: 142235 | D13: =(C13/X13)*Y13 -> 144.30872 | E13: =C13/$C$3 -> 0.031841373 | F13: 96585 | G13: =(F$3/X13)*$Y13 -> 4648.6339 | H13: =$F13/$F$3 -> 0.021079991 | I13: 118748 | J13: =(I$3/X13)*$Y13 -> 4261.0564 | K13: =$I13/$I$3 -> 0.028274511 | L13: 132036 | M13: =(L$3/X13)*$Y13 -> 3808.8695 | N13: =$L13/$L$3 -> 0.035170809 | O13: 102245 | P13: =(O$3/X13)*$Y13 -> 2865.8168 | Q13: =$O13/$O$3 -> 0.036197597 | R13: 133370 | S13: =(R$3/X13)*$Y13 -> 1973.766 | T13: =$R13/$R$3 -> 0.068556489 | U13: 125939 | V13: =(U13/X13)*Y13 -> 127.77513 | W13: =$U13/$U$3 -> 0.070375501 | X13: 98563 | Y13: 100 | Z13: =X13/$X$3 -> 0.05684603
A14: 1.01.08.03 | B14: Outros | C14: 142235 | D14: =(C14/X14)*Y14 -> 144.30872 | E14: =C14/$C$3 -> 0.031841373 | F14: 96585 | G14: =(F$3/X14)*$Y14 -> 4648.6339 | H14: =$F14/$F$3 -> 0.021079991 | I14: 118748 | J14: =(I$3/X14)*$Y14 -> 4261.0564 | K14: =$I14/$I$3 -> 0.028274511 | L14: 132036 | M14: =(L$3/X14)*$Y14 -> 3808.8695 | N14: =$L14/$L$3 -> 0.035170809 | O14: 102245 | P14: =(O$3/X14)*$Y14 -> 2865.8168 | Q14: =$O14/$O$3 -> 0.036197597 | R14: 133370 | S14: =(R$3/X14)*$Y14 -> 1973.766 | T14: =$R14/$R$3 -> 0.068556489 | U14: 125939 | V14: =(U14/X14)*Y14 -> 127.77513 | W14: =$U14/$U$3 -> 0.070375501 | X14: 98563 | Y14: 100 | Z14: =X14/$X$3 -> 0.05684603
A15: 1.01.08.03.01 | B15: Partes Relacionadas | C15: 21658 | D15: =(C15/X15)*Y15 -> 174.90107 | E15: =C15/$C$3 -> 0.0048484583 | F15: 12382 | G15: =(F$3/X15)*$Y15 -> 37000.993 | H15: =$F15/$F$3 -> 0.0027024119 | I15: 13997 | J15: =(I$3/X15)*$Y15 -> 33916.054 | K15: =$I15/$I$3 -> 0.0033327579 | L15: 14502 | M15: =(L$3/X15)*$Y15 -> 30316.854 | N15: =$L15/$L$3 -> 0.0038629394 | O15: 20410 | P15: =(O$3/X15)*$Y15 -> 22810.587 | Q15: =$O15/$O$3 -> 0.0072257123 | R15: 20378 | S15: =(R$3/X15)*$Y15 -> 15710.272 | T15: =$R15/$R$3 -> 0.01047495 | U15: 21103 | V15: =(U15/X15)*Y15 -> 170.41912 | W15: =$U15/$U$3 -> 0.011792488 | X15: 12383 | Y15: 100 | Z15: =X15/$X$3 -> 0.0071418726
A16: 1.01.08.03.02 | B16: Outros Créditos | C16: 20037 | D16: =(C16/X16)*Y16 -> 84.359212 | E16: =C16/$C$3 -> 0.0044855738 | F16: 30680 | G16: =(F$3/X16)*$Y16 -> 19290.304 | H16: =$F16/$F$3 -> 0.0066960101 | I16: 43088 | J16: =(I$3/X16)*$Y16 -> 17681.985 | K16: =$I16/$I$3 -> 0.010259475 | L16: 56823 | M16: =(L$3/X16)*$Y16 -> 15805.557 | N16: =$L16/$L$3 -> 0.015136106 | O16: 28608 | P16: =(O$3/X16)*$Y16 -> 11892.199 | Q16: =$O16/$O$3 -> 0.010128034 | R16: 52457 | S16: =(R$3/X16)*$Y16 -> 8190.4808 | T16: =$R16/$R$3 -> 0.026964593 | U16: 36349 | V16: =(U16/X16)*Y16 -> 153.03553 | W16: =$U16/$U$3 -> 0.020312049 | X16: 23752 | Y16: 100 | Z16: =X16/$X$3 -> 0.013698922
A17: 1.02 | B17: Ativos Não Circulante | C17: 1499240 | D17: =(C17/X17)*Y17 -> 464.8417 | E17: =C17/$C$3 -> 0.33562668 | F17: 1006660 | G17: =(F$3/X17)*$Y17 -> 1420.6045 | H17: =$F17/$F$3 -> 0.21970683 | I17: 769763 | J17: =(I$3/X17)*$Y17 -> 1302.1623 | K17: =$I17/$I$3 -> 0.18328454 | L17: 634096 | M17: =(L$3/X17)*$Y17 -> 1163.9757 | N17: =$L17/$L$3 -> 0.16890597 | O17: 613398 | P17: =(O$3/X17)*$Y17 -> 875.78249 | Q17: =$O17/$O$3 -> 0.21716009 | R17: 473640 | S17: =(R$3/X17)*$Y17 -> 603.17524 | T17: =$R17/$R$3 -> 0.24346626 | U17: 370789 | V17: =(U17/X17)*Y17 -> 114.96371 | W17: =$U17/$U$3 -> 0.20719921 | X17: 322527 | Y17: 100 | Z17: =X17/$X$3 -> 0.18601686
A18: 1.02.01 | B18: Ativo Realizável a Longo Prazo | C18: 765802 | D18: =(C18/X18)*Y18 -> 511.69109 | E18: =C18/$C$3 -> 0.17143591 | F18: 502346 | G18: =(F$3/X18)*$Y18 -> 3061.4743 | H18: =$F18/$F$3 -> 0.10963865 | I18: 383872 | J18: =(I$3/X18)*$Y18 -> 2806.2254 | K18: =$I18/$I$3 -> 0.091401904 | L18: 339982 | M18: =(L$3/X18)*$Y18 -> 2508.4264 | N18: =$L18/$L$3 -> 0.090561983 | O18: 337585 | P18: =(O$3/X18)*$Y18 -> 1887.3554 | Q18: =$O18/$O$3 -> 0.11951456 | R18: 206351 | S18: =(R$3/X18)*$Y18 -> 1299.873 | T18: =$R18/$R$3 -> 0.10607108 | U18: 192540 | V18: =(U18/X18)*Y18 -> 128.65075 | W18: =$U18/$U$3 -> 0.10759256 | X18: 149661 | Y18: 100 | Z18: =X18/$X$3 -> 0.086316707
A19: 1.02.01.01 | B19: Aplicações Financeiras Avaliadas a Valor Justo através do Resultado | C19: 0 | E19: =C19/$C$3 -> 0 | F19: 0 | H19: =$F19/$F$3 -> 0 | I19: 0 | K19: =$I19/$I$3 -> 0 | L19: 0 | N19: =$L19/$L$3 -> 0 | O19: 0 | Q19: =$O19/$O$3 -> 0 | R19: 0 | T19: =$R19/$R$3 -> 0 | U19: 0 | W19: =$U19/$U$3 -> 0 | X19: 0 | Y19: 100 | Z19: =X19/$X$3 -> 0
A20: 1.02.01.04 | B20: Contas a Receber | C20: 185092 | D20: =(C20/X20)*Y20 -> 70645.802 | E20: =C20/$C$3 -> 0.041435536 | F20: 31972 | G20: =(F$3/X20)*$Y20 -> 1748791.2 | H20: =$F20/$F$3 -> 0.0069779933 | I20: 13573 | J20: =(I$3/X20)*$Y20 -> 1602986.6 | K20: =$I20/$I$3 -> 0.0032318013 | L20: 0 | M20: =(L$3/X20)*$Y20 -> 1432876.3 | N20: =$L20/$L$3 -> 0 | O20: 0 | P20: =(O$3/X20)*$Y20 -> 1078105 | Q20: =$O20/$O$3 -> 0 | R20: 70 | S20: =(R$3/X20)*$Y20 -> 742520.23 | T20: =$R20/$R$3 -> 3.5982262e-05 | U20: 28 | V20: =(U20/X20)*Y20 -> 10.687023 | W20: =$U20/$U$3 -> 1.5646575e-05 | X20: 262 | Y20: 100 | Z20: =X20/$X$3 -> 0.00015110802
A21: 1.02.01.07 | B21: Tributos Diferidos | C21: 1190 | D21: =(C21/X21)*Y21 -> 1.7832791 | E21: =C21/$C$3 -> 0.00026639881 | F21: 2743 | G21: =(F$3/X21)*$Y21 -> 6866.1237 | H21: =$F21/$F$3 -> 0.0005986687 | I21: 1712 | J21: =(I$3/X21)*$Y21 -> 6293.6641 | K21: =$I21/$I$3 -> 0.00040763603 | L21: 624 | M21: =(L$3/X21)*$Y21 -> 5625.7751 | N21: =$L21/$L$3 -> 0.00016621667 | O21: 599 | P21: =(O$3/X21)*$Y21 -> 4232.8678 | Q21: =$O21/$O$3 -> 0.0002120628 | R21: 60296 | S21: =(R$3/X21)*$Y21 -> 2915.2912 | T21: =$R21/$R$3 -> 0.030994092 | U21: 64744 | V21: =(U21/X21)*Y21 -> 97.022373 | W21: =$U21/$U$3 -> 0.036179352 | X21: 66731 | Y21: 100 | Z21: =X21/$X$3 -> 0.038486982
A22: 1.02.01.10 | B22: Outros Ativos Não Circulantes | C22: 579520 | D22: =(C22/X22)*Y22 -> 701.02095 | E22: =C22/$C$3 -> 0.12973398 | F22: 467631 | G22: =(F$3/X22)*$Y22 -> 5542.4505 | H22: =$F22/$F$3 -> 0.10206199 | I22: 368587 | J22: =(I$3/X22)*$Y22 -> 5080.3515 | K22: =$I22/$I$3 -> 0.087762466 | L22: 339358 | M22: =(L$3/X22)*$Y22 -> 4541.2203 | N22: =$L22/$L$3 -> 0.090395766 | O22: 336986 | P22: =(O$3/X22)*$Y22 -> 3416.8421 | Q22: =$O22/$O$3 -> 0.11930249 | R22: 145985 | S22: =(R$3/X22)*$Y22 -> 2353.2721 | T22: =$R22/$R$3 -> 0.075041007 | U22: 127768 | V22: =(U22/X22)*Y22 -> 154.55557 | W22: =$U22/$U$3 -> 0.071397558 | X22: 82668 | Y22: 100 | Z22: =X22/$X$3 -> 0.047678617
A23: 1.02.01.10.03 | B23: Tributos a Recuperar | C23: 501080 | D23: =(C23/X23)*Y23 -> 662.927 | E23: =C23/$C$3 -> 0.11217404 | F23: 457924 | G23: =(F$3/X23)*$Y23 -> 6061.7482 | H23: =$F23/$F$3 -> 0.099943407 | I23: 298614 | J23: =(I$3/X23)*$Y23 -> 5556.353 | K23: =$I23/$I$3 -> 0.071101534 | L23: 275722 | M23: =(L$3/X23)*$Y23 -> 4966.7081 | N23: =$L23/$L$3 -> 0.073444862 | O23: 275415 | P23: =(O$3/X23)*$Y23 -> 3736.9817 | Q23: =$O23/$O$3 -> 0.097504633 | R23: 86096 | S23: =(R$3/X23)*$Y23 -> 2573.761 | T23: =$R23/$R$3 -> 0.044256126 | U23: 75507 | V23: =(U23/X23)*Y23 -> 99.895483 | W23: =$U23/$U$3 -> 0.042193784 | X23: 75586 | Y23: 100 | Z23: =X23/$X$3 -> 0.043594087
A24: 1.02.01.10.04 | B24: Outros Ativos | C24: 2641 | D24: =(C24/X24)*Y24 -> 37.291726 | E24: =C24/$C$3 -> 0.00059122626 | F24: 9707 | G24: =(F$3/X24)*$Y24 -> 64696.879 | H24: =$F24/$F$3 -> 0.0021185844 | I24: 69973 | J24: =(I$3/X24)*$Y24 -> 59302.81 | K24: =$I24/$I$3 -> 0.016660932 | L24: 63636 | M24: =(L$3/X24)*$Y24 -> 53009.545 | N24: =$L24/$L$3 -> 0.016950904 | O24: 61571 | P24: =(O$3/X24)*$Y24 -> 39884.708 | Q24: =$O24/$O$3 -> 0.021797861 | R24: 59889 | S24: =(R$3/X24)*$Y24 -> 27469.684 | T24: =$R24/$R$3 -> 0.030784881 | U24: 52261 | V24: =(U24/X24)*Y24 -> 737.94126 | W24: =$U24/$U$3 -> 0.029203774 | X24: 7082 | Y24: 100 | Z24: =X24/$X$3 -> 0.0040845305
A25: 1.02.01.10.05 | B25: Depósitos Judiciais | C25: 35760 | E25: =C25/$C$3 -> 0.008005396 | F25: 0 | H25: =$F25/$F$3 -> 0 | I25: 0 | K25: =$I25/$I$3 -> 0 | L25: 0 | N25: =$L25/$L$3 -> 0 | O25: 0 | Q25: =$O25/$O$3 -> 0 | R25: 0 | T25: =$R25/$R$3 -> 0 | U25: 0 | W25: =$U25/$U$3 -> 0 | X25: 0 | Y25: 100 | Z25: =X25/$X$3 -> 0
B26: ATIVO FIXO | C26: =SUM(C27,C30,C33) -> 733438 | D26: =(C26/X26)*Y26 -> 424.28124 | E26: =C26/$C$3 -> 0.16419076 | F26: =SUM(F27,F30,F33) -> 504314 | G26: =(F$3/X26)*$Y26 -> 2650.5114 | H26: =$F26/$F$3 -> 0.11006818 | I26: =SUM(I27,I30,I33) -> 385891 | J26: =(I$3/X26)*$Y26 -> 2429.5263 | K26: =$I26/$I$3 -> 0.091882638 | L26: =SUM(L27,L30,L33) -> 294114 | M26: =(L$3/X26)*$Y26 -> 2171.7029 | N26: =$L26/$L$3 -> 0.078343992 | O26: =SUM(O27,O30,O33) -> 275813 | P26: =(O$3/X26)*$Y26 -> 1634.0026 | Q26: =$O26/$O$3 -> 0.097645537 | R26: =SUM(R27,R30,R33) -> 267289 | S26: =(R$3/X26)*$Y26 -> 1125.3821 | T26: =$R26/$R$3 -> 0.13739518 | U26: =SUM(U27,U30,U33) -> 178249 | V26: =(U26/X26)*Y26 -> 103.11397 | W26: =$U26/$U$3 -> 0.099606656 | X26: =SUM(X27,X30,X33) -> 172866 | Y26: 100 | Z26: =X26/$X$3 -> 0.099700149
A27: 1.02.02 | B27: Investimentos | C27: 256770 | D27: =(C27/X27)*Y27 -> 479.01276 | E27: =C27/$C$3 -> 0.057481699 | F27: 226969 | G27: =(F$3/X27)*$Y27 -> 8547.558 | H27: =$F27/$F$3 -> 0.049536725 | I27: 164127 | J27: =(I$3/X27)*$Y27 -> 7834.9097 | K27: =$I27/$I$3 -> 0.039079485 | L27: 114226 | M27: =(L$3/X27)*$Y27 -> 7003.4624 | N27: =$L27/$L$3 -> 0.030426708 | O27: 91692 | P27: =(O$3/X27)*$Y27 -> 5269.4482 | Q27: =$O27/$O$3 -> 0.032461539 | R27: 73433 | S27: =(R$3/X27)*$Y27 -> 3629.2124 | T27: =$R27/$R$3 -> 0.037746935 | U27: 48087 | V27: =(U27/X27)*Y27 -> 89.707858 | W27: =$U27/$U$3 -> 0.026871316 | X27: 53604 | Y27: 100 | Z27: =X27/$X$3 -> 0.030916009
A28: 1.02.02.01 | B28: Participações Societárias | C28: 256770 | D28: =(C28/X28)*Y28 -> 479.01276 | E28: =C28/$C$3 -> 0.057481699 | F28: 226969 | G28: =(F$3/X28)*$Y28 -> 8547.558 | H28: =$F28/$F$3 -> 0.049536725 | I28: 164127 | J28: =(I$3/X28)*$Y28 -> 7834.9097 | K28: =$I28/$I$3 -> 0.039079485 | L28: 114226 | M28: =(L$3/X28)*$Y28 -> 7003.4624 | N28: =$L28/$L$3 -> 0.030426708 | O28: 91692 | P28: =(O$3/X28)*$Y28 -> 5269.4482 | Q28: =$O28/$O$3 -> 0.032461539 | R28: 73433 | S28: =(R$3/X28)*$Y28 -> 3629.2124 | T28: =$R28/$R$3 -> 0.037746935 | U28: 48087 | V28: =(U28/X28)*Y28 -> 89.707858 | W28: =$U28/$U$3 -> 0.026871316 | X28: 53604 | Y28: 100 | Z28: =X28/$X$3 -> 0.030916009
A29: 1.02.02.01.01 | B29: Participações em Coligadas | C29: 136724 | E29: =C29/$C$3 -> 0.030607656 | F29: 226969 | H29: =$F29/$F$3 -> 0.049536725 | I29: 131714 | K29: =$I29/$I$3 -> 0.031361783 | L29: 76284 | N29: =$L29/$L$3 -> 0.020319988 | O29: 53154 | Q29: =$O29/$O$3 -> 0.018818007 | R29: 27317 | T29: =$R29/$R$3 -> 0.014041821 | U29: 8303 | W29: =$U29/$U$3 -> 0.0046397683 | X29: 0 | Y29: 100 | Z29: =X29/$X$3 -> 0
A30: 1.02.03 | B30: Imobilizado | C30: 155481 | D30: =(C30/X30)*Y30 -> 272.33413 | E30: =C30/$C$3 -> 0.034806683 | F30: 146818 | G30: =(F$3/X30)*$Y30 -> 8025.3503 | H30: =$F30/$F$3 -> 0.032043507 | I30: 110987 | J30: =(I$3/X30)*$Y30 -> 7356.2408 | K30: =$I30/$I$3 -> 0.026426577 | L30: 92894 | M30: =(L$3/X30)*$Y30 -> 6575.5903 | N30: =$L30/$L$3 -> 0.024744442 | O30: 86298 | P30: =(O$3/X30)*$Y30 -> 4947.5145 | Q30: =$O30/$O$3 -> 0.030551912 | R30: 88718 | S30: =(R$3/X30)*$Y30 -> 3407.4879 | T30: =$R30/$R$3 -> 0.045603919 | U30: 50746 | V30: =(U30/X30)*Y30 -> 88.884607 | W30: =$U30/$U$3 -> 0.028357182 | X30: 57092 | Y30: 100 | Z30: =X30/$X$3 -> 0.032927706
A31: 1.02.03.01 | B31: Imobilizado em Operação | C31: 125036 | E31: =C31/$C$3 -> 0.027991127 | F31: 116974 | H31: =$F31/$F$3 -> 0.025529957 | I31: 84915 | K31: =$I31/$I$3 -> 0.0202187 | L31: 60279 | N31: =$L31/$L$3 -> 0.016056691 | O31: 47700 | Q31: =$O31/$O$3 -> 0.016887138 | R31: 0 | T31: =$R31/$R$3 -> 0 | U31: 0 | W31: =$U31/$U$3 -> 0 | X31: 0 | Y31: 100 | Z31: =X31/$X$3 -> 0
A32: 1.02.03.02 | B32: Direito de Uso em Arrendamento | C32: 30445 | E32: =C32/$C$3 -> 0.006815556 | F32: 29844 | H32: =$F32/$F$3 -> 0.0065135504 | I32: 26072 | K32: =$I32/$I$3 -> 0.0062078777 | L32: 32615 | N32: =$L32/$L$3 -> 0.0086877513 | O32: 38598 | Q32: =$O32/$O$3 -> 0.013664774 | R32: 41694 | T32: =$R32/$R$3 -> 0.021432063 | U32: 0 | W32: =$U32/$U$3 -> 0 | X32: 0 | Y32: 100 | Z32: =X32/$X$3 -> 0
A33: 1.02.04 | B33: Intangível | C33: 321187 | D33: =(C33/X33)*Y33 -> 516.62699 | E33: =C33/$C$3 -> 0.071902381 | F33: 130527 | G33: =(F$3/X33)*$Y33 -> 7369.8456 | H33: =$F33/$F$3 -> 0.028487944 | I33: 110777 | J33: =(I$3/X33)*$Y33 -> 6755.3885 | K33: =$I33/$I$3 -> 0.026376575 | L33: 86994 | M33: =(L$3/X33)*$Y33 -> 6038.5009 | N33: =$L33/$L$3 -> 0.023172842 | O33: 97823 | P33: =(O$3/X33)*$Y33 -> 4543.4052 | Q33: =$O33/$O$3 -> 0.034632085 | R33: 105138 | S33: =(R$3/X33)*$Y33 -> 3129.1668 | T33: =$R33/$R$3 -> 0.054044329 | U33: 79416 | V33: =(U33/X33)*Y33 -> 127.74007 | W33: =$U33/$U$3 -> 0.044378158 | X33: 62170 | Y33: 100 | Z33: =X33/$X$3 -> 0.035856434
A34: 2 | B34: Passivo Total | C34: 4466987 | D34: =(C34/X34)*Y34 -> 257.63266 | E34: =C34/$C$3 -> 1 | F34: 4581833 | G34: =(F$3/X34)*$Y34 -> 264.25638 | H34: =$F34/$F$3 -> 1 | I34: 4199825 | J34: =(I$3/X34)*$Y34 -> 242.22414 | K34: =$I34/$I$3 -> 1 | L34: 3754136 | M34: =(L$3/X34)*$Y34 -> 216.51911 | N34: =$L$34/$L$34 -> 1 | O34: 2824635 | P34: =(O$3/X34)*$Y34 -> 162.91031 | Q34: =$O$34/$O$34 -> 1 | R34: 1945403 | S34: =(R$3/X34)*$Y34 -> 112.20076 | T34: =$R$34/$R$34 -> 1 | U34: 1789529 | V34: =(U34/X34)*Y34 -> 103.21076 | W34: =$U34/$U$34 -> 1 | X34: 1733859 | Y34: 100 | Z34: =X34/$X$3 -> 1
A35: 2.01 | B35: Passivo Circulante | C35: 1503102 | D35: =(C35/X35)*Y35 -> 137.8004 | E35: =C35/$C$3 -> 0.33649124 | F35: 1934265 | G35: =(F$3/X35)*$Y35 -> 420.05029 | H35: =$F35/$F$3 -> 0.42215965 | I35: 1773213 | J35: =(I$3/X35)*$Y35 -> 385.02881 | K35: =$I$3/$I$3 -> 1 | L35: 1937651 | M35: =(L$3/X35)*$Y35 -> 344.16923 | N35: =$L35/$L$34 -> 0.51613767 | O35: 1370932 | P35: =(O$3/X35)*$Y35 -> 258.95504 | Q35: =$O35/$O$34 -> 0.48534837 | R35: 1178943 | S35: =(R$3/X35)*$Y35 -> 178.34939 | T35: =$R35/$R$34 -> 0.60601479 | U35: 1111886 | V35: =(U35/X35)*Y35 -> 101.93476 | W35: =$U35/$U$34 -> 0.62132885 | X35: 1090782 | Y35: 100 | Z35: =X35/$X$3 -> 0.62910652
A36: 2.01.01 | B36: Obrigações Sociais e Trabalhistas | C36: 105953 | D36: =(C36/X36)*Y36 -> 526.55303 | E36: =C36/$C$3 -> 0.02371912 | F36: 80891 | H36: =$F36/$F$3 -> 0.017654725 | I36: 42753 | K36: =$I36/$I$35 -> 0.024110471 | L36: 38387 | N36: =$L36/$L$34 -> 0.010225256 | O36: 33263 | Q36: =$O36/$O$34 -> 0.011776035 | R36: 20281 | T36: =$R36/$R$34 -> 0.010425089 | U36: 18205 | W36: =$U36/$U$34 -> 0.010173068 | X36: 20122 | Y36: 100 | Z36: =X36/$X$3 -> 0.011605327
A37: 2.01.02 | B37: Fornecedores | C37: 658247 | D37: =(C37/X37)*Y37 -> 135.40249 | E37: =C37/$C$3 -> 0.14735816 | F37: 832121 | G37: =(F$3/X37)*$Y37 -> 942.49055 | H37: =$F37/$F$3 -> 0.18161312 | I37: 594245 | J37: =(I$3/X37)*$Y37 -> 863.91088 | K37: =$I37/$I$35 -> 0.3351233 | L37: 1186214 | M37: =(L$3/X37)*$Y37 -> 772.23192 | N37: =$L37/$L$34 -> 0.31597523 | O37: 562210 | P37: =(O$3/X37)*$Y37 -> 581.03205 | Q37: =$O37/$O$34 -> 0.19903811 | R37: 383964 | S37: =(R$3/X37)*$Y37 -> 400.17258 | T37: =$R37/$R$34 -> 0.1973699 | U37: 449260 | V37: =(U37/X37)*Y37 -> 92.413518 | W37: =$U37/$U$34 -> 0.2510493 | X37: 486141 | Y37: 100 | Z37: =X37/$X$3 -> 0.28038093
A38: 2.01.02.01 | B38: Fornecedores Nacionais | C38: 105953 | E38: =C38/$C$3 -> 0.02371912 | F38: 191211 | H38: =$F38/$F$3 -> 0.041732425 | I38: 290682 | K38: =$I38/$I$35 -> 0.16392954 | L38: 280741 | O38: 207963 | R38: 196025 | U38: 280194 | W38: =$U38/$U$34 -> 0.15657416 | X38: 0 | Y38: 100 | Z38: =X38/$X$3 -> 0
A39: 2.01.02.01.01 | B39: Fornecedores | C39: 167077 | E39: =C39/$C$3 -> 0.037402616 | F39: 0 | H39: =$F39/$F$3 -> 0 | I39: 0 | K39: =$I39/$I$35 -> 0 | L39: 0 | O39: 0 | R39: 0 | U39: 0 | W39: =$U39/$U$34 -> 0 | X39: 0 | Y39: 100 | Z39: =X39/$X$3 -> 0
A40: 2.01.02.01.02 | B40: Fornecedores - Convênio | C40: 491170 | E40: =C40/$C$3 -> 0.10995555 | F40: 0 | H40: =$F40/$F$3 -> 0 | I40: 0 | K40: =$I40/$I$35 -> 0 | L40: 0 | O40: 0 | R40: 0 | U40: 0 | W40: =$U40/$U$34 -> 0 | X40: 0 | Y40: 100 | Z40: =X40/$X$3 -> 0
A41: 2.01.03 | B41: Obrigações Fiscais | C41: 102656 | D41: =(C41/X41)*Y41 -> 285.39338 | E41: =C41/$C$3 -> 0.022981038 | F41: 73369 | G41: =(F$3/X41)*$Y41 -> 12737.929 | H41: =$F41/$F$3 -> 0.016013024 | I41: 192806 | J41: =(I$3/X41)*$Y41 -> 11675.91 | K41: =$I41/$I$35 -> 0.10873257 | L41: 52814 | M41: =(L$3/X41)*$Y41 -> 10436.853 | N41: =$L41/$L$34 -> 0.014068217 | O41: 32037 | P41: =(O$3/X41)*$Y41 -> 7852.7523 | Q41: =$O41/$O$34 -> 0.011341996 | R41: 24035 | S41: =(R$3/X41)*$Y41 -> 5408.4042 | T41: =$R41/$R$34 -> 0.012354767 | U41: 21563 | V41: =(U41/X41)*Y41 -> 59.947178 | W41: =$U41/$U$34 -> 0.012049539 | X41: 35970 | Y41: 100 | Z41: =X41/$X$3 -> 0.020745632
A42: 2.01.03.01 | B42: Obrigações Fiscais Federais | C42: 100299 | E42: =C42/$C$3 -> 0.02245339 | F42: 60165 | H42: =$F42/$F$3 -> 0.013131208 | I42: 180197 | K42: =$I42/$I$35 -> 0.10162175 | L42: 40831 | N42: =$L42/$L$34 -> 0.010876271 | O42: 27643 | Q42: =$O42/$O$34 -> 0.0097863972 | R42: 19004 | T42: =$R42/$R$34 -> 0.00976867 | U42: 20242 | W42: =$U42/$U$34 -> 0.011311356 | X42: 0 | Y42: 100 | Z42: =X42/$X$3 -> 0
A43: 2.01.03.01.02 | B43: Tributos a Recolher | C43: 93811 | E43: =C43/$C$3 -> 0.021000957 | F43: 0 | H43: =$F43/$F$3 -> 0 | I43: 0 | K43: =$I43/$I$35 -> 0 | L43: 0 | N43: =$L43/$L$34 -> 0 | O43: 0 | Q43: =$O43/$O$34 -> 0 | R43: 0 | T43: =$R43/$R$34 -> 0 | U43: 0 | W43: =$U43/$U$34 -> 0 | X43: 0 | Y43: 100 | Z43: =X43/$X$3 -> 0
A44: 2.01.04 | B44: Empréstimos e Financiamentos | C44: 341080 | D44: =(C44/X44)*Y44 -> 77.570189 | E44: =C44/$C$3 -> 0.076355718 | F44: 694839 | H44: =$F44/$F$3 -> 0.15165088 | I44: 655704 | K44: =$I44/$I$35 -> 0.36978299 | L44: 400196 | N44: =$L44/$L$34 -> 0.10660136 | O44: 461373 | Q44: =$O44/$O$34 -> 0.16333898 | R44: 601728 | T44: =$R44/$R$34 -> 0.30930763 | U44: 519434 | W44: =$U44/$U$34 -> 0.29026297 | X44: 439705 | Y44: 100 | Z44: =X44/$X$3 -> 0.25359905
A45: 2.01.05 | B45: Outras Obrigações | C45: 156265 | D45: =(C45/X45)*Y45 -> 821.23712 | E45: =C45/$C$3 -> 0.034982193 | F45: 123124 | G45: =(F$3/X45)*$Y45 -> 24079.425 | H45: =$F45/$F$3 -> 0.026872215 | I45: 118263 | J45: =(I$3/X45)*$Y45 -> 22071.815 | K45: =$I45/$I$35 -> 0.066694187 | L45: 95975 | M45: =(L$3/X45)*$Y45 -> 19729.535 | N45: =$L45/$L$34 -> 0.025565137 | O45: 135275 | P45: =(O$3/X45)*$Y45 -> 14844.624 | Q45: =$O45/$O$34 -> 0.047891143 | R45: 57980 | S45: =(R$3/X45)*$Y45 -> 10223.896 | T45: =$R45/$R$34 -> 0.029803593 | U45: 24220 | V45: =(U45/X45)*Y45 -> 127.2861 | W45: =$U45/$U$34 -> 0.013534288 | X45: 19028 | Y45: 100 | Z45: =X45/$X$3 -> 0.010974364
A46: 2.01.05.01 | B46: Passivos com Partes Relacionadas | C46: 1205 | D46: =(C46/X46)*Y46 -> 31.594127 | E46: =C46/$C$3 -> 0.00026975677 | F46: 2949 | G46: =(F$3/X46)*$Y46 -> 120131.96 | H46: =$F46/$F$3 -> 0.00064362887 | I46: 1140 | J46: =(I$3/X46)*$Y46 -> 110116.02 | K46: =$I46/$I$35 -> 0.00064290077 | L46: 745 | M46: =(L$3/X46)*$Y46 -> 98430.414 | N46: =$L46/$L$34 -> 0.00019844779 | O46: 1213 | P46: =(O$3/X46)*$Y46 -> 74059.649 | Q46: =$O46/$O$34 -> 0.00042943602 | R46: 763 | S46: =(R$3/X46)*$Y46 -> 51006.896 | T46: =$R46/$R$34 -> 0.00039220665 | U46: 755 | V46: =(U46/X46)*Y46 -> 19.79549 | W46: =$U46/$U$34 -> 0.00042189872 | X46: 3814 | Y46: 100 | Z46: =X46/$X$3 -> 0.0021997175
A47: 2.01.05.02 | B47: Outros | C47: 155060 | D47: =(C47/X47)*Y47 -> 1019.1928 | E47: =C47/$C$3 -> 0.034712436 | F47: 120175 | G47: =(F$3/X47)*$Y47 -> 30115.9 | H47: =$F47/$F$3 -> 0.026228586 | I47: 117123 | J47: =(I$3/X47)*$Y47 -> 27605.002 | K47: =$I47/$I$35 -> 0.066051287 | L47: 95230 | M47: =(L$3/X47)*$Y47 -> 24675.536 | N47: =$L47/$L$34 -> 0.025366689 | O47: 134062 | P47: =(O$3/X47)*$Y47 -> 18566.025 | Q47: =$O47/$O$34 -> 0.047461707 | R47: 57217 | S47: =(R$3/X47)*$Y47 -> 12786.927 | T47: =$R47/$R$34 -> 0.029411387 | U47: 23465 | V47: =(U47/X47)*Y47 -> 154.23294 | W47: =$U47/$U$34 -> 0.013112389 | X47: 15214 | Y47: 100 | Z47: =X47/$X$3 -> 0.0087746466
A48: 2.01.05.02.01 | B48: Dividendos e JCP a Pagar | C48: 0 | E48: =C48/$C$3 -> 0 | F48: 0 | H48: =$F48/$F$3 -> 0 | I48: 0 | K48: =$I48/$I$35 -> 0 | L48: 0 | N48: =$L48/$L$34 -> 0 | O48: 0 | Q48: =$O48/$O$34 -> 0 | R48: 0 | T48: =$R48/$R$34 -> 0 | U48: 0 | W48: =$U48/$U$34 -> 0 | X48: 0 | Y48: 100 | Z48: =X48/$X$3 -> 0
A49: 2.01.05.02.04 | B49: Receitas Diferidas | C49: 21404 | D49: =(C49/X49)*Y49 -> 211.60652 | E49: =C49/$C$3 -> 0.0047915967 | F49: 11619 | G49: =(F$3/X49)*$Y49 -> 45297.41 | H49: =$F49/$F$3 -> 0.0025358847 | I49: 9668 | J49: =(I$3/X49)*$Y49 -> 41520.761 | K49: =$I49/$I$35 -> 0.0054522497 | L49: 5753 | M49: =(L$3/X49)*$Y49 -> 37114.543 | N49: =$L49/$L$34 -> 0.0015324432 | O49: 7492 | P49: =(O$3/X49)*$Y49 -> 27925.21 | Q49: =$O49/$O$34 -> 0.0026523781 | R49: 8344 | S49: =(R$3/X49)*$Y49 -> 19232.852 | T49: =$R49/$R$34 -> 0.0042890856 | U49: 9346 | V49: =(U49/X49)*Y49 -> 92.39743 | W49: =$U49/$U$34 -> 0.0052226033 | X49: 10115 | Y49: 100 | Z49: =X49/$X$3 -> 0.0058338077
A50: 2.01.05.02.05 | B50: Outras Contas a Pagar | C50: 81978 | D50: =(C50/X50)*Y50 -> 1608.6735 | E50: =C50/$C$3 -> 0.018351967 | F50: 22024 | G50: =(F$3/X50)*$Y50 -> 89910.381 | H50: =$F50/$F$3 -> 0.0048068099 | I50: 23967 | J50: =(I$3/X50)*$Y50 -> 82414.148 | K50: =$I50/$I$35 -> 0.013516143 | L50: 32751 | M50: =(L$3/X50)*$Y50 -> 73668.289 | N50: =$L50/$L$34 -> 0.008723978 | O50: 59942 | P50: =(O$3/X50)*$Y50 -> 55428.473 | Q50: =$O50/$O$34 -> 0.021221149 | R50: 22309 | S50: =(R$3/X50)*$Y50 -> 38175.098 | T50: =$R50/$R$34 -> 0.011467547 | U50: 13874 | V50: =(U50/X50)*Y50 -> 272.25275 | W50: =$U50/$U$34 -> 0.007752878 | X50: 5096 | Y50: 100 | Z50: =X50/$X$3 -> 0.0029391087
A51: 2.01.05.02.06 | B51: Instrumento Financeiro Deritivos | C51: 81978 | E51: =C51/$C$3 -> 0.018351967 | F51: 17682 | H51: =$F51/$F$3 -> 0.0038591542 | I51: 0 | K51: =$I51/$I$35 -> 0 | L51: 0 | N51: =$L51/$L$34 -> 0 | O51: 8727 | Q51: =$O51/$O$34 -> 0.0030896027 | R51: 14584 | T51: =$R51/$R$34 -> 0.0074966472 | U51: 242 | W51: =$U51/$U$34 -> 0.00013523111 | X51: 0 | Y51: 100 | Z51: =X51/$X$3 -> 0
A52: 2.01.05.02.07 | B52: Parceiros e outros depósitos | C52: 12455 | E52: =C52/$C$3 -> 0.0027882329 | F52: 0 | H52: =$F52/$F$3 -> 0 | I52: 0 | K52: =$I52/$I$35 -> 0 | L52: 0 | N52: =$L52/$L$34 -> 0 | O52: 0 | Q52: =$O52/$O$34 -> 0 | R52: 0 | T52: =$R52/$R$34 -> 0 | U52: 0 | W52: =$U52/$U$34 -> 0 | X52: 0 | Y52: 100 | Z52: =X52/$X$3 -> 0
A53: 2.02 | B53: Passivo Não Circulante | C53: 1317764 | D53: =(C53/X53)*Y53 -> 963.96834 | E53: =C53/$C$3 -> 0.29500063 | F53: 1051141 | G53: =(F$3/X53)*$Y53 -> 3351.6942 | H53: =$F53/$F$3 -> 0.22941495 | I53: 1020292 | J53: =(I$3/X53)*$Y53 -> 3072.2484 | K53: =$I53/$I$35 -> 0.57539168 | L53: 634824 | M53: =(L$3/X53)*$Y53 -> 2746.2188 | N53: =$L53/$L$34 -> 0.16909989 | O53: 420565 | P53: =(O$3/X53)*$Y53 -> 2066.2719 | Q53: =$O53/$O$34 -> 0.1488918 | R53: 231568 | S53: =(R$3/X53)*$Y53 -> 1423.0977 | T53: =$R53/$R$34 -> 0.11903343 | U53: 167735 | V53: =(U53/X53)*Y53 -> 122.7012 | W53: =$U53/$U$34 -> 0.093731367 | X53: 136702 | Y53: 100 | Z53: =X53/$X$3 -> 0.078842628
A54: 2.02.01 | B54: Empréstimos e Financiamentos | C54: 941744 | D54: =(C54/X54)*Y54 -> 1028.0824 | E54: =C54/$C$3 -> 0.21082309 | F54: 690894 | G54: =(F$3/X54)*$Y54 -> 5001.8919 | H54: =$F54/$F$3 -> 0.15078987 | I54: 876281 | J54: =(I$3/X54)*$Y54 -> 4584.8617 | K54: =$I54/$I$35 -> 0.49417695 | L54: 500406 | M54: =(L$3/X54)*$Y54 -> 4098.3123 | N54: =$L54/$L$34 -> 0.13329458 | O54: 301561 | P54: =(O$3/X54)*$Y54 -> 3083.5953 | Q54: =$O54/$O$34 -> 0.10676105 | R54: 110396 | S54: =(R$3/X54)*$Y54 -> 2123.756 | T54: =$R54/$R$34 -> 0.056747111 | U54: 90801 | V54: =(U54/X54)*Y54 -> 99.125565 | W54: =$U54/$U$34 -> 0.050740167 | X54: 91602 | Y54: 100 | Z54: =X54/$X$3 -> 0.052831286
A55: 2.02.02 | B55: Outras Obrigações | C55: 72020 | D55: =(C55/X55)*Y55 -> 2579.5129 | E55: =C55/$C$3 -> 0.016122724 | F55: 221553 | G55: =(F$3/X55)*$Y55 -> 164105.77 | H55: =$F55/$F$3 -> 0.048354665 | I55: 30916 | J55: =(I$3/X55)*$Y55 -> 150423.53 | K55: =$I55/$I$35 -> 0.017435018 | L55: 47969 | M55: =(L$3/X55)*$Y55 -> 134460.46 | N55: =$L55/$L$34 -> 0.01277764 | O55: 65201 | P55: =(O$3/X55)*$Y55 -> 101168.88 | Q55: =$O55/$O$34 -> 0.023082982 | R55: 71250 | S55: =(R$3/X55)*$Y55 -> 69677.758 | T55: =$R55/$R$34 -> 0.036624802 | U55: 29953 | V55: =(U55/X55)*Y55 -> 1072.8152 | W55: =$U55/$U$34 -> 0.016737924 | X55: 2792 | Y55: 100 | Z55: =X55/$X$3 -> 0.0016102809
A56: 2.02.02.02 | B56: Outros | C56: 72020 | D56: =(C56/X56)*Y56 -> 2579.5129 | E56: =C56/$C$3 -> 0.016122724 | F56: 221553 | G56: =(F$3/X56)*$Y56 -> 164105.77 | H56: =$F56/$F$3 -> 0.048354665 | I56: 29026 | J56: =(I$3/X56)*$Y56 -> 150423.53 | K56: =$I56/$I$35 -> 0.016369156 | L56: 44529 | M56: =(L$3/X56)*$Y56 -> 134460.46 | N56: =$L56/$L$34 -> 0.011861318 | O56: 60808 | P56: =(O$3/X56)*$Y56 -> 101168.88 | Q56: =$O56/$O$34 -> 0.021527737 | R56: 65307 | S56: =(R$3/X56)*$Y56 -> 69677.758 | T56: =$R56/$R$34 -> 0.033569908 | U56: 29953 | V56: =(U56/X56)*Y56 -> 1072.8152 | W56: =$U56/$U$34 -> 0.016737924 | X56: 2792 | Y56: 100 | Z56: =X56/$X$3 -> 0.0016102809
A57: 2.02.02.02.03 | B57: Tributos a Recolher | C57: 0 | E57: =C57/$C$3 -> 0 | F57: 0 | H57: =$F57/$F$3 -> 0 | I57: 0 | K57: =$I57/$I$35 -> 0 | L57: 0 | N57: =$L57/$L$34 -> 0 | O57: 0 | Q57: =$O57/$O$34 -> 0 | R57: 0 | T57: =$R57/$R$34 -> 0 | U57: 0 | W57: =$U57/$U$34 -> 0 | X57: 0 | Y57: 100 | Z57: =X57/$X$3 -> 0
A58: 2.02.02.02.04 | B58: Arrendamento Mercantil | C58: 9286 | E58: =C58/$C$3 -> 0.0020788061 | F58: 23137 | H58: =$F58/$F$3 -> 0.0050497257 | I58: 18125 | K58: =$I58/$I$35 -> 0.010221558 | L58: 26525 | N58: =$L58/$L$34 -> 0.0070655405 | O58: 31839 | Q58: =$O58/$O$34 -> 0.011271899 | R58: 35713 | T58: =$R58/$R$34 -> 0.018357636 | U58: 0 | W58: =$U58/$U$34 -> 0 | X58: 0 | Y58: 100 | Z58: =X58/$X$3 -> 0
A59: 2.02.02.02.05 | B59: Outras Contas a Pagar | C59: 22731 | D59: =(C59/X59)*Y59 -> 974.3249 | E59: =C59/$C$3 -> 0.0050886649 | F59: 15895 | G59: =(F$3/X59)*$Y59 -> 196392.33 | H59: =$F59/$F$3 -> 0.0034691356 | I59: 10426 | J59: =(I$3/X59)*$Y59 -> 180018.22 | K59: =$I59/$I$35 -> 0.0058797223 | L59: 17529 | M59: =(L$3/X59)*$Y59 -> 160914.53 | N59: =$L59/$L$34 -> 0.0046692501 | O59: 28512 | P59: =(O$3/X59)*$Y59 -> 121073.08 | Q59: =$O59/$O$34 -> 0.010094048 | R59: 29135 | S59: =(R$3/X59)*$Y59 -> 83386.327 | T59: =$R59/$R$34 -> 0.014976331 | U59: 23993 | V59: =(U59/X59)*Y59 -> 1028.4183 | W59: =$U59/$U$34 -> 0.013407438 | X59: 2333 | Y59: 100 | Z59: =X59/$X$3 -> 0.0013455535
A60: 2.02.03 | B60: Tributos Diferidos | C60: 18150 | E60: =C60/$C$3 -> 0.0040631414 | F60: 4666 | H60: =$F60/$F$3 -> 0.0010183697 | I60: 492 | K60: =$I60/$I$35 -> 0.00027746244 | L60: 654 | N60: =$L60/$L$34 -> 0.00017420786 | O60: 0 | Q60: =$O60/$O$34 -> 0 | R60: 0 | T60: =$R60/$R$34 -> 0 | U60: 0 | W60: =$U60/$U$34 -> 0 | X60: 0 | Y60: 100 | Z60: =X60/$X$3 -> 0
A61: 2.02.03.01 | B61: Imposto de Renda e Contribuição Social Diferidos | C61: 18150 | E61: =C61/$C$3 -> 0.0040631414 | F61: 4666 | H61: =$F61/$F$3 -> 0.0010183697 | I61: 492 | K61: =$I61/$I$35 -> 0.00027746244 | L61: 654 | N61: =$L61/$L$34 -> 0.00017420786 | O61: 0 | Q61: =$O61/$O$34 -> 0 | R61: 0 | T61: =$R61/$R$34 -> 0 | U61: 0 | W61: =$U61/$U$34 -> 0 | X61: 0 | Y61: 100 | Z61: =X61/$X$3 -> 0
A62: 2.02.04 | B62: Provisões | C62: 285850 | D62: =(C62/X62)*Y62 -> 675.64054 | E62: =C62/$C$3 -> 0.063991679 | F62: 134028 | G62: =(F$3/X62)*$Y62 -> 10829.708 | H62: =$F62/$F$3 -> 0.029252048 | I62: 112603 | J62: =(I$3/X62)*$Y62 -> 9926.7869 | K62: =$I62/$I$35 -> 0.063502241 | L62: 85795 | M62: =(L$3/X62)*$Y62 -> 8873.3478 | N62: =$L62/$L$34 -> 0.022853461 | O62: 53803 | P62: =(O$3/X62)*$Y62 -> 6676.3614 | Q62: =$O62/$O$34 -> 0.019047771 | R62: 49922 | S62: =(R$3/X62)*$Y62 -> 4598.1918 | T62: =$R62/$R$34 -> 0.025661521 | U62: 46981 | V62: =(U62/X62)*Y62 -> 111.04519 | W62: =$U62/$U$34 -> 0.026253277 | X62: 42308 | Y62: 100 | Z62: =X62/$X$3 -> 0.024401061
A63: 2.02.04.01 | B63: Provisões Fiscais Previdenciárias Trabalhistas e Cíveis | C63: 206836 | D63: =(C63/X63)*Y63 -> 625.03324 | E63: =C63/$C$3 -> 0.046303246 | F63: 48113 | G63: =(F$3/X63)*$Y63 -> 13845.742 | H63: =$F63/$F$3 -> 0.010500819 | I63: 48017 | J63: =(I$3/X63)*$Y63 -> 12691.36 | K63: =$I63/$I$35 -> 0.027079093 | L63: 39584 | M63: =(L$3/X63)*$Y63 -> 11344.542 | N63: =$L63/$L$34 -> 0.010544104 | O63: 34497 | P63: =(O$3/X63)*$Y63 -> 8535.7035 | Q63: =$O63/$O$34 -> 0.012212905 | R63: 30600 | S63: =(R$3/X63)*$Y63 -> 5878.7713 | T63: =$R63/$R$34 -> 0.015729389 | U63: 32921 | V63: =(U63/X63)*Y63 -> 99.483259 | W63: =$U63/$U$34 -> 0.018396461 | X63: 33092 | Y63: 100 | Z63: =X63/$X$3 -> 0.01908575
A64: 2.02.06 | B64: Lucros e Receitas a Apropriar | C64: 0 | E64: =C64/$C$3 -> 0 | F64: 0 | H64: =$F64/$F$3 -> 0 | I64: 0 | K64: =$I64/$I$35 -> 0 | L64: 0 | N64: =$L64/$L$34 -> 0 | O64: 0 | Q64: =$O64/$O$34 -> 0 | R64: 0 | T64: =$R64/$R$34 -> 0 | U64: 0 | W64: =$U64/$U$34 -> 0 | X64: 0 | Y64: 100 | Z64: =X64/$X$3 -> 0
A65: 2.02.06.02 | B65: Receitas a Apropriar | C65: 0 | E65: =C65/$C$3 -> 0 | F65: 0 | H65: =$F65/$F$3 -> 0 | I65: 0 | K65: =$I65/$I$35 -> 0 | L65: 0 | N65: =$L65/$L$34 -> 0 | O65: 0 | Q65: =$O65/$O$34 -> 0 | R65: 0 | T65: =$R65/$R$34 -> 0 | U65: 0 | W65: =$U65/$U$34 -> 0 | X65: 0 | Y65: 100 | Z65: =X65/$X$3 -> 0
A66: 2.03 | B66: Patrimônio Líquido Consolidado | C66: 1646121 | D66: =(C66/X66)*Y66 -> 325.07944 | E66: =C66/$C$3 -> 0.36850812 | F66: 1596427 | G66: =(F$3/X66)*$Y66 -> 904.83002 | H66: =$F66/$F$3 -> 0.3484254 | I66: 1406320 | J66: =(I$3/X66)*$Y66 -> 829.39027 | K66: =$I66/$I$35 -> 0.79309141 | L66: 1181661 | M66: =(L$3/X66)*$Y66 -> 741.37467 | N66: =$L66/$L$34 -> 0.31476244 | O66: 1033138 | P66: =(O$3/X66)*$Y66 -> 557.81486 | Q66: =$O66/$O$34 -> 0.36575982 | R66: 534894 | S66: =(R$3/X66)*$Y66 -> 384.18228 | T66: =$R66/$R$34 -> 0.2749528 | U66: 509908 | V66: =(U66/X66)*Y66 -> 100.6977 | W66: =$U66/$U$34 -> 0.28493978 | X66: 506375 | Y66: 100 | Z66: =X66/$X$3 -> 0.29205085
A67: 2.03.01 | B67: Capital Social Realizado | C67: 721670 | D67: =(C67/X67)*Y67 -> 185.51928 | E67: =C67/$C$3 -> 0.16155632 | F67: 721670 | G67: =(F$3/X67)*$Y67 -> 1177.8491 | H67: =$F67/$F$3 -> 0.15750683 | I67: 721670 | J67: =(I$3/X67)*$Y67 -> 1079.6465 | K67: =$I67/$I$35 -> 0.40698438 | L67: 721670 | M67: =(L$3/X67)*$Y67 -> 965.07352 | N67: =$L67/$L$34 -> 0.19223331 | O67: 721670 | P67: =(O$3/X67)*$Y67 -> 726.12725 | Q67: =$O67/$O$34 -> 0.25549142 | R67: 389000 | S67: =(R$3/X67)*$Y67 -> 500.1036 | T67: =$R67/$R$34 -> 0.19995857 | U67: 389000 | V67: =(U67/X67)*Y67 -> 100 | W67: =$U67/$U$34 -> 0.21737563 | X67: 389000 | Y67: 100 | Z67: =X67/$X$3 -> 0.22435504
A68: 2.03.02 | B68: Reservas de Capital | C68: 101055 | D68: =(C68/X68)*Y68 -> 105.92434 | E68: =C68/$C$3 -> 0.022622631 | F68: 104889 | G68: =(F$3/X68)*$Y68 -> 4802.6089 | H68: =$F68/$F$3 -> 0.022892366 | I68: 101910 | J68: =(I$3/X68)*$Y68 -> 4402.1939 | K68: =$I68/$I$35 -> 0.057471945 | L68: 98811 | M68: =(L$3/X68)*$Y68 -> 3935.0293 | N68: =$L68/$L$34 -> 0.02632057 | O68: 106086 | P68: =(O$3/X68)*$Y68 -> 2960.7402 | Q68: =$O68/$O$34 -> 0.037557419 | R68: 106789 | S68: =(R$3/X68)*$Y68 -> 2039.1424 | T68: =$R68/$R$34 -> 0.054892996 | U68: 99888 | V68: =(U68/X68)*Y68 -> 104.70111 | W68: =$U68/$U$34 -> 0.055818039 | X68: 95403 | Y68: 100 | Z68: =X68/$X$3 -> 0.055023505
A69: 2.03.02.05 | B69: Ações em Tesouraria | C69: -21203 | D69: =(C69/X69)*Y69 -> 91.752131 | E69: =C69/$C$3 -> -0.0047465999 | F69: -17493 | G69: =(F$3/X69)*$Y69 -> -19827.05 | H69: =$F69/$F$3 -> -0.0038179043 | I69: -19033 | J69: =(I$3/X69)*$Y69 -> -18173.98 | K69: =$I69/$I$35 -> -0.010733623 | L69: -21128 | M69: =(L$3/X69)*$Y69 -> -16245.342 | N69: =$L69/$L$34 -> -0.0056279261 | O69: -13325 | P69: =(O$3/X69)*$Y69 -> -12223.095 | Q69: =$O69/$O$34 -> -0.0047174237 | R69: -12501 | S69: =(R$3/X69)*$Y69 -> -8418.3781 | T69: =$R69/$R$34 -> -0.0064259179 | U69: -19229 | V69: =(U69/X69)*Y69 -> 83.210005 | W69: =$U69/$U$34 -> -0.010745285 | X69: -23109 | Y69: 100 | Z69: =X69/$X$3 -> -0.013328073
A70: 2.03.02.07 | B70: Reserva de Capital | C70: 122258 | D70: =(C70/X70)*Y70 -> 103.16086 | E70: =C70/$C$3 -> 0.027369231 | F70: 122382 | G70: =(F$3/X70)*$Y70 -> 3866.1342 | H70: =$F70/$F$3 -> 0.026710271 | I70: 120943 | J70: =(I$3/X70)*$Y70 -> 3543.7973 | K70: =$I70/$I$35 -> 0.068205568 | L70: 119939 | M70: =(L$3/X70)*$Y70 -> 3167.7265 | N70: =$L70/$L$34 -> 0.031948496 | O70: 119411 | P70: =(O$3/X70)*$Y70 -> 2383.4169 | Q70: =$O70/$O$34 -> 0.042274843 | R70: 119290 | S70: =(R$3/X70)*$Y70 -> 1641.5241 | T70: =$R70/$R$34 -> 0.061318914 | U70: 119117 | V70: =(U70/X70)*Y70 -> 100.5105 | W70: =$U70/$U$34 -> 0.066563325 | X70: 118512 | Y70: 100 | Z70: =X70/$X$3 -> 0.068351579
A71: 2.03.04 | B71: Reservas de Lucros | C71: 820122 | D71: =(C71/X71)*Y71 -> 1222.8034 | E71: =C71/$C$3 -> 0.18359624 | F71: 779421 | G71: =(F$3/X71)*$Y71 -> 6831.5213 | H71: =$F71/$F$3 -> 0.17011118 | I71: 591779 | J71: =(I$3/X71)*$Y71 -> 6261.9467 | K71: =$I71/$I$35 -> 0.33373261 | L71: 361419 | M71: =(L$3/X71)*$Y71 -> 5597.4235 | N71: =$L71/$L$34 -> 0.096272218 | O71: 211233 | P71: =(O$3/X71)*$Y71 -> 4211.5359 | Q71: =$O71/$O$34 -> 0.074782406 | R71: 68687 | S71: =(R$3/X71)*$Y71 -> 2900.5994 | T71: =$R71/$R$34 -> 0.035307337 | U71: 61843 | V71: =(U71/X71)*Y71 -> 92.208025 | W71: =$U71/$U$34 -> 0.034558255 | X71: 67069 | Y71: 100 | Z71: =X71/$X$3 -> 0.038681923
A72: 2.03.04.01 | B72: Reserva Legal | C72: 0 | E72: =C72/$C$3 -> 0 | F72: 0 | H72: =$F72/$F$3 -> 0 | I72: 0 | K72: =$I72/$I$35 -> 0 | L72: 0 | N72: =$L72/$L$34 -> 0 | O72: 0 | Q72: =$O72/$O$34 -> 0 | R72: 0 | T72: =$R72/$R$34 -> 0 | U72: 0 | W72: =$U72/$U$34 -> 0 | X72: 0 | Y72: 100 | Z72: =X72/$X$3 -> 0
A73: 2.03.04.05 | B73: Reserva de Retenção de Lucros | C73: 0 | E73: =C73/$C$3 -> 0 | F73: 0 | H73: =$F73/$F$3 -> 0 | I73: 0 | K73: =$I73/$I$35 -> 0 | L73: 0 | N73: =$L73/$L$34 -> 0 | O73: 0 | Q73: =$O73/$O$34 -> 0 | R73: 0 | T73: =$R73/$R$34 -> 0 | U73: 0 | W73: =$U73/$U$34 -> 0 | X73: 0 | Y73: 100 | Z73: =X73/$X$3 -> 0
A74: 2.03.08 | B74: Outros Resultados Abrangentes | C74: 0 | E74: =C74/$C$3 -> 0 | F74: 0 | H74: =$F74/$F$3 -> 0 | I74: 0 | K74: =$I74/$I$35 -> 0 | L74: 0 | N74: =$L74/$L$34 -> 0 | O74: 0 | Q74: =$O74/$O$34 -> 0 | R74: 0 | T74: =$R74/$R$34 -> 0 | U74: 0 | W74: =$U74/$U$34 -> 0 | X74: 0 | Y74: 100 | Z74: =X74/$X$3 -> 0
A75: TOTAL DO PASSIVO E PATRIMÔNIO LÍQUIDO | C75: =SUM(C66,C34) -> 6113108 | D75: =(C75/X75)*Y75 -> 272.8781 | E75: =C75/$C$3 -> 1.3685081 | F75: =SUM(F66,F34) -> 6178260 | G75: =(F$3/X75)*$Y75 -> 204.52475 | H75: =$F75/$F$3 -> 1.3484254 | I75: =SUM(I34,I66) -> 5606145 | J75: =(I$3/X75)*$Y75 -> 187.4726 | K75: =$I75/$I$3 -> 1.334852 | L75: =SUM(L34,L66) -> 4935797 | M75: =(L$3/X75)*$Y75 -> 167.57785 | N75: =$L75/$L$3 -> 1.3147624 | O75: =SUM(O34,O66) -> 3857773 | P75: =(O$3/X75)*$Y75 -> 126.08661 | Q75: =$O75/$O$3 -> 1.3657598 | R75: =SUM(R34,R66) -> 2480297 | S75: =(R$3/X75)*$Y75 -> 86.839277 | T75: =$R75/$R$3 -> 1.2749528 | U75: =SUM(U34,U66) -> 2299437 | V75: =(U75/X75)*Y75 -> 102.64272 | W75: =$U75/$U$3 -> 1.2849398 | X75: =X34+X66 -> 2240234 | Y75: 100 | Z75: =X75/$X$3 -> 1.2920509

Sheet DRE - AH e AV
A1: Demonstração do Resultado do Exercício - Análise Horizontal (ANO BASE 2017)
A2: Código da Conta | B2: Descrição da Conta | C2: 2024 | D2: AH 24 | E2: AV24 | F2: 2023 | G2: AH23 | H2: AV22 | I2: 2022 | J2: AH22 | K2: AV22 | L2: 2021 | M2: AH21 | N2: AV21 | O2: 2020 | P2: AH20 | Q2: AV20 | R2: 2019 | S2: AH19 | T2: AV19 | U2: 2018 | V2: AH18 | W2: AV18 | X2: 2017 | Y2: AH17 | Z2: AV17
A3: 3.01 | B3: Receita de Venda de Bens e/ou Serviços | C3: 3688326 | D3: =(C3/X3)*Y3 -> 1.9274198 | E3: =C3/C3 -> 1 | F3: 3926631 | G3: =(F3/X3)*$Y3 -> 2.0519516 | H3: =$F$3/$F$3 -> 1 | I3: 4993235 | J3: =(I3/X3)*$Y3 -> 2.6093301 | K3: =I3/$I$3 -> 1 | L3: 3365487 | M3: =(L3/X3)*$Y3 -> 1.7587129 | N3: =L3/L$3 -> 1 | O3: 2192173 | P3: =(O3/X3)*$Y3 -> 1.1455706 | Q3: =O3/O$3 -> 1 | R3: 1915308 | S3: =(R3/X3)*$Y3 -> 1.0008884 | T3: =R3/$R$3 -> 1 | U3: 1890654 | V3: =(U3/X3)*Y3 -> 0.98800486 | W3: =U3/$U$3 -> 1 | X3: 1913608 | Y3: 1 | Z3: =X3/X3 -> 1
A4: 3.02 | B4: Custo dos Bens e/ou Serviços Vendidos | C4: -2764289 | D4: =(C4/X4)*Y4 -> 1.9463274 | E4: =F4/C3 -> -0.77653168 | F4: -2864102 | G4: =(F4/X4)*$Y4 -> 2.0166054 | H4: =I4/$F$3 -> -0.96685377 | I4: -3796478 | J4: =(I4/X4)*$Y4 -> 2.6730885 | K4: =I4/$I$3 -> -0.76032432 | L4: -2596881 | M4: =(L4/X4)*$Y4 -> 1.8284559 | N4: =L4/L$3 -> -0.77162117 | O4: -1743427 | P4: =(O4/X4)*$Y4 -> 1.2275416 | Q4: =O4/O$3 -> -0.79529627 | R4: -1435200 | S4: =(R4/X4)*$Y4 -> 1.0105199 | T4: =R4/$R$3 -> -0.74933118 | U4: -1436949 | V4: =(U4/X4)*Y4 -> 1.0117514 | W4: =U4/$U$3 -> -0.76002748 | X4: -1420259 | Y4: 1 | Z4: =X4/$X$3 -> -0.7421891
A5: 3.03 | B5: Resultado Bruto | C5: 924037 | D5: =(C5/X5)*Y5 -> 1.8729885 | E5: =F5/C4 -> -0.38437696 | F5: 1062529 | G5: =(F5/X5)*$Y5 -> 2.1537066 | H5: =I5/$F$3 -> 0.30477959 | I5: 1196757 | J5: =(I5/X5)*$Y5 -> 2.4257817 | K5: =I5/$I$3 -> 0.23967568 | L5: 768606 | M5: =(L5/X5)*$Y5 -> 1.5579357 | N5: =L5/L$3 -> 0.22837883 | O5: 448746 | P5: =(O5/X5)*$Y5 -> 0.90959138 | Q5: =O5/O$3 -> 0.20470373 | R5: 480108 | S5: =(R5/X5)*$Y5 -> 0.97316099 | T5: =R5/$R$3 -> 0.25066882 | U5: 453705 | V5: =(U5/X5)*Y5 -> 0.91964309 | W5: =U5/$U$3 -> 0.23997252 | X5: 493349 | Y5: 1 | Z5: =X5/$X$3 -> 0.2578109
B6: Margem Bruta | C6: =C5/C3 -> 0.25053019 | D6: =(C6/X6)*Y6 -> 0.97175948 | E6: =F6/C5 -> 2.9284063e-07 | F6: =F5/F3 -> 0.27059558 | G6: =(F6/X6)*$Y6 -> 1.0495894 | H6: =I6/$F$3 -> 6.1038504e-08 | I6: =I5/I3 -> 0.23967568 | J6: =(I6/X6)*$Y6 -> 0.9296569 | L6: =L5/L3 -> 0.22837883 | M6: =(L6/X6)*$Y6 -> 0.88583856 | O6: =O5/O3 -> 0.20470373 | P6: =(O6/X6)*$Y6 -> 0.79400729 | R6: =R5/R3 -> 0.25066882 | S6: =(R6/X6)*$Y6 -> 0.97229722 | T6: =R6/$R$3 -> 1.3087651e-07 | U6: =U5/U3 -> 0.23997252 | V6: =(U6/X6)*Y6 -> 0.93080827 | W6: =U6/$U$3 -> 1.2692567e-07 | X6: =X5/X3 -> 0.2578109 | Y6: 1 | Z6: =X6/$X$3 -> 1.3472503e-07
A7: 3.04 | B7: Despesas/Receitas Operacionais | C7: -614527 | D7: =(C7/X7)*Y7 -> 1.3527732 | E7: =F7/C6 -> -2211118.8 | F7: -553952 | G7: =(F7/X7)*$Y7 -> 1.219428 | H7: =I7/$F$3 -> -0.14558587 | I7: -571662 | J7: =(I7/X7)*$Y7 -> 1.2584135 | K7: =I7/$I$3 -> -0.1144873 | L7: -465457 | M7: =(L7/X7)*$Y7 -> 1.0246218 | N7: =L7/L$3 -> -0.13830302 | O7: -171070 | P7: =(O7/X7)*$Y7 -> 0.37658055 | Q7: =O7/O$3 -> -0.078036724 | R7: -381253 | S7: =(R7/X7)*$Y7 -> 0.8392615 | T7: =R7/$R$3 -> -0.19905571 | U7: -378691 | V7: =(U7/X7)*Y7 -> 0.83362171 | W7: =U7/$U$3 -> -0.2002963 | X7: -454272 | Y7: 1 | Z7: =X7/$X$3 -> -0.23739031
B8: %Receita Líquida | D8: =(C8/X8)*Y8 -> 0 | E8: =F8/C7 -> 2.2956785e-07 | F8: =F7/F3 -> -0.14107564 | G8: =(F8/X8)*$Y8 -> 0.59427718 | H8: =I8/$F$3 -> -2.9156623e-08 | I8: =I7/I3 -> -0.1144873 | J8: =(I8/X8)*$Y8 -> 0.48227453 | K8: =I8/$I$3 -> -2.2928483e-08 | L8: =L7/L3 -> -0.13830302 | M8: =(L8/X8)*$Y8 -> 0.58259755 | O8: =O7/O3 -> -0.078036724 | P8: =(O8/X8)*$Y8 -> 0.3287275 | R8: =R7/R3 -> -0.19905571 | S8: =(R8/X8)*$Y8 -> 0.83851658 | T8: =R8/$R$3 -> -1.0392883e-07 | U8: =U7/U3 -> -0.2002963 | V8: =(U8/X8)*Y8 -> 0.84374252 | W8: =U8/$U$3 -> -1.0594022e-07 | X8: =X7/X3 -> -0.23739031 | Y8: 1 | Z8: =X8/$X$3 -> -1.2405378e-07
A9: 3.04.01 | B9: Despesas com Vendas | C9: -436329 | D9: =(C9/X9)*Y9 -> 1.31369 | F9: -496236 | G9: =(F9/X9)*$Y9 -> 1.4940567 | H9: =I9/$F$3 -> -0.1375897 | I9: -540264 | J9: =(I9/X9)*$Y9 -> 1.6266153 | K9: =I9/$I$3 -> -0.10819919 | L9: -363763 | M9: =(L9/X9)*$Y9 -> 1.0952099 | N9: =L9/L$3 -> -0.10808629 | O9: -310653 | P9: =(O9/X9)*$Y9 -> 0.9353074 | Q9: =O9/O$3 -> -0.14171007 | R9: -273006 | S9: =(R9/X9)*$Y9 -> 0.82196062 | T9: =R9/$R$3 -> -0.14253895 | U9: -276226 | V9: =(U9/X9)*Y9 -> 0.83165533 | W9: =U9/$U$3 -> -0.14610077 | X9: -332140 | Y9: 1 | Z9: =X9/$X$3 -> -0.17356742
A10: 3.04.02 | B10: Despesas Gerais e Administrativas | C10: 220817 | D10: =(C10/X10)*Y10 -> -2.2322786 | E10: =F10/C9 -> 0.49543349 | F10: -216172 | G10: =(F10/X10)*$Y10 -> 2.1853215 | H10: =I10/$F$3 -> -0.050253003 | I10: -197325 | J10: =(I10/X10)*$Y10 -> 1.9947938 | K10: =I10/$I$3 -> -0.039518468 | L10: -163437 | M10: =(L10/X10)*$Y10 -> 1.6522139 | N10: =L10/L$3 -> -0.04856266 | O10: -82691 | P10: =(O10/X10)*$Y10 -> 0.83593813 | Q10: =O10/O$3 -> -0.037721019 | R10: -112095 | S10: =(R10/X10)*$Y10 -> 1.1331884 | T10: =R10/$R$3 -> -0.058525835 | U10: -105148 | V10: =(U10/X10)*Y10 -> 1.06296 | W10: =U10/$U$3 -> -0.055614618 | X10: -98920 | Y10: 1 | Z10: =X10/$X$3 -> -0.051692928
A11: 3.04.03 | B11: Perdas pela Não Recuperabilidade de Ativos | C11: 0 | E11: =F11/C10 -> 0 | F11: 0 | H11: =I11/$F$3 -> 0 | I11: 0 | K11: =I11/$I$3 -> 0 | L11: 0 | N11: =L11/L$3 -> 0 | O11: 0 | Q11: =O11/O$3 -> 0 | R11: 0 | T11: =R11/$R$3 -> 0 | U11: 0 | W11: =U11/$U$3 -> 0 | X11: 0 | Y11: 1 | Z11: =X11/$X$3 -> 0
A12: 3.04.04 | B12: Outras Receitas Operacionais | C12: 50284 | F12: 165013 | H12: =I12/$F$3 -> 0.044362967 | I12: 174197 | K12: =I12/$I$3 -> 0.034886602 | L12: 57585 | N12: =L12/L$3 -> 0.017110451 | O12: 221150 | Q12: =O12/O$3 -> 0.10088164 | R12: 5896 | T12: =R12/$R$3 -> 0.0030783561 | U12: 5610 | W12: =U12/$U$3 -> 0.0029672272 | X12: 0 | Y12: 1 | Z12: =X12/$X$3 -> 0
A13: 3.04.06 | B13: Resultado de Equivalência Patrimonial | C13: -7665 | D13: =(C13/X13)*Y13 -> 1.2514286 | E13: =F13/C12 -> -0.13039933 | F13: -6557 | G13: =(F13/X13)*$Y13 -> 1.0705306 | H13: =I13/$F$3 -> -0.0021061312 | I13: -8270 | J13: =(I13/X13)*$Y13 -> 1.3502041 | K13: =I13/$I$3 -> -0.0016562409 | L13: 4158 | M13: =(L13/X13)*$Y13 -> -0.67885714 | N13: =L13/L$3 -> 0.0012354824 | O13: 1124 | P13: =(O13/X13)*$Y13 -> -0.1835102 | Q13: =O13/O$3 -> 0.00051273326 | R13: -2048 | S13: =(R13/X13)*$Y13 -> 0.33436735 | T13: =R13/$R$3 -> -0.0010692797 | U13: -2927 | V13: =(U13/X13)*Y13 -> 0.47787755 | W13: =U13/$U$3 -> -0.0015481415 | X13: -6125 | Y13: 1 | Z13: =X13/$X$3 -> -0.00320076
A14: 3.05 | B14: Resultado Antes do Resultado Financeiro e dos Tributos | C14: 309510 | D14: =(C14/X14)*Y14 -> 7.9205159 | E14: =F14/C13 -> -66.350554 | F14: 508577 | G14: =(F14/X14)*$Y14 -> 13.01474 | H14: =I14/$F$3 -> 0.15919372 | I14: 625095 | J14: =(I14/X14)*$Y14 -> 15.996494 | K14: =I14/$I$3 -> 0.12518838 | L14: 303149 | M14: =(L14/X14)*$Y14 -> 7.7577347 | N14: =L14/L$3 -> 0.09007582 | O14: 277676 | P14: =(O14/X14)*$Y14 -> 7.1058679 | Q14: =O14/O$3 -> 0.12666701 | R14: 98855 | S14: =(R14/X14)*$Y14 -> 2.529749 | T14: =R14/$R$3 -> 0.051613109 | U14: 75014 | V14: =(U14/X14)*Y14 -> 1.9196458 | W14: =U14/$U$3 -> 0.039676218 | X14: 39077 | Y14: 1 | Z14: =X14/$X$3 -> 0.020420588
A15: 3.06 | B15: Resultado Financeiro | C15: -207374 | D15: =(C15/X15)*Y15 -> 2.4965569 | E15: =F15/C14 -> -0.82202837 | F15: -254426 | G15: =(F15/X15)*$Y15 -> 3.0630117 | H15: =I15/$F$3 -> -0.0081013469 | I15: -31811 | J15: =(I15/X15)*$Y15 -> 0.38296976 | K15: =I15/$I$3 -> -0.0063708197 | L15: -94912 | M15: =(L15/X15)*$Y15 -> 1.142637 | N15: =L15/L$3 -> -0.028201565 | O15: -5287 | P15: =(O15/X15)*$Y15 -> 0.063649716 | Q15: =O15/O$3 -> -0.0024117622 | R15: -70575 | S15: =(R15/X15)*$Y15 -> 0.84964606 | T15: =R15/$R$3 -> -0.036847859 | U15: -64781 | V15: =(U15/X15)*Y15 -> 0.77989261 | W15: =U15/$U$3 -> -0.034263805 | X15: -83064 | Y15: 1 | Z15: =X15/$X$3 -> -0.043407009
A16: 3.06.01 | B16: Receitas Financeiras | C16: 114170 | D16: =(C16/X16)*Y16 -> 1.7528211 | E16: =F16/C15 -> -0.50305246 | F16: 104320 | G16: =(F16/X16)*$Y16 -> 1.6015967 | H16: =I16/$F$3 -> 0.010061806 | I16: 39509 | J16: =(I16/X16)*$Y16 -> 0.60657097 | K16: =I16/$I$3 -> 0.0079125056 | L16: 63856 | M16: =(L16/X16)*$Y16 -> 0.98036386 | N16: =L16/L$3 -> 0.018973777 | O16: 95289 | P16: =(O16/X16)*$Y16 -> 1.4629462 | Q16: =O16/O$3 -> 0.043467828 | R16: 37406 | S16: =(R16/X16)*$Y16 -> 0.57428418 | T16: =R16/$R$3 -> 0.019530018 | U16: 48130 | V16: =(U16/X16)*Y16 -> 0.73892684 | W16: =U16/$U$3 -> 0.0254568 | X16: 65135 | Y16: 1 | Z16: =X16/$X$3 -> 0.034037797
A17: 3.06.02 | B17: Despesas Financeiras | C17: -321544 | D17: =(C17/X17)*Y17 -> -4.9365779 | E17: =F17/C16 -> 0.91372515 | F17: 104320 | G17: =(F17/X17)*$Y17 -> 1.6015967 | H17: =I17/$F$3 -> 0.021990862 | I17: 86350 | J17: =(I17/X17)*$Y17 -> 1.3257081 | K17: =I17/$I$3 -> 0.017293398 | L17: 43706 | M17: =(L17/X17)*$Y17 -> 0.67100637 | N17: =L17/L$3 -> 0.012986531 | O17: 59756 | P17: =(O17/X17)*$Y17 -> 0.91741767 | Q17: =O17/O$3 -> 0.027258798 | R17: 32306 | S17: =(R17/X17)*$Y17 -> 0.49598526 | T17: =R17/$R$3 -> 0.016867261 | U17: 48130 | V17: =(U17/X17)*Y17 -> 0.73892684 | W17: =U17/$U$3 -> 0.0254568 | X17: 65135 | Y17: 1 | Z17: =X17/$X$3 -> 0.034037797
A18: 3.07 | B18: Resultado Antes dos Tributos sobre o Lucro | C18: 102136 | D18: =(C18/X18)*Y18 -> -2.3219588 | E18: =F18/C17 -> -0.79040816 | F18: 254151 | G18: =(F18/X18)*$Y18 -> -5.7778662 | H18: =I18/$F$3 -> 0.078179997 | I18: 306984 | J18: =(I18/X18)*$Y18 -> -6.9789711 | K18: =I18/$I$3 -> 0.061479982 | L18: 208237 | M18: =(L18/X18)*$Y18 -> -4.7340578 | N18: =L18/L$3 -> 0.061874255 | O18: 272389 | P18: =(O18/X18)*$Y18 -> -6.1924887 | Q18: =O18/O$3 -> 0.12425525 | R18: 28280 | S18: =(R18/X18)*$Y18 -> -0.64291723 | T18: =R18/$R$3 -> 0.014765249 | U18: 10233 | V18: =(U18/X18)*Y18 -> -0.23263692 | W18: =U18/$U$3 -> 0.0054124128 | X18: -43987 | Y18: 1 | Z18: =X18/$X$3 -> -0.022986421
A19: 3.08 | B19: Imposto de Renda e Contribuição Social sobre o Lucro | C19: -17098 | D19: =(C19/X19)*Y19 -> 4.7974186 | E19: =F19/C18 -> -0.032006344 | F19: -3269 | G19: =(F19/X19)*$Y19 -> 0.91722783 | H19: =I19/$F$3 -> -0.00015967887 | I19: -627 | J19: =(I19/X19)*$Y19 -> 0.17592593 | K19: =I19/$I$3 -> -0.0001255699 | L19: -5341 | M19: =(L19/X19)*$Y19 -> 1.4985971 | N19: =L19/L$3 -> -0.0015869917 | O19: -76547 | P19: =(O19/X19)*$Y19 -> 21.477834 | Q19: =O19/O$3 -> -0.034918321 | R19: -7432 | S19: =(R19/X19)*$Y19 -> 2.0852974 | T19: =R19/$R$3 -> -0.0038803159 | U19: -10694 | V19: =(U19/X19)*Y19 -> 3.0005612 | W19: =U19/$U$3 -> -0.0056562438 | X19: -3564 | Y19: 1 | Z19: =X19/$X$3 -> -0.0018624504
A20: 3.09 | B20: Resultado Líquido das Operações Continuadas | C20: 85038 | D20: =(C20/X20)*Y20 -> -1.7883536 | E20: =F20/C19 -> -14.673178 | F20: 250882 | G20: =(F20/X20)*$Y20 -> -5.2760615 | H20: =I20/$F$3 -> 0.078020318 | I20: 306357 | J20: =(I20/X20)*$Y20 -> -6.4427036 | K20: =I20/$I$3 -> 0.061354413 | L20: 202896 | M20: =(L20/X20)*$Y20 -> -4.2669134 | N20: =L20/L$3 -> 0.060287263 | O20: 195842 | P20: =(O20/X20)*$Y20 -> -4.1185674 | Q20: =O20/O$3 -> 0.089336927 | R20: 20848 | S20: =(R20/X20)*$Y20 -> -0.43843452 | T20: =R20/$R$3 -> 0.010884933 | U20: -461 | V20: =(U20/X20)*Y20 -> 0.0096948539 | W20: =U20/$U$3 -> -0.00024383097 | X20: -47551 | Y20: 1 | Z20: =X20/$X$3 -> -0.024848872
A21: 3.11 | B21: Lucro/Prejuízo do Período | C21: 85038 | D21: =(C21/X21)*Y21 -> -1.7883536 | E21: =F21/C20 -> 2.950234 | F21: 250882 | G21: =(F21/X21)*$Y21 -> -5.2760615 | H21: =I21/$F$3 -> 0.078020318 | I21: 306357 | J21: =(I21/X21)*$Y21 -> -6.4427036 | K21: =I21/$I$3 -> 0.061354413 | L21: 202896 | M21: =(L21/X21)*$Y21 -> -4.2669134 | N21: =L21/L$3 -> 0.060287263 | O21: 195842 | P21: =(O21/X21)*$Y21 -> -4.1185674 | Q21: =O21/O$3 -> 0.089336927 | R21: 20848 | S21: =(R21/X21)*$Y21 -> -0.43843452 | T21: =R21/$R$3 -> 0.010884933 | U21: -461 | V21: =(U21/X21)*Y21 -> 0.0096948539 | W21: =U21/$U$3 -> -0.00024383097 | X21: -47551 | Y21: 1 | Z21: =X21/$X$3 -> -0.024848872
A22: 3.11.01 | B22: Atribuído a Sócios da Empresa Controladora | C22: 80378 | D22: =(C22/X22)*Y22 -> -1.6903535 | E22: =F22/C21 -> 2.9017616 | F22: 246760 | G22: =(F22/X22)*$Y22 -> -5.1893756 | H22: =I22/$F$3 -> 0.077195183 | I22: 303117 | J22: =(I22/X22)*$Y22 -> -6.3745663 | K22: =I22/$I$3 -> 0.060705535 | L22: 200258 | M22: =(L22/X22)*$Y22 -> -4.2114361 | N22: =L22/L$3 -> 0.059503424 | O22: 190971 | P22: =(O22/X22)*$Y22 -> -4.01613 | Q22: =O22/O$3 -> 0.087114931 | R22: 16459 | S22: =(R22/X22)*$Y22 -> -0.34613362 | T22: =R22/$R$3 -> 0.0085933959 | U22: -461 | V22: =(U22/X22)*Y22 -> 0.0096948539 | W22: =U22/$U$3 -> -0.00024383097 | X22: -47551 | Y22: 1 | Z22: =X22/$X$3 -> -0.024848872
A23: 3.99 | B23: Lucro por Ação - (Reais / Ação)
A24: 3.99.01 | B24: Lucro Básico por Ação
A25: 3.99.01.01 | B25: ON | F25: 1.7617 | I25: 2.1673 | L25: 1.4287 | O25: 1.4024
A26: 3.99.02 | B26: Lucro Diluído por Ação | C26: 0.57450
A27: 3.99.02.01 | B27: ON | C27: 0.57390 | F27: 1.7583 | I27: 2.1638 | L27: 1.4234 | O27: 1.4005

Sheet índices
C2: Ano 2024 | D2: Ano 2023 | E2: Ano 2022 | F2: Ano 2021 | G2: Ano 2020 | H2: Ano 2019 | I2: Ano 2018 | J2: Ano 2017 | M2: Ano 2024 | N2: Ano 2023 | O2: Ano 2022 | P2: Ano 2021 | Q2: Ano 2020 | R2: Ano 2019 | S2: Ano 2018 | T2: Ano 2017 | W2: Ano 2024 | X2: Ano 2023 | Y2: Ano 2022 | Z2: Ano 2021 | AA2: Ano 2020 | AB2: Ano 2019 | AC2: Ano 2018 | AD2: Ano 2017
B3: Liquidez Geral | C3: =(C4+C5)/(C6+C7) -> 1.3235471 | D3: =(D4+D5)/(D6+D7) -> 1.3658172 | E3: =(E4+E5)/(E6+E7) -> 1.3652863 | F3: =(F4+F5)/(F6+F7) -> 1.3450168 | G3: =(G4+G5)/(G6+G7) -> 1.4227331 | H3: =(H4+H5)/(H6+H7) -> 1.1897206 | I3: =(I4+I5)/(I6+I7) -> 1.2591853 | J3: =(J4+J5)/(J6+J7) -> 1.2717013 | L3: Margem Bruta | M3: =M4/M5 -> 0.25053019 | N3: =N4/N5 -> 0.27059558 | O3: =O4/O5 -> 0.23967568 | P3: =P4/P5 -> 0.22837883 | Q3: =Q4/Q5 -> 0.20470373 | R3: =R4/R5 -> 0.25066882 | S3: =S4/S5 -> 0.23997252 | T3: =T4/T5 -> 0.2578109 | V3: Índice P/L | W3: =W4/W5 -> 0.086375973 | X3: =X4/X5 -> 0.039338334 | Y3: =Y4/Y5 -> 0.043462431 | Z3: =Z4/Z5 -> 0.076177943 | AA3: =AA4/AA5 -> 0.036926706 | AB3: =AB4/AB5 -> 0.42914524 | AC3: =AC4/AC5 -> -4.2662039 | AD3: =AD4/AD5 -> -0.057424239
B4: Ativo Circulante | C4: 2967747 | D4: 3575173 | E4: 3430062 | F4: 3120040 | G4: 2211237 | H4: 1471763 | I4: 1418740 | J4: 1411332 | L4: Lucro Bruto | M4: 924037 | N4: =DRE!D5 -> 1062529 | O4: =DRE!E5 -> 1196757 | P4: =DRE!F5 -> 768606 | Q4: =DRE!G5 -> 448746 | R4: =DRE!H5 -> 480108 | S4: =DRE!I5 -> 453705 | T4: =DRE!J5 -> 493349 | V4: Preço no mercado | W4: =AG7*W38 -> 734524 | X4: =AG8*$Y$38 -> 986928 | Y4: =$AG$9*$Y$38 -> 1331502 | Z4: =$AG$10*$Z$38 -> 1545620 | AA4: =$AG$11*$AA$38 -> 723180 | AB4: =$AG$12*$AB$38 -> 894682 | AC4: =$AG$13*$AC$38 -> 196672 | AD4: =$AG$14*$AD$38 -> 273058
B5: Ativo Realizável a Longo Prazo | C5: 765802 | D5: 502346 | E5: 383872 | F5: 339982 | G5: 337585 | H5: 206351 | I5: 192540 | J5: 149661 | L5: Receita Líquida | M5: 3688326 | N5: =DRE!D3 -> 3926631 | O5: =DRE!E3 -> 4993235 | P5: =DRE!F3 -> 3365487 | Q5: =DRE!G3 -> 2192173 | R5: =DRE!H3 -> 1915308 | S5: =DRE!I3 -> 1890654 | T5: =DRE!J3 -> 1913608 | V5: Lucro Líquido (em milhares) | W5: =DRE!C21*100 -> 8503800 | X5: =DRE!D21*100 -> 25088200 | Y5: =DRE!E21*100 -> 30635700 | Z5: =DRE!F21*100 -> 20289600 | AA5: =DRE!G21*100 -> 19584200 | AB5: =DRE!H21*100 -> 2084800 | AC5: =DRE!I21*100 -> -46100 | AD5: =DRE!J21*100 -> -4755100
B6: Passivo Cirulante | C6: 1503102 | D6: 1934265 | E6: 1773213 | F6: 1937651 | G6: 1370932 | H6: 1178943 | I6: 1111886 | J6: 1090782 | AF6: Preço das ações que estão no BP
B7: Passivo Exigivel a Longo Prazo | C7: 1317764 | D7: 1051141 | E7: 1020292 | F7: 634824 | G7: 420565 | H7: 231568 | I7: 167735 | J7: 136702 | M7: Ano 2024 | N7: Ano 2023 | O7: Ano 2022 | P7: Ano 2021 | Q7: Ano 2020 | R7: Ano 2019 | S7: Ano 2018 | T7: Ano 2017 | W7: Ano 2024 | X7: Ano 2023 | Y7: Ano 2022 | Z7: Ano 2021 | AA7: Ano 2020 | AB7: Ano 2019 | AC7: Ano 2018 | AD7: Ano 2017 | AF7: 2024 | AG7: 5.18
L8: Margem Líquida | M8: =M9/M10 -> 0.023055988 | N8: =N9/N10 -> 0.063892431 | O8: =O9/O10 -> 0.061354413 | P8: =P9/P10 -> 0.060287263 | Q8: =Q9/Q10 -> 0.089336927 | R8: =R9/R10 -> 0.010884933 | S8: =S9/S10 -> -0.00024383097 | T8: =T9/T10 -> -0.024848872 | V8: Índice P/VPA | W8: =W9/W10 -> 116.58362 | X8: =X9/X10 -> 152.71878 | Y8: =Y9/Y10 -> 224.77958 | Z8: =Z9/Z10 -> 291.90327 | AA8: =AA9/AA10 -> 181.52243 | AB8: =AB9/AB10 -> 201.89411 | AC8: =AC9/AC10 -> 48.246778 | AD8: =AD9/AD10 -> 69.136223 | AF8: 2023 | AG8: 6.96
C9: Ano 2024 | D9: Ano 2023 | E9: Ano 2022 | F9: Ano 2021 | G9: Ano 2020 | H9: Ano 2019 | I9: Ano 2018 | J9: Ano 2017 | L9: Lucro Líquido | M9: 85038 | N9: =DRE!D21 -> 250882 | O9: =DRE!E21 -> 306357 | P9: =DRE!F21 -> 202896 | Q9: =DRE!G21 -> 195842 | R9: =DRE!H21 -> 20848 | S9: =DRE!I21 -> -461 | T9: =DRE!J21 -> -47551 | V9: Preço no mercado | W9: =W4 -> 734524 | X9: =AG8*$Y$38 -> 986928 | Y9: =$AG$9*$Y$38 -> 1331502 | Z9: =$AG$10*$Z$38 -> 1545620 | AA9: =$AG$11*$AA$38 -> 723180 | AB9: =$AG$12*$AB$38 -> 894682 | AC9: =$AG$13*$AC$38 -> 196672 | AD9: =$AG$14*$AD$38 -> 273058 | AF9: 2022 | AG9: 9.39
B10: Liquidez Corrente | C10: =C11/C12 -> 1.9744149 | D10: =D11/D12 -> 1.8483367 | E10: =E11/E12 -> 1.9343768 | F10: =F11/F12 -> 1.6102177 | G10: =G11/G12 -> 1.6129443 | H10: =H11/H12 -> 1.248375 | I10: =I11/I12 -> 1.2759761 | J10: =J11/J12 -> 1.2938717 | L10: Receita Líquida | M10: 3688326 | N10: =DRE!D3 -> 3926631 | O10: =DRE!E3 -> 4993235 | P10: =DRE!F3 -> 3365487 | Q10: =DRE!G3 -> 2192173 | R10: =DRE!H3 -> 1915308 | S10: =DRE!I3 -> 1890654 | T10: =T5 -> 1913608 | V10: Valor Patrimonial da Ação | W10: =W36 -> 6300.4048 | X10: =X36 -> 6462.3879 | Y10: =Y36 -> 5923.5896 | Z10: =Z36 -> 5294.9732 | AA10: =AA36 -> 3983.9704 | AB10: =AB36 -> 4431.4419 | AC10: =AC36 -> 4076.3759 | AD10: =AD36 -> 3949.5649 | AF10: 2021 | AG10: 10.9
B11: Ativo Circulante | C11: 2967747 | D11: 3575173 | E11: 3430062 | F11: 3120040 | G11: 2211237 | H11: 1471763 | I11: 1418740 | J11: 1411332 | AF11: 2020 | AG11: 5.1
B12: Passivo Circulante | C12: 1503102 | D12: 1934265 | E12: 1773213 | F12: 1937651 | G12: 1370932 | H12: 1178943 | I12: 1111886 | J12: 1090782 | M12: Ano 2024 | N12: Ano 2023 | O12: Ano 2022 | P12: Ano 2021 | Q12: Ano 2020 | R12: Ano 2019 | S12: Ano 2018 | T12: Ano 2017 | W12: Ano 2024 | X12: Ano 2023 | Y12: Ano 2022 | Z12: Ano 2021 | AA12: Ano 2020 | AB12: Ano 2019 | AC12: Ano 2018 | AD12: Ano 2017 | AF12: 2019 | AG12: 10.19
L13: Margem Operacional | M13: =M14/M15 -> 0.0084618793 | N13: =N14/N15 -> 0.063550711 | O13: =O14/O15 -> 0.061319092 | P13: =P14/P15 -> 0.059954176 | Q13: =Q14/Q15 -> 0.081676636 | R13: =R14/R15 -> 0.0064522076 | S13: =S14/S15 -> -0.026847468 | T13: =T14/T15 -> -0.022090996 | V13: Índice Dívida Líquida | W13: =W14-W15 -> 3900058 | X13: =X14-X15 -> 3990458 | Y13: =Y14-Y15 -> 3773249 | Z13: =Z14-Z15 -> 3395129 | AA13: =AA14-AA15 -> 2280473 | AB13: =AB14-AB15 -> 1484689 | AC13: =AC14-AC15 -> 1396181 | AD13: =AD14-AD15 -> 1346033 | AF13: 2018 | AG13: 2.24
L14: Lucro Operacional Líquido (Ajustado) | M14: =W19 -> 31210.169 | N14: =X19 -> 249540.19 | O14: =Y19 -> 306180.63 | P14: =Z19 -> 201775 | Q14: =AA19 -> 179049.32 | R14: =AB19 -> 12357.965 | S14: =AC19 -> -50759.272 | T14: =AD19 -> -42273.506 | V14: Dívida Bruta | W14: =BP!C36 -> 4466987 | X14: =BP!D36 -> 4581833 | Y14: =BP!E36 -> 4199825 | Z14: =BP!F36 -> 3754136 | AA14: =BP!G36 -> 2824635 | AB14: =BP!H36 -> 1945403 | AC14: =BP!I36 -> 1789529 | AD14: =BP!J36 -> 1733859 | AF14: 2017 | AG14: 3.11
C15: Ano 2024 | D15: Ano 2023 | E15: Ano 2022 | F15: Ano 2021 | G15: Ano 2020 | H15: Ano 2019 | I15: Ano 2018 | J15: Ano 2017 | L15: Receita Líquida | M15: 3688326 | N15: =DRE!D3 -> 3926631 | O15: =DRE!E3 -> 4993235 | P15: =DRE!F3 -> 3365487 | Q15: =DRE!G3 -> 2192173 | R15: =DRE!H3 -> 1915308 | S15: =DRE!I3 -> 1890654 | T15: =T10 -> 1913608 | V15: Disponibilidades | W15: =BP!C7+BP!C8 -> 566929 | X15: =BP!D7+BP!D8 -> 591375 | Y15: =BP!E7+BP!E8 -> 426576 | Z15: =BP!F7+BP!F8 -> 359007 | AA15: =BP!G7+BP!G8 -> 544162 | AB15: =BP!H7+BP!H8 -> 460714 | AC15: =BP!I7+BP!I8 -> 393348 | AD15: =BP!J7+BP!J8 -> 387826
B16: Liquidez Seca | C16: =(C17-C18-C19)/C20 -> 1.2450925 | D16: =(D17-D18-D19)/D20 -> 1.1987447 | E16: =(E17-E18-E19)/E20 -> 1.1500812 | F16: =(F17-F18-F19)/F20 -> 0.73784856 | G16: =(G17-G18-G19)/G20 -> 1.1419144 | H16: =(H17-H18-H19)/H20 -> 0.82899767 | I16: =(I17-I18-I19)/I20 -> 0.79505813 | J16: =(J17-J18-J19)/J20 -> 0.82949022
B17: Ativo Circulante | C17: 2967747 | D17: =D4 -> 3575173 | E17: =BP!E6 -> 3430062 | F17: =BP!F6 -> 3120040 | G17: =BP!G6 -> 2211237 | H17: =BP!H6 -> 1471763 | I17: =BP!I6 -> 1418740 | J17: =J11 -> 1411332 | M17: Ano 2024 | N17: Ano 2023 | O17: Ano 2022 | P17: Ano 2021 | Q17: Ano 2020 | R17: Ano 2019 | S17: Ano 2018 | T17: Ano 2017
B18: Estoques | C18: 1096246 | D18: 1256483 | E18: 1390723 | F18: 1690347 | G18: 645750 | H18: 494422 | I18: 534726 | J18: 506539 | L18: Retorno sobre PL | M18: =M19/M20 -> 0.051659629 | N18: =N19/N20 -> 0.15715219 | O18: =O19/O20 -> 0.21784302 | P18: =P19/P20 -> 0.17170407 | Q18: =Q19/Q20 -> 0.18956035 | R18: =R19/R20 -> 0.038975947 | S18: =S19/S20 -> -0.00090408466 | T18: =T19/T20 -> -0.093904715 | W18: Ano 2024 | X18: Ano 2023 | Y18: Ano 2022 | Z18: Ano 2021 | AA18: Ano 2020 | AB18: Ano 2019 | AC18: Ano 2018 | AD18: Ano 2017
B19: Despesas Antecipadas | C19: 0 | D19: 0 | E19: 0 | F19: 0 | G19: 0 | H19: 0 | I19: 0 | J19: 0 | L19: Lucro Líquido | M19: 85038 | N19: =DRE!D21 -> 250882 | O19: =DRE!E21 -> 306357 | P19: =DRE!F21 -> 202896 | Q19: =DRE!G21 -> 195842 | R19: =DRE!H21 -> 20848 | S19: =DRE!I21 -> -461 | T19: =T9 -> -47551 | V19: Lucro Operacional Líquido (Ajustado) | W19: =W20-(W21*W22) -> 31210.169 | X19: =X20-(X21*X22) -> 249540.19 | Y19: =Y20-(Y21*Y22) -> 306180.63 | Z19: =Z20-(Z21*Z22) -> 201775 | AA19: =AA20-(AA21*AA22) -> 179049.32 | AB19: =AB20-(AB21*AB22) -> 12357.965 | AC19: =AC20-(AC21*AC22) -> -50759.272 | AD19: =AD20-(AD21*AD22) -> -42273.506
B20: Passivo Circulante | C20: 1503102 | D20: =D6 -> 1934265 | E20: =BP!E37 -> 1773213 | F20: =BP!F37 -> 1937651 | G20: =BP!G37 -> 1370932 | H20: =BP!H37 -> 1178943 | I20: =BP!I37 -> 1111886 | J20: =J12 -> 1090782 | L20: Patrimônio Líquido | M20: 1646121 | N20: =BP!D68 -> 1596427 | O20: =BP!E68 -> 1406320 | P20: =BP!F68 -> 1181661 | Q20: =BP!G68 -> 1033138 | R20: =BP!H68 -> 534894 | S20: =BP!I68 -> 509908 | T20: =BP!J68 -> 506375 | V20: Lucro Líquido | W20: =DRE!C21 -> 85038 | X20: =DRE!D21 -> 250882 | Y20: =DRE!E21 -> 306357 | Z20: =DRE!F21 -> 202896 | AA20: =DRE!G21 -> 195842 | AB20: =DRE!H21 -> 20848 | AC20: =DRE!I21 -> -461 | AD20: =DRE!J21 -> -47551
V21: Despesa Financeira | W21: =DRE!C17 -> -321544 | X21: =-DRE!D17 -> -104320 | Y21: =-DRE!E17 -> -86350 | Z21: =-DRE!F17 -> -43706 | AA21: =-DRE!G17 -> -59756 | AB21: =-DRE!H17 -> -32306 | AC21: =-DRE!I17 -> -48130 | AD21: =-DRE!J17 -> -65135
M22: Ano 2024 | N22: Ano 2023 | O22: Ano 2022 | P22: Ano 2021 | Q22: Ano 2020 | R22: Ano 2019 | S22: Ano 2018 | T22: Ano 2017 | V22: Líquidas do Imposto de Renda | W22: =W25 -> -0.16740425 | X22: =X25 -> -0.012862432 | Y22: =Y25 -> -0.0020424517 | Z22: =Z25 -> -0.02564866 | AA22: =AA25 -> -0.28102089 | AB22: =AB25 -> -0.26280057 | AC22: =AC25 -> -1.0450503 | AD22: =AD25 -> 0.081023939
C23: Ano 2024 | D23: Ano 2023 | E23: Ano 2022 | F23: Ano 2021 | G23: Ano 2020 | H23: Ano 2019 | I23: Ano 2018 | J23: Ano 2017 | L23: ROA - Return on Asset (Retorno sobre o Ativo) | M23: =M24/M25 -> 0.019036993 | N23: =N24/N25 -> 0.054755815 | O23: =O24/O25 -> 0.072945182 | P23: =P24/P25 -> 0.054045991 | Q23: =Q24/Q25 -> 0.06933356 | R23: =R24/R25 -> 0.010716546 | S23: =S24/S25 -> -0.00025760968 | T23: =T24/T25 -> -0.027424952
B24: Liquidez Imediata | C24: =C25/C26 -> 0.37717267 | D24: =D25/D26 -> 0.30573629 | E24: =E25/E26 -> 0.2405667 | F24: =F25/F26 -> 0.1852795 | G24: =G25/G26 -> 0.39692851 | H24: =H25/H26 -> 0.39078564 | I24: =I25/I26 -> 0.35376648 | J24: =J25/J26 -> 0.35554859 | L24: Lucro Líquido | M24: 85038 | N24: =DRE!D21 -> 250882 | O24: =DRE!E21 -> 306357 | P24: =DRE!F21 -> 202896 | Q24: =DRE!G21 -> 195842 | R24: =DRE!H21 -> 20848 | S24: =DRE!I21 -> -461 | T24: =T19 -> -47551 | W24: Ano 2024 | X24: Ano 2023 | Y24: Ano 2022 | Z24: Ano 2021 | AA24: Ano 2020 | AB24: Ano 2019 | AC24: Ano 2018 | AD24: Ano 2017
B25: Disponivel | C25: 566929 | D25: 591375 | E25: 426576 | F25: 359007 | G25: 544162 | H25: 460714 | I25: 393348 | J25: 387826 | L25: Ativo Total | M25: 4466987 | N25: =BP!D5 -> 4581833 | O25: =BP!E5 -> 4199825 | P25: =BP!F5 -> 3754136 | Q25: =BP!G5 -> 2824635 | R25: =BP!H5 -> 1945403 | S25: =BP!I5 -> 1789529 | T25: =BP!J5 -> 1733859 | V25: IMPOSTO | W25: =W26/W27 -> -0.16740425 | X25: =X26/X27 -> -0.012862432 | Y25: =Y26/Y27 -> -0.0020424517 | Z25: =Z26/Z27 -> -0.02564866 | AA25: =AA26/AA27 -> -0.28102089 | AB25: =AB26/AB27 -> -0.26280057 | AC25: =AC26/AC27 -> -1.0450503 | AD25: =AD26/AD27 -> 0.081023939
B26: Passivo Circulante | C26: 1503102 | D26: =D12 -> 1934265 | E26: =BP!E37 -> 1773213 | F26: =BP!F37 -> 1937651 | G26: =BP!G37 -> 1370932 | H26: =BP!H37 -> 1178943 | I26: =BP!I37 -> 1111886 | J26: =BP!J37 -> 1090782 | V26: Impostos Federais do Período (Imposto de Renda e Contribuição Social sobre o Lucro) | W26: =DRE!C19 -> -17098 | X26: =DRE!D19 -> -3269 | Y26: =DRE!E19 -> -627 | Z26: =DRE!F19 -> -5341 | AA26: =DRE!G19 -> -76547 | AB26: =DRE!H19 -> -7432 | AC26: =DRE!I19 -> -10694 | AD26: =DRE!J19 -> -3564
M27: Ano 2024 | N27: Ano 2023 | O27: Ano 2022 | P27: Ano 2021 | Q27: Ano 2020 | R27: Ano 2019 | S27: Ano 2018 | T27: Ano 2017 | V27: LAIR (Resultado antes dos Tributos sobre o Lucro) | W27: =DRE!C18 -> 102136 | X27: =DRE!D18 -> 254151 | Y27: =DRE!E18 -> 306984 | Z27: =DRE!F18 -> 208237 | AA27: =DRE!G18 -> 272389 | AB27: =DRE!H18 -> 28280 | AC27: =DRE!I18 -> 10233 | AD27: =DRE!J18 -> -43987
L28: Grau de Alavancagem Financeira - GAF | M28: =(M29/M30)/(M31/M32) -> 2.1233532 | N28: =(N29/N30)/(N31/N32) -> 0.87268899 | O28: =(O29/O30)/(O31/O32) -> 1.0899848 | P28: =(P29/P30)/(P31/P32) -> 0.76638348 | Q28: =(Q29/Q30)/(Q31/Q32) -> 0.8077218 | R28: =(R29/R30)/(R31/R32) -> 2.2459772 | S28: =(S29/S30)/(S31/S32) -> 0.010869031 | T28: =(T29/T30)/(T31/T32) -> 1.3038878
C29: Ano 2024 | D29: Ano 2023 | E29: Ano 2022 | F29: Ano 2021 | G29: Ano 2020 | H29: Ano 2019 | I29: Ano 2018 | J29: Ano 2017 | L29: Lucro Líquido | M29: 85038 | N29: =DRE!D21 -> 250882 | O29: =DRE!E21 -> 306357 | P29: =DRE!F21 -> 202896 | Q29: =DRE!G21 -> 195842 | R29: =DRE!H21 -> 20848 | S29: =DRE!I21 -> -461 | T29: =T24 -> -47551 | W29: Ano 2024 | X29: Ano 2023 | Y29: Ano 2022 | Z29: Ano 2021 | AA29: Ano 2020 | AB29: Ano 2019 | AC29: Ano 2018 | AD29: Ano 2017
B30: Endividamento | C30: =(C31/C32) -> 2.7136444 | D30: =(D31/D32) -> 2.8700548 | E30: =(E31/E32) -> 2.9863936 | F30: =(F31/F32) -> 3.1769992 | G30: =(G31/G32) -> 2.7340346 | H30: =(H31/H32) -> 3.6369879 | I30: =(I31/I32) -> 3.5095135 | J30: =J31/J32 -> 3.4240612 | L30: Patrimônio Líquido | M30: 1646121 | N30: =BP!D68 -> 1596427 | O30: =BP!E68 -> 1406320 | P30: =BP!F68 -> 1181661 | Q30: =BP!G68 -> 1033138 | R30: =BP!H68 -> 534894 | S30: =BP!I68 -> 509908 | T30: =T20 -> 506375 | V30: Investimentos | W30: =W31-W32 -> 1282824 | X30: =X31-X32 -> 1385733 | Y30: =Y31-Y32 -> 1531985 | Z30: =Z31-Z32 -> 900602 | AA30: =AA31-AA32 -> 762934 | AB30: =AB31-AB32 -> 712124 | AC30: =AC31-AC32 -> 610235 | AD30: =AD31-AD32 -> 586977
B31: Capital de Terceiros | C31: 4466987 | D31: 4581833 | E31: =BP!E36 -> 4199825 | F31: =BP!F36 -> 3754136 | G31: =BP!G36 -> 2824635 | H31: =BP!H36 -> 1945403 | I31: =BP!I36 -> 1789529 | J31: =BP!J36 -> 1733859 | L31: Lucro Operacional Líquido (Ajustado) | M31: =W19 -> 31210.169 | N31: =X19 -> 249540.19 | O31: =Y19 -> 306180.63 | P31: =Z19 -> 201775 | Q31: =AA19 -> 179049.32 | R31: =AB19 -> 12357.965 | S31: =AC19 -> -50759.272 | T31: =T14 -> -42273.506 | V31: Ativo Total | W31: 4466987 | X31: =BP!D5 -> 4581833 | Y31: =BP!E5 -> 4199825 | Z31: =BP!F5 -> 3754136 | AA31: =BP!G5 -> 2824635 | AB31: =BP!H5 -> 1945403 | AC31: =BP!I5 -> 1789529 | AD31: =BP!I5 -> 1789529
B32: Patrimônio Líquido | C32: 1646121 | D32: 1596427 | E32: =BP!E68 -> 1406320 | F32: =BP!F68 -> 1181661 | G32: =BP!G68 -> 1033138 | H32: =BP!H68 -> 534894 | I32: =BP!I68 -> 509908 | J32: =BP!J68 -> 506375 | L32: Investimento | M32: =W30 -> 1282824 | N32: =X30 -> 1385733 | O32: =Y30 -> 1531985 | P32: =Z30 -> 900602 | Q32: =AA30 -> 762934 | R32: =AB30 -> 712124 | S32: =AC30 -> 610235 | T32: =AD30 -> 586977 | V32: Passivos não Financeiro (ou seja, menos todos os passivos exceto Empréstimos e Financiamentos) | W32: =BP!C36-BP!C46-BP!C56 -> 3184163 | X32: =BP!D36-BP!D46-BP!D56 -> 3196100 | Y32: =BP!E36-BP!E46-BP!E56 -> 2667840 | Z32: =BP!F36-BP!F46-BP!F56 -> 2853534 | AA32: =BP!G36-BP!G46-BP!G56 -> 2061701 | AB32: =BP!H36-BP!H46-BP!H56 -> 1233279 | AC32: =BP!I36-BP!I46-BP!I56 -> 1179294 | AD32: =BP!J36-BP!J46-BP!J56 -> 1202552
C34: Ano 2024 | D34: Ano 2023 | E34: Ano 2022 | F34: Ano 2021 | G34: Ano 2020 | H34: Ano 2019 | I34: Ano 2018 | J34: Ano 2017 | M34: Ano 2024 | N34: Ano 2023 | O34: Ano 2022 | P34: Ano 2021 | Q34: Ano 2020 | R34: Ano 2019 | S34: Ano 2018 | T34: Ano 2017
B35: Composição do Endividamento | C35: =C36/C37 -> 0.33649124 | D35: =D36/D37 -> 0.42215965 | E35: =E36/E37 -> 0.42221116 | F35: =F36/F37 -> 0.51613767 | G35: =G36/G37 -> 0.48534837 | H35: =H36/H37 -> 0.60601479 | I35: =I36/I37 -> 0.62132885 | J35: =J36/J37 -> 0.62910652 | L35: EBITDA | M35: =M36 -> 102136 | N35: =N36 -> 254151 | O35: =O36 -> 306984 | P35: =P36 -> 208237 | Q35: =Q36 -> 272389 | R35: =R36 -> 28280 | S35: =S36 -> 10233 | T35: =T36 -> -43987 | W35: Ano 2024 | X35: Ano 2023 | Y35: Ano 2022 | Z35: Ano 2021 | AA35: Ano 2020 | AB35: Ano 2019 | AC35: Ano 2018 | AD35: Ano 2017
B36: Passivo Circulante | C36: 1503102 | D36: 1934265 | E36: 1773213 | F36: 1937651 | G36: 1370932 | H36: 1178943 | I36: 1111886 | J36: 1090782 | L36: Resultado antes dos Juros, Impostos e Depreciação, Amortização e Exaustão | M36: 102136 | N36: =DRE!D18 -> 254151 | O36: =DRE!E18 -> 306984 | P36: =DRE!F18 -> 208237 | Q36: =DRE!G18 -> 272389 | R36: =DRE!H18 -> 28280 | S36: =DRE!I18 -> 10233 | T36: =DRE!J18 -> -43987 | V36: Valor Patrimonial da Ação | W36: =W37/W38 -> 6300.4048 | X36: =X37/X38 -> 6462.3879 | Y36: =Y37/Y38 -> 5923.5896 | Z36: =Z37/Z38 -> 5294.9732 | AA36: =AA37/AA38 -> 3983.9704 | AB36: =AB37/AB38 -> 4431.4419 | AC36: =AC37/AC38 -> 4076.3759 | AD36: =AD37/AD38 -> 3949.5649
B37: Capitais de Terceiros | C37: 4466987 | D37: 4581833 | E37: 4199825 | F37: 3754136 | G37: 2824635 | H37: 1945403 | I37: 1789529 | J37: 1733859 | V37: Valor Contábil da Empresa | W37: =(BP!C5+BP!C36)*100 -> 893397400 | X37: =(BP!D5+BP!D36)*100 -> 916366600 | Y37: =(BP!E5+BP!E36)*100 -> 839965000 | Z37: =(BP!F5+BP!F36)*100 -> 750827200 | AA37: =(BP!G5+BP!G36)*100 -> 564927000 | AB37: =(BP!H5+BP!H36)*100 -> 389080600 | AC37: =(BP!I5+BP!I36)*100 -> 357905800 | AD37: =(BP!J5+BP!J36)*100 -> 346771800
M38: Ano 2024 | N38: Ano 2023 | O38: Ano 2022 | P38: Ano 2021 | Q38: Ano 2020 | R38: Ano 2019 | S38: Ano 2018 | T38: Ano 2017 | V38: Nº total de ações em circulação | W38: 141800 | X38: 141800 | Y38: 141800 | Z38: 141800 | AA38: 141800 | AB38: 87800 | AC38: 87800 | AD38: 87800
C39: Ano 2024 | D39: Ano 2023 | E39: Ano 2022 | F39: Ano 2021 | G39: Ano 2020 | H39: Ano 2019 | I39: Ano 2018 | J39: Ano 2017 | L39: Margem EBITDA | M39: =M40/M41 -> 0.027691695 | N39: =N40/N41 -> 0.064724951 | O39: =O40/O41 -> 0.061479982 | P39: =P40/P41 -> 0.061874255 | Q39: =Q40/Q41 -> 0.12425525 | R39: =R40/R41 -> 0.014765249 | S39: =S40/S41 -> 0.0054124128 | T39: =T40/T41 -> -0.022986421
B40: Imobilização do Patrimônio Líquido | C40: =(C41-C42)/C43 -> 0.44555534 | D40: =(D41-D42)/D43 -> 0.3159017 | E40: =(E41-E42)/E43 -> 0.27439772 | F40: =(F41-F42)/F43 -> 0.2488988 | G40: =(G41-G42)/G43 -> 0.26696627 | H40: =(H41-H42)/H43 -> 0.49970461 | I40: =(I41-I42)/I43 -> 0.3495709 | J40: =(J41-J42)/J43 -> 0.34137941 | L40: EBITIDA | M40: =M35 -> 102136 | N40: =N35 -> 254151 | O40: =O35 -> 306984 | P40: =P35 -> 208237 | Q40: =Q35 -> 272389 | R40: =R35 -> 28280 | S40: =S35 -> 10233 | T40: =T35 -> -43987
B41: Ativo Não Circulante | C41: 1499240 | D41: 1006660 | E41: 769763 | F41: 634096 | G41: 613398 | H41: 473640 | I41: 370789 | J41: 322527 | L41: Receitas Líquidas | M41: 3688326 | N41: =DRE!D3 -> 3926631 | O41: =DRE!E3 -> 4993235 | P41: =DRE!F3 -> 3365487 | Q41: =DRE!G3 -> 2192173 | R41: =DRE!H3 -> 1915308 | S41: =DRE!I3 -> 1890654 | T41: =DRE!J3 -> 1913608
B42: Ativo Realizável a Longo Prazo | C42: 765802 | D42: 502346 | E42: 383872 | F42: 339982 | G42: 337585 | H42: 206351 | I42: 192540 | J42: 149661
B43: Patrimônio Líquido | C43: 1646121 | D43: 1596427 | E43: 1406320 | F43: 1181661 | G43: 1033138 | H43: 534894 | I43: 509908 | J43: 506375 | M43: Ano 2024 | N43: Ano 2023 | O43: Ano 2022 | P43: Ano 2021 | Q43: Ano 2020 | R43: Ano 2019 | S43: Ano 2018 | T43: Ano 2017
L44: Retorno sobre Investimento | M44: =M45/M46 -> 0.024329268 | N44: =N45/N46 -> 0.18007812 | O44: =O45/O46 -> 0.19985877 | P44: =P45/P46 -> 0.22404458 | Q44: =Q45/Q46 -> 0.2346852 | R44: =R45/R46 -> 0.01735367 | S44: =S45/S46 -> -0.083179877 | T44: =T45/T46 -> -0.072019016
C45: Ano 2024 | D45: Ano 2023 | E45: Ano 2022 | F45: Ano 2021 | G45: Ano 2020 | H45: Ano 2019 | I45: Ano 2018 | J45: Ano 2017 | L45: Lucro Operacional Líquido (ajustado) | M45: =W19 -> 31210.169 | N45: =X19 -> 249540.19 | O45: =Y19 -> 306180.63 | P45: =Z19 -> 201775 | Q45: =AA19 -> 179049.32 | R45: =AB19 -> 12357.965 | S45: =AC19 -> -50759.272 | T45: =T31 -> -42273.506
B46: Imobilização dos Recursos Não Correntes | C46: =(C47-C48)/(C49+C50) -> 0.24745832 | D46: =(D47-D48)/(D49+D50) -> 0.19048198 | E46: =(E47-E48)/(E49+E50) -> 0.1590246 | F46: =(F47-F48)/(F49+F50) -> 0.16191381 | G46: =(G47-G48)/(G49+G50) -> 0.18973133 | H46: =(H47-H48)/(H49+H50) -> 0.34873092 | I46: =(I47-I48)/(I49+I50) -> 0.26304263 | J46: =(J47-J48)/(J49+J50) -> 0.26881073 | L46: Investimento | M46: =W30 -> 1282824 | N46: =X30 -> 1385733 | O46: =Y30 -> 1531985 | P46: =Z30 -> 900602 | Q46: =AA30 -> 762934 | R46: =AB30 -> 712124 | S46: =AC30 -> 610235 | T46: =AD30 -> 586977
B47: Ativo Não Circulante | C47: 1499240 | D47: =D41 -> 1006660 | E47: =BP!E19 -> 769763 | F47: =BP!F19 -> 634096 | G47: =BP!G19 -> 613398 | H47: =BP!H19 -> 473640 | I47: =BP!I19 -> 370789 | J47: =BP!J19 -> 322527
B48: Ativo Realizável a Longo Prazo | C48: 765802 | D48: =D42 -> 502346 | E48: =BP!E20 -> 383872 | F48: =BP!F20 -> 339982 | G48: =BP!G20 -> 337585 | H48: =BP!H20 -> 206351 | I48: =BP!I20 -> 192540 | J48: =BP!J20 -> 149661 | M48: Ano 2024 | N48: Ano 2023 | O48: Ano 2022 | P48: Ano 2021 | Q48: Ano 2020 | R48: Ano 2019 | S48: Ano 2018 | T48: Ano 2017
B49: Patrimônio Líquido | C49: 1646121 | D49: =D43 -> 1596427 | E49: =BP!E68 -> 1406320 | F49: =BP!F68 -> 1181661 | G49: =BP!G68 -> 1033138 | H49: =BP!H68 -> 534894 | I49: =BP!I68 -> 509908 | J49: =J32 -> 506375 | L49: Giro do Ativo | M49: =M50/M51 -> 2.8751614 | N49: =N50/N51 -> 2.833613 | O49: =O50/O51 -> 3.2593237 | P49: =P50/P51 -> 3.7369304 | Q49: =Q50/Q51 -> 2.8733455 | R49: =R50/R51 -> 2.6895709 | S49: =S50/S51 -> 3.0982392 | T49: =T50/T51 -> 3.2601073
B50: Passivo Não Circulante | C50: 1317764 | D50: 1051141 | E50: 1020292 | F50: 634824 | G50: 420565 | H50: 231568 | I50: 167735 | J50: 136702 | L50: Receita Líquida | M50: 3688326 | N50: =DRE!D3 -> 3926631 | O50: =DRE!E3 -> 4993235 | P50: =DRE!F3 -> 3365487 | Q50: =DRE!G3 -> 2192173 | R50: =DRE!H3 -> 1915308 | S50: =DRE!I3 -> 1890654 | T50: =T41 -> 1913608
L51: Investimento | M51: =M46 -> 1282824 | N51: =X30 -> 1385733 | O51: =Y30 -> 1531985 | P51: =Z30 -> 900602 | Q51: =AA30 -> 762934 | R51: =AB30 -> 712124 | S51: =AC30 -> 610235 | T51: =AD30 -> 586977
C53: Ano 2024 | D53: Ano 2023 | E53: Ano 2022 | F53: Ano 2021 | G53: Ano 2020 | H53: Ano 2019 | I53: Ano 2018 | J53: Ano 2017
B54: PMRE (365 dias) | C54: =(C55/C56)*C57 -> 144.74962 | D54: =(D55/D56)*D57 -> 160.12569 | E54: =(E55/E56)*E57 -> 133.70653 | F54: =(F55/F56)*F57 -> 237.58372 | G54: =(G55/G56)*G57 -> 135.19278 | H54: =(H55/H56)*H57 -> 125.74138 | I54: =(I55/I56)*I57 -> 135.82597 | J54: =(J55/J56)*J57 -> 130.17818 | M54: Ano 2024 | N54: Ano 2023 | O54: Ano 2022 | P54: Ano 2021 | Q54: Ano 2020 | R54: Ano 2019 | S54: Ano 2018 | T54: Ano 2017
B55: Estoque | C55: 1096246 | D55: =D18 -> 1256483 | E55: =BP!E10 -> 1390723 | F55: =BP!F10 -> 1690347 | G55: =BP!G10 -> 645750 | H55: =BP!H10 -> 494422 | I55: =BP!I10 -> 534726 | J55: =BP!J10 -> 506539 | L55: Ciclo Operacional (365 dias) | M55: =M56+M57 -> 229.94871 | N55: =N56+N57 -> 283.41748 | O55: =O56+O57 -> 216.48979 | P55: =P56+P57 -> 320.29333 | Q55: =Q56+Q57 -> 251.41813 | R55: =R56+R57 -> 175.03075 | S55: =S56+S57 -> 181.24831 | T55: =T56+T57 -> 182.86911
B56: Custo das Mercadorias Vendas | C56: 2764289 | D56: 2864102 | E56: 3796478 | F56: 2596881 | G56: 1743427 | H56: 1435200 | I56: 1436949 | J56: 1420259 | L56: PMRE | M56: =C54 -> 144.74962 | N56: =D54 -> 160.12569 | O56: =E54 -> 133.70653 | P56: =F54 -> 237.58372 | Q56: =G54 -> 135.19278 | R56: =H54 -> 125.74138 | S56: =I54 -> 135.82597 | T56: =J54 -> 130.17818
B57: Dias | C57: 365 | D57: 365 | E57: 365 | F57: 365 | G57: 365 | H57: 365 | I57: 365 | J57: =I57 -> 365 | L57: PMRV | M57: =C60 -> 85.199086 | N57: =D60 -> 123.2918 | O57: =E60 -> 82.783265 | P57: =F60 -> 82.709612 | Q57: =G60 -> 116.22534 | R57: =H60 -> 49.289373 | S57: =I60 -> 45.422341 | T57: =J60 -> 52.690933
C59: Ano 2024 | D59: Ano 2023 | E59: Ano 2022 | F59: Ano 2021 | G59: Ano 2020 | H59: Ano 2019 | I59: Ano 2018 | J59: Ano 2017 | M59: Ano 2024 | N59: Ano 2023 | O59: Ano 2022 | P59: Ano 2021 | Q59: Ano 2020 | R59: Ano 2019 | S59: Ano 2018 | T59: Ano 2017
B60: PMRV (365 dias) | C60: =(C61/C62)*C63 -> 85.199086 | D60: =(D61/D62)*D63 -> 123.2918 | E60: =(E61/E62)*E63 -> 82.783265 | F60: =(F61/F62)*F63 -> 82.709612 | G60: =(G61/G62)*G63 -> 116.22534 | H60: =(H61/H62)*H63 -> 49.289373 | I60: =(I61/I62)*I63 -> 45.422341 | J60: =(J61/J62)*J63 -> 52.690933 | L60: Ciclo de Caixa (365 dias) | M60: =M61-M62 -> 137.96359 | N60: =N61-N62 -> 171.57219 | O60: =O61-O62 -> 155.06197 | P60: =P61-P62 -> 201.9454 | Q60: =Q61-Q62 -> 145.32322 | R60: =R61-R62 -> 75.806329 | S60: =S61-S62 -> 71.939234 | T60: =T61-T62 -> 63.620177
B61: Duplicatas a Receber | C61: 860937 | D61: 1326360 | E61: 1132483 | F61: 762625 | G61: 698044 | H61: 258642 | I61: 235282 | J61: 276246 | L61: Ciclo Operacional | M61: =M55 -> 229.94871 | N61: =N55 -> 283.41748 | O61: =O55 -> 216.48979 | P61: =P55 -> 320.29333 | Q61: =Q55 -> 251.41813 | R61: =R55 -> 175.03075 | S61: =S55 -> 181.24831 | T61: =T55 -> 182.86911
B62: Vendas | C62: 3688326 | D62: 3926631 | E62: 4993235 | F62: 3365487 | G62: 2192173 | H62: 1915308 | I62: 1890654 | J62: 1913608 | L62: PMPF | M62: =C66 -> 91.985116 | N62: =D66 -> 111.84529 | O62: =E66 -> 61.427821 | P62: =F66 -> 118.34794 | Q62: =G66 -> 106.09491 | R62: =H66 -> 99.224425 | S62: =I66 -> 109.30908 | T62: =J66 -> 119.24894
B63: Dias | C63: 365 | D63: 365 | E63: 365 | F63: 365 | G63: 365 | H63: 365 | I63: 365 | J63: =I63 -> 365
M64: Ano 2024 | N64: Ano 2023 | O64: Ano 2022 | P64: Ano 2021 | Q64: Ano 2020 | R64: Ano 2019 | S64: Ano 2018 | T64: Ano 2017
C65: Ano 2024 | D65: Ano 2023 | E65: Ano 2022 | F65: Ano 2021 | G65: Ano 2020 | H65: Ano 2019 | I65: Ano 2018 | J65: Ano 2017 | L65: Ciclo Operacional (360 dias) | M65: =M66+M67 -> 226.79873 | N65: =N66+N67 -> 279.53505 | O65: =O66+O67 -> 213.52418 | P65: =P66+P67 -> 315.90575 | Q65: =Q66+Q67 -> 247.97404 | R65: =R66+R67 -> 172.63307 | S65: =S66+S67 -> 178.76546 | T65: =T66+T67 -> 180.36406
B66: PMPF (365 dias) | C66: =(C67/C68)*C69 -> 91.985116 | D66: =(D67/D68)*D69 -> 111.84529 | E66: =(E67/E68)*E69 -> 61.427821 | F66: =(F67/F68)*F69 -> 118.34794 | G66: =(G67/G68)*G69 -> 106.09491 | H66: =(H67/H68)*H69 -> 99.224425 | I66: =(I67/I68)*I69 -> 109.30908 | J66: =(J67/J68)*J69 -> 119.24894 | L66: PMRE | M66: =C73 -> 142.76675 | N66: =D73 -> 157.93218 | O66: =E73 -> 131.87493 | P66: =F73 -> 234.32915 | Q66: =G73 -> 133.34083 | R66: =H73 -> 124.0189 | S66: =I73 -> 133.96534 | T66: =J73 -> 128.39492
B67: Fornecedores | C67: 658247 | D67: 832121 | E67: 594245 | F67: 1186214 | G67: 562210 | H67: 383964 | I67: 449260 | J67: 486141 | L67: PMRV | M67: =C79 -> 84.031975 | N67: =D79 -> 121.60287 | O67: =E79 -> 81.649247 | P67: =F79 -> 81.576604 | Q67: =G79 -> 114.63322 | R67: =H79 -> 48.614176 | S67: =I79 -> 44.800117 | T67: =J79 -> 51.969139
B68: Compras | C68: =-(DRE!C4+DFC!C22) -> 2611946 | D68: =-(DRE!D$4+DFC!D$22) -> 2715574 | E68: =-(DRE!E$4+DFC!E$22) -> 3530964 | F68: =-(DRE!F$4+DFC!F$22) -> 3658434 | G68: =-(DRE!G$4+DFC!G$22) -> 1934180 | H68: =-(DRE!H$4+DFC!H$22) -> 1412423 | I68: =-(DRE!I$4+DFC!I$22) -> 1500149 | J68: =(-DRE!J4+(-DFC!J22)) -> 1487992
B69: Dias | C69: 365 | D69: 365 | E69: 365 | F69: 365 | G69: 365 | H69: 365 | I69: 365 | J69: =I69 -> 365 | M69: Ano 2024 | N69: Ano 2023 | O69: Ano 2022 | P69: Ano 2021 | Q69: Ano 2020 | R69: Ano 2019 | S69: Ano 2018 | T69: Ano 2017
L70: Ciclo de Caixa (360 dias) | M70: =M71-M72 -> 136.07368 | N70: =N71-N72 -> 169.22189 | O70: =O71-O72 -> 152.93784 | P70: =P71-P72 -> 199.17902 | Q70: =Q71-Q72 -> 143.33249 | R70: =R71-R72 -> 74.767886 | S70: =S71-S72 -> 70.953765 | T70: =T71-T72 -> 62.748668
L71: Ciclo Operacional | M71: =M65 -> 226.79873 | N71: =N65 -> 279.53505 | O71: =O65 -> 213.52418 | P71: =P65 -> 315.90575 | Q71: =Q65 -> 247.97404 | R71: =R65 -> 172.63307 | S71: =S65 -> 178.76546 | T71: =T65 -> 180.36406
C72: Ano 2024 | D72: Ano 2023 | E72: Ano 2022 | F72: Ano 2021 | G72: Ano 2020 | H72: Ano 2019 | I72: Ano 2018 | J72: Ano 2017 | L72: PMPF | M72: =C85 -> 90.725046 | N72: =D85 -> 110.31316 | O72: =E85 -> 60.586344 | P72: =F85 -> 116.72673 | Q72: =G85 -> 104.64155 | R72: =H85 -> 97.865186 | S72: =I85 -> 107.81169 | T72: =J85 -> 117.61539
B73: PMRE (360 dias) | C73: =(C74/C75)*C76 -> 142.76675 | D73: =(D74/D75)*D76 -> 157.93218 | E73: =(E74/E75)*E76 -> 131.87493 | F73: =(F74/F75)*F76 -> 234.32915 | G73: =(G74/G75)*G76 -> 133.34083 | H73: =(H74/H75)*H76 -> 124.0189 | I73: =(I74/I75)*I76 -> 133.96534 | J73: =(J74/J75)*J76 -> 128.39492
B74: Estoque | C74: 1096246 | D74: =BP!D10 -> 1256483 | E74: =BP!E10 -> 1390723 | F74: =BP!F10 -> 1690347 | G74: =BP!G10 -> 645750 | H74: =BP!H10 -> 494422 | I74: =BP!I10 -> 534726 | J74: =BP!J10 -> 506539
B75: Custo das Mercadorias Vendas | C75: 2764289 | D75: =D56 -> 2864102 | E75: =-DRE!E4 -> 3796478 | F75: =-DRE!F4 -> 2596881 | G75: =-DRE!G4 -> 1743427 | H75: =-DRE!H4 -> 1435200 | I75: =-DRE!I4 -> 1436949 | J75: =-DRE!J4 -> 1420259
B76: Dias | C76: 360 | D76: 360 | E76: 360 | F76: 360 | G76: 360 | H76: 360 | I76: 360 | J76: =I76 -> 360
C78: Ano 2024 | D78: Ano 2023 | E78: Ano 2022 | F78: Ano 2021 | G78: Ano 2020 | H78: Ano 2019 | I78: Ano 2018 | J78: Ano 2017
B79: PMRV (360 dias) | C79: =(C80/C81)*C82 -> 84.031975 | D79: =(D80/D81)*D82 -> 121.60287 | E79: =(E80/E81)*E82 -> 81.649247 | F79: =(F80/F81)*F82 -> 81.576604 | G79: =(G80/G81)*G82 -> 114.63322 | H79: =(H80/H81)*H82 -> 48.614176 | I79: =(I80/I81)*I82 -> 44.800117 | J79: =(J80/J81)*J82 -> 51.969139
B80: Duplicatas a Receber | C80: 860937 | D80: =BP!D9 -> 1326360 | E80: =BP!E9 -> 1132483 | F80: =BP!F9 -> 762625 | G80: =BP!G9 -> 698044 | H80: =BP!H9 -> 258642 | I80: =BP!I9 -> 235282 | J80: =J61 -> 276246
B81: Vendas | C81: 3688326 | D81: =DRE!D3 -> 3926631 | E81: =DRE!E3 -> 4993235 | F81: =DRE!F3 -> 3365487 | G81: =DRE!G3 -> 2192173 | H81: =DRE!H3 -> 1915308 | I81: =DRE!I3 -> 1890654 | J81: =J62 -> 1913608
B82: Dias | C82: 360 | D82: 360 | E82: 360 | F82: 360 | G82: 360 | H82: 360 | I82: 360 | J82: =I82 -> 360
C84: Ano 2024 | D84: Ano 2023 | E84: Ano 2022 | F84: Ano 2021 | G84: Ano 2020 | H84: Ano 2019 | I84: Ano 2018 | J84: Ano 2017
B85: PMPF (360 dias) | C85: =(C86/C87)*C88 -> 90.725046 | D85: =(D86/D87)*D88 -> 110.31316 | E85: =(E86/E87)*E88 -> 60.586344 | F85: =(F86/F87)*F88 -> 116.72673 | G85: =(G86/G87)*G88 -> 104.64155 | H85: =(H86/H87)*H88 -> 97.865186 | I85: =(I86/I87)*I88 -> 107.81169 | J85: =(J86/J87)*J88 -> 117.61539
B86: Fornecedores | C86: 658247 | D86: =D67 -> 832121 | E86: =BP!E39 -> 594245 | F86: =BP!F39 -> 1186214 | G86: =BP!G39 -> 562210 | H86: =BP!H39 -> 383964 | I86: =BP!I39 -> 449260 | J86: =J67 -> 486141
B87: Compras | C87: =C68 -> 2611946 | D87: =D68 -> 2715574 | E87: =-(DRE!E$4+DFC!E$22) -> 3530964 | F87: =-(DRE!F$4+DFC!F$22) -> 3658434 | G87: =-(DRE!G$4+DFC!G$22) -> 1934180 | H87: =-(DRE!H$4+DFC!H$22) -> 1412423 | I87: =-(DRE!I$4+DFC!I$22) -> 1500149 | J87: =J68 -> 1487992
B88: Dias | C88: =D88 -> 360 | D88: =E88 -> 360 | E88: 360 | F88: 360 | G88: 360 | H88: 360 | I88: 360 | J88: =I88 -> 360
